Workbook

Sheet Consultas
A1: Tipo | B1: PED | C1: COD WEB | D1: 2-Empresa | E1: 3-Cliente | F1: 4-Total Ped. R$ | G1: Desconto Ped | H1: 5-Faturado | I1: 6-Entrada | J1: 7-Quant. Grande? | K1: 8-Prod. Q Ñ Combinam? | L1: Armário ou Cofre > 2.000 | M1: Entrega=Cadastro | N1: UF do Cliente | O1: Google Maps 0|5|10 | P1: Registro.Br | Q1: ScamAdvizer | R1: 9-Pgtos Abertos | S1: 10-Comprou e pagou? | T1: 10-Comprou e pagou +5X? | U1: 11-Cadastro=Receita | V1: 12-CNPJ Ativo | W1: 14-Casa/Sala/Conj/Apart no end. | X1: EmailSiteReceita=@corporativo? | Y1: Existe Mail Financeiro Diferente? | Z1: 15-Mail gratuito | AA1: 16-Possui Site | AB1: 18-Fundação Matriz | AC1: 20-Grande /Conhecida/Filiais | AD1: 29-Capital Soc. (Matriz) | AE1: 25-SalvarPDFConsltRede | AF1: 24-PFIN S ou N | AG1: 23-Ch s/ Fundo | AH1: 21-Protestos S ou N | AI1: 22-Vlr Prot. (número) | AJ1: 28 - SCORE Serasa | AK1: Nome que consta na consulta REGULARIDADE DO FGTS | AL1: Situação Regular? | AM1: 33-RAZÃO E FGTS IGUAL?S/N | AN1: 34-Tem Certid Trib Mobiliar.? | AO1: 30-3 NF Conf. | AP1: 31 - Conta de Luz | AQ1: OBS | AR1: Final: Lib/Entrada/Bloqu. só AV | AS1: Data | AT1: Total Score | AU1: Risco | AV1: Sugestão | AW1: Obs: | AX1: Contratato Entrega | AY1: Perigo de Golpe | AZ1: Cadastro = Receita
A2: ='Parâmetros'!$A$19 -> Rel. Básico PJ | B2: 162 | C2: 24896 | D2: Metalpleno | E2: 034331 | F2: 11700 | G2: OK | H2: S | I2: N | J2: N | K2: N | L2: S | M2: N | N2: SC | O2: 0 | P2: N | Q2: 100 | R2: N | S2: S | T2: N | U2: S | V2: S | W2: N | X2: S | Y2: S | Z2: N | AA2: S | AB2: 34935 | AC2: N | AD2: R$ 40.740.000,00 | AE2: S | AF2: N | AG2: N | AH2: N | AI2: 0 | AJ2: 982 | AK2: FAST INDUSTRIA E COMERCIO LTDA | AL2: S | AM2: S | AN2: D | AO2: N/D | AP2: N/D | AQ2: Transportadora Faoli transportes ok | AR2: Liberado | AS2: 46127 | AT2: =Calculo!AQ2 -> 45 | AU2: =Calculo!AV2 -> SEM-RISCO | AV2: =Calculo!AW2 -> LIBERADO | AW2: =Calculo!AX2 -> SOLICITAR PED COMPRA | AX2: =Calculo!K2 -> SOLIC CONTRATO DE ENTREGA | AY2: =Calculo!AY2 -> CHECAGEM REVERSA | AZ2: =Calculo!AZ2 -> N/A
A3: ='Parâmetros'!$A$19 -> Rel. Básico PJ | B3: 166 | C3: 24879 | D3: Metalpleno | E3: 141660 | F3: 12931 | G3: OK | H3: S | I3: S | J3: N | K3: N | L3: S | M3: S | N3: RS | O3: 5 | P3: N | Q3: 100 | R3: N | S3: N | T3: N | U3: S | V3: S | W3: N | X3: S | Y3: S | Z3: N | AA3: S | AB3: 24323 | AC3: N | AD3: R$ 29.200.000,00 | AE3: S | AF3: S | AG3: N | AH3: N | AI3: 20724.06 | AJ3: 699 | AK3: FARINA SA COMPONENTES AUTOMOTIVOS | AL3: S | AM3: S | AN3: D | AO3: N/D | AP3: N/D | AR3: Liberado | AS3: 46129 | AT3: =Calculo!AQ3 -> 56 | AU3: =Calculo!AV3 -> SEM-RISCO | AV3: =Calculo!AW3 -> LIBERADO | AW3: =Calculo!AX3 -> SOLICITAR PED COMPRA | AX3: =Calculo!K3 -> SOLIC CONTRATO DE ENTREGA | AY3: =Calculo!AY3 -> N/A | AZ3: =Calculo!AZ3 -> N/A
A4: ='Parâmetros'!$A$19 -> Rel. Básico PJ | B4: 167 | C4: 25087 | D4: Metalpleno | E4: 144468 | F4: 4100 | G4: OK | H4: S | I4: S | J4: N | K4: N | L4: S | M4: S | N4: RS | O4: 5 | P4: S | Q4: 100 | R4: N | S4: N | T4: N | U4: S | V4: S | W4: S | X4: S | Y4: N | Z4: N | AA4: S | AB4: 38422 | AC4: N | AD4: R$ 50.000,00 | AE4: S | AF4: N | AG4: N | AH4: N | AI4: 0 | AJ4: 651 | AK4: NEW TECH INFORMATICA LTDA | AL4: S | AM4: S | AN4: D | AO4: N/D | AP4: N/D | AR4: Liberado | AS4: 46129 | AT4: =Calculo!AQ4 -> 45 | AU4: =Calculo!AV4 -> SEM-RISCO | AV4: =Calculo!AW4 -> LIBERADO | AW4: =Calculo!AX4 -> N/A | AX4: =Calculo!K4 -> SOLIC CONTRATO DE ENTREGA | AY4: =Calculo!AY4 -> N/A | AZ4: =Calculo!AZ4 -> N/A
A5: ='Parâmetros'!$A$19 -> Rel. Básico PJ | B5: 1864 | C5: 25085 | D5: GsiBW | E5: 021332 | F5: 1180 | G5: OK | H5: S | I5: N | J5: N | K5: N | L5: N | M5: S | N5: SP | O5: - | P5: N | Q5: 100 | R5: N | S5: S | T5: N | U5: S | V5: S | W5: N | X5: S | Y5: S | Z5: N | AA5: S | AB5: 30467 | AC5: N | AD5: R$ 42.171.656,00 | AE5: S | AF5: N | AG5: N | AH5: N | AI5: 0 | AJ5: 1000 | AK5: LEVITARE-INDUSTRIA E COMERCIO DE LATICINIOS LTDA | AL5: S | AM5: S | AN5: D | AO5: N/D | AP5: N/D | AR5: Liberado | AS5: 46134 | AT5: =Calculo!AQ5 -> 59 | AU5: =Calculo!AV5 -> SEM-RISCO | AV5: =Calculo!AW5 -> LIBERADO | AW5: =Calculo!AX5 -> N/A | AX5: =Calculo!K5 -> N/A | AY5: =Calculo!AY5 -> N/A | AZ5: =Calculo!AZ5 -> N/A
A6: ='Parâmetros'!$A$19 -> Rel. Básico PJ | B6: 442 | C6: 25081 | D6: Oaco | E6: 144469 | F6: 679 | G6: OK | H6: S | I6: N | J6: N | K6: N | L6: N | M6: S | N6: PR | O6: - | P6: N | Q6: 100 | R6: N | S6: N | T6: N | U6: S | V6: S | W6: N | X6: S | Y6: S | Z6: N | AA6: S | AB6: 42863 | AC6: S | AD6: R$ 5.000.000,00 | AE6: S | AF6: S | AG6: N | AH6: S | AI6: 520974.26 | AJ6: 826 | AK6: GF4 PARTICIPACOES LTDA | AL6: S | AM6: S | AN6: D | AO6: N/D | AP6: N/D | AQ6: Pedido cancelado | AR6: Liberado | AS6: 46134 | AT6: =Calculo!AQ6 -> 13 | AU6: =Calculo!AV6 -> SEM-RISCO | AV6: =Calculo!AW6 -> LIBERADO | AW6: =Calculo!AX6 -> N/A | AX6: =Calculo!K6 -> N/A | AY6: =Calculo!AY6 -> N/A | AZ6: =Calculo!AZ6 -> N/A
A7: ='Parâmetros'!$A$19 -> Rel. Básico PJ | B7: 444 | C7: 25091 | D7: Oaco | E7: 144471 | F7: 679 | G7: OK | H7: S | I7: N | J7: N | K7: N | L7: N | M7: S | N7: PR | O7: - | P7: N | Q7: 100 | R7: N | S7: N | T7: N | U7: S | V7: S | W7: N | X7: S | Y7: S | Z7: N | AA7: S | AB7: 42863 | AC7: S | AD7: R$ 5.000.000,00 | AE7: S | AF7: S | AG7: N | AH7: S | AI7: 520974.26 | AJ7: 826 | AK7: GF4 PARTICIPACOES LTDA | AL7: S | AM7: S | AN7: D | AO7: N/D | AP7: N/D | AQ7: Pedido cancelado | AR7: Liberado | AS7: 46134 | AT7: =Calculo!AQ7 -> 13 | AU7: =Calculo!AV7 -> SEM-RISCO | AV7: =Calculo!AW7 -> LIBERADO | AW7: =Calculo!AX7 -> N/A | AX7: =Calculo!K7 -> N/A | AY7: =Calculo!AY7 -> N/A | AZ7: =Calculo!AZ7 -> N/A
A8: ='Parâmetros'!$A$19 -> Rel. Básico PJ | D8: Metalpleno | F8: 12804 | G8: OK | H8: S | I8: N | J8: N | K8: N | L8: S | M8: N | N8: SP | O8: 0 | P8: S | Q8: 100 | R8: N | S8: N | T8: N | U8: S | V8: S | W8: S | X8: S | Y8: N | Z8: N | AA8: S | AB8: 39654 | AC8: S | AD8: R$ 184.120.000,00 | AE8: S | AF8: S | AG8: N | AH8: N | AI8: 1413.88 | AJ8: 797 | AK8: RG LOG LOGISTICA E TRANSPORTE LTDA | AL8: S | AM8: S | AN8: D | AO8: N/D | AP8: N/D | AQ8: Pré análise-Andrea | AR8: Liberado | AS8: 46134 | AT8: =Calculo!AQ8 -> 21 | AU8: =Calculo!AV8 -> SEM-RISCO | AV8: =Calculo!AW8 -> LIBERADO | AW8: =Calculo!AX8 -> SOLICITAR PED COMPRA | AX8: =Calculo!K8 -> SOLIC CONTRATO DE ENTREGA | AY8: =Calculo!AY8 -> CHECAGEM REVERSA | AZ8: =Calculo!AZ8 -> N/A
A9: ='Parâmetros'!$A$19 -> Rel. Básico PJ | B9: 446 | C9: 25094 | D9: Oaco | E9: 144472 | F9: 2370.14 | G9: OK | H9: S | I9: N | J9: N | K9: N | L9: S | M9: S | N9: RJ | O9: 5 | Q9: 100 | R9: N | S9: N | T9: N | U9: S | V9: S | W9: N | X9: S | Y9: S | Z9: N | AA9: S | AB9: 45366 | AC9: N | AD9: R$ 100.000,00 | AE9: S | AF9: N | AG9: N | AH9: S | AI9: 68159.59 | AK9: ECOSI METAIS E ACESSORIOS LTDA | AL9: S | AM9: S | AN9: D | AO9: N/D | AP9: N/D | AR9: Bloqueado | AS9: 46134 | AT9: =Calculo!AQ9 -> -29 | AU9: =Calculo!AV9 -> GRANDE-OU-FALINDO: | AV9: =Calculo!AW9 -> SE FALINDO SÓ ANTECIPADO | SE GRANDE BUROCR PEGAR CONTATOS FINANCEIRO | AW9: =Calculo!AX9 -> N/A | AX9: =Calculo!K9 -> SOLIC CONTRATO DE ENTREGA | AY9: =Calculo!AY9 -> N/A | AZ9: =Calculo!AZ9 -> N/A
A10: ='Parâmetros'!$A$19 -> Rel. Básico PJ | B10: 170 | C10: 25110 | D10: Metalpleno | E10: 144477 | F10: 8081 | G10: OK | H10: S | I10: S | J10: N | K10: N | L10: S | M10: S | N10: SP | O10: 5 | P10: S | Q10: 100 | R10: N | S10: N | T10: N | U10: S | V10: S | W10: N | X10: S | Y10: S | Z10: N | AA10: S | AB10: 30124 | AC10: S | AD10: R$ 879.784.955,67 | AE10: S | AF10: S | AG10: N | AH10: S | AI10: 2607178 | AK10: BOMBRIL S/A-EM RECUPERACAO JUDICIAL | AL10: S | AM10: S | AN10: D | AO10: N/D | AP10: N/D | AR10: Liberado | AS10: 46142 | AT10: =Calculo!AQ10 -> 12 | AU10: =Calculo!AV10 -> SEM-RISCO | AV10: =Calculo!AW10 -> LIBERADO | AW10: =Calculo!AX10 -> SOLICITAR PED COMPRA | AX10: =Calculo!K10 -> SOLIC CONTRATO DE ENTREGA | AY10: =Calculo!AY10 -> N/A | AZ10: =Calculo!AZ10 -> N/A
A11: ='Parâmetros'!$A$19 -> Rel. Básico PJ | B11: 172 | C11: 25148 | D11: Metalpleno | E11: 144481 | F11: 4567 | G11: OK | H11: S | I11: N | J11: N | K11: N | L11: S | M11: N | N11: SP | O11: 0 | P11: S | Q11: 100 | R11: N | S11: N | T11: N | U11: S | V11: S | W11: N | X11: S | Y11: N | Z11: N | AA11: S | AB11: 39423 | AC11: N | AD11: R$ 1.490.000,00 | AE11: S | AF11: S | AG11: N | AH11: N | AI11: 424.52 | AJ11: 745 | AK11: TECNOR INDUSTRIA E COMERCIO DE MAQUINAS E EQUIPAMENTOS | AL11: S | AM11: S | AN11: D | AO11: N/D | AP11: N/D | AR11: Liberado | AS11: 46139 | AT11: =Calculo!AQ11 -> 22 | AU11: =Calculo!AV11 -> SEM-RISCO | AV11: =Calculo!AW11 -> LIBERADO | AW11: =Calculo!AX11 -> N/A | AX11: =Calculo!K11 -> SOLIC CONTRATO DE ENTREGA | AY11: =Calculo!AY11 -> CHECAGEM REVERSA | AZ11: =Calculo!AZ11 -> N/A
A12: ='Parâmetros'!$A$19 -> Rel. Básico PJ | B12: 171 | C12: 24933 | D12: Metalpleno | E12: 144480 | F12: 4103 | G12: OK | H12: S | I12: N | J12: N | K12: N | L12: S | M12: N | N12: SC | O12: 0 | P12: - | Q12: 100 | R12: N | S12: N | T12: N | U12: S | V12: S | W12: N | X12: S | Y12: S | Z12: N | AA12: S | AB12: 39772 | AC12: N | AD12: R$ 21.300,000,00 | AE12: S | AF12: N | AG12: N | AH12: N | AI12: 0 | AJ12: 1000 | AK12: ADF EMPRESAS REUNIDAS LTDA | AL12: S | AM12: S | AN12: D | AO12: N/D | AP12: N/D | AR12: Liberado | AS12: 46139 | AT12: =Calculo!AQ12 -> 29 | AU12: =Calculo!AV12 -> SEM-RISCO | AV12: =Calculo!AW12 -> LIBERADO | AW12: =Calculo!AX12 -> N/A | AX12: =Calculo!K12 -> SOLIC CONTRATO DE ENTREGA | AY12: =Calculo!AY12 -> CHECAGEM REVERSA | AZ12: =Calculo!AZ12 -> N/A
A13: ='Parâmetros'!$A$19 -> Rel. Básico PJ | B13: 460 | C13: 25168 | D13: Oaco | E13: 144485 | F13: 2199 | G13: OK | H13: S | I13: N | J13: N | K13: N | L13: S | M13: N | N13: RS | O13: 0 | P13: S | Q13: 100 | R13: N | S13: N | T13: N | U13: S | V13: S | W13: N | X13: S | Y13: S | Z13: N | AA13: S | AB13: 38408 | AC13: N | AD13: R$ 6.041.064,00 | AE13: S | AF13: N | AG13: N | AH13: N | AI13: 0 | AJ13: 832 | AK13: MARQUESPAN ALIMENTOS LTDA | AL13: S | AM13: S | AN13: D | AO13: N/D | AP13: N/D | AQ13: MODULAR TRANSPORTES LTDA (SP) | AR13: Liberado | AS13: 46140 | AT13: =Calculo!AQ13 -> 35 | AU13: =Calculo!AV13 -> SEM-RISCO | AV13: =Calculo!AW13 -> LIBERADO | AW13: =Calculo!AX13 -> N/A | AX13: =Calculo!K13 -> SOLIC CONTRATO DE ENTREGA | AY13: =Calculo!AY13 -> CHECAGEM REVERSA | AZ13: =Calculo!AZ13 -> N/A
A14: ='Parâmetros'!$A$19 -> Rel. Básico PJ | B14: 176 | C14: 25175 | D14: Metalpleno | E14: 033086 | F14: 6402 | G14: OK | H14: S | I14: N | J14: N | K14: N | L14: S | M14: 0 | N14: SP | O14: 0 | P14: S | Q14: 100 | R14: N | S14: N | T14: N | U14: S | V14: S | W14: N | X14: S | Y14: N | Z14: N | AA14: S | AB14: 43642 | AC14: N | AD14: R$ 437.323,00 | AE14: S | AF14: N | AG14: N | AH14: N | AI14: 0 | AJ14: 902 | AK14: CYMZ CONSTRUCOES LTDA | AL14: S | AM14: S | AN14: D | AO14: N/D | AP14: N/D | AR14: Liberado | AS14: 46140 | AT14: =Calculo!AQ14 -> 24 | AU14: =Calculo!AV14 -> SEM-RISCO | AV14: =Calculo!AW14 -> LIBERADO | AW14: =Calculo!AX14 -> SOLICITAR PED COMPRA | AX14: =Calculo!K14 -> SOLIC CONTRATO DE ENTREGA | AY14: =Calculo!AY14 -> CHECAGEM REVERSA | AZ14: =Calculo!AZ14 -> N/A
A15: ='Parâmetros'!$A$19 -> Rel. Básico PJ | B15: 175 | C15: 25079 | D15: Metalpleno | E15: 005031 | F15: 6402 | G15: OK | H15: S | I15: N | J15: N | K15: N | L15: S | M15: N | N15: PA | O15: 0 | P15: N | Q15: 100 | R15: N | S15: N | T15: N | U15: S | V15: S | W15: N | X15: S | Y15: S | Z15: N | AA15: S | AB15: 31400 | AC15: N | AD15: R$ 2.548.010.108,99 | AE15: S | AF15: S | AG15: N | AH15: N | AI15: 8068.54 | AJ15: 850 | AK15: SIDERURGICA NORTE BRASIL SA | AL15: S | AM15: S | AN15: D | AO15: N/D | AP15: N/D | AR15: Liberado | AS15: 46141 | AT15: =Calculo!AQ15 -> 27 | AU15: =Calculo!AV15 -> SEM-RISCO | AV15: =Calculo!AW15 -> LIBERADO | AW15: =Calculo!AX15 -> SOLICITAR PED COMPRA | AX15: =Calculo!K15 -> SOLIC CONTRATO DE ENTREGA | AY15: =Calculo!AY15 -> CHECAGEM REVERSA | AZ15: =Calculo!AZ15 -> N/A
A16: ='Parâmetros'!$A$19 -> Rel. Básico PJ | B16: 177 | C16: 25159 | D16: Metalpleno | E16: 144489 | F16: 4103.1 | G16: OK | H16: S | I16: N | J16: N | K16: N | L16: S | M16: S | N16: SP | O16: 5 | P16: N | Q16: 100 | R16: N | S16: N | T16: N | U16: S | V16: S | W16: N | X16: S | Y16: S | Z16: N | AA16: S | AB16: 35607 | AC16: N | AD16: R$ 32.224.443,00 | AE16: S | AF16: N | AG16: N | AH16: N | AI16: 0 | AJ16: 639 | AK16: SLEEVER INTERNATIONAL LTDA | AL16: S | AM16: S | AN16: D | AO16: N/D | AP16: N/D | AR16: Liberado | AS16: 46141 | AT16: =Calculo!AQ16 -> 42 | AU16: =Calculo!AV16 -> SEM-RISCO | AV16: =Calculo!AW16 -> LIBERADO | AW16: =Calculo!AX16 -> N/A | AX16: =Calculo!K16 -> SOLIC CONTRATO DE ENTREGA | AY16: =Calculo!AY16 -> N/A | AZ16: =Calculo!AZ16 -> N/A
A17: ='Parâmetros'!$A$19 -> Rel. Básico PJ | B17: 178 | C17: 24981 | D17: Metalpleno | E17: 144490 | F17: 23405 | G17: OK | H17: S | I17: S | J17: N | K17: N | L17: S | M17: S | N17: SP | O17: 5 | P17: S | Q17: 100 | R17: N | S17: N | T17: N | U17: S | V17: S | W17: N | X17: S | Y17: S | Z17: N | AA17: S | AB17: 30124 | AC17: S | AD17: R$ 879.784.955,67 | AE17: S | AF17: S | AG17: N | AH17: N | AI17: 2607178 | AK17: BOMBRIL S/A-EM RECUPERACAO JUDICIAL | AL17: S | AM17: S | AN17: D | AO17: N/D | AP17: N/D | AR17: Liberado | AS17: 46142 | AT17: =Calculo!AQ17 -> 19 | AU17: =Calculo!AV17 -> SEM-RISCO | AV17: =Calculo!AW17 -> LIBERADO | AW17: =Calculo!AX17 -> SOLICITAR PED COMPRA | AX17: =Calculo!K17 -> SOLIC CONTRATO DE ENTREGA | AY17: =Calculo!AY17 -> N/A | AZ17: =Calculo!AZ17 -> N/A
A18: ='Parâmetros'!$A$19 -> Rel. Básico PJ | B18: 466 | C18: 25024 | D18: Oaco | E18: 028293 | F18: 4990 | G18: OK | H18: S | I18: N | J18: N | K18: N | L18: N | M18: S | N18: SP | O18: - | P18: N | Q18: 100 | R18: N | S18: S | T18: S | U18: S | V18: S | W18: N | X18: S | Y18: S | Z18: N | AA18: S | AB18: 37971 | AC18: S | AD18: R$ 15.711.359.775,89 | AE18: S | AF18: S | AG18: N | AH18: S | AI18: 42379256 | AJ18: 791 | AK18: REDE D'OR SAO LUIZ SA | AL18: S | AM18: S | AN18: D | AO18: N/D | AP18: N/D | AR18: Liberado | AS18: 46142 | AT18: =Calculo!AQ18 -> 52 | AU18: =Calculo!AV18 -> SEM-RISCO | AV18: =Calculo!AW18 -> LIBERADO | AW18: =Calculo!AX18 -> N/A | AX18: =Calculo!K18 -> N/A | AY18: =Calculo!AY18 -> N/A | AZ18: =Calculo!AZ18 -> N/A
A19: ='Parâmetros'!$A$19 -> Rel. Básico PJ | B19: 182 | C19: 24852 | D19: Metalpleno | E19: 143634 | F19: 6753.14 | G19: OK | H19: S | I19: N | J19: N | K19: N | L19: S | M19: S | N19: SP | O19: 5 | P19: N | Q19: 100 | R19: N | S19: S | T19: N | U19: S | V19: S | W19: N | X19: S | Y19: N | Z19: N | AA19: S | AB19: 31315 | AC19: S | AD19: R$ 247.060.169,00 | AE19: S | AF19: S | AG19: N | AH19: S | AI19: 1821.14 | AJ19: 868 | AK19: JM LUBRIFICANTES E PECAS P VEICULOS LTDA | AL19: S | AM19: S | AN19: D | AO19: N/D | AP19: N/D | AR19: Liberado | AS19: 46146 | AT19: =Calculo!AQ19 -> 39 | AU19: =Calculo!AV19 -> SEM-RISCO | AV19: =Calculo!AW19 -> LIBERADO | AW19: =Calculo!AX19 -> SOLICITAR PED COMPRA | AX19: =Calculo!K19 -> SOLIC CONTRATO DE ENTREGA | AY19: =Calculo!AY19 -> N/A | AZ19: =Calculo!AZ19 -> N/A
A20: ='Parâmetros'!$A$19 -> Rel. Básico PJ | B20: 185 | C20: 23478 | D20: Metalpleno | E20: 144500 | F20: 7870 | G20: OK | H20: S | I20: N | J20: N | K20: N | L20: S | M20: S | N20: GO | O20: - | P20: S | Q20: 100 | R20: N | S20: S | T20: N | U20: S | V20: S | W20: S | X20: S | Y20: N | Z20: N | AA20: S | AB20: 41884 | AC20: S | AD20: R$ 5.000,00 | AE20: S | AF20: S | AG20: N | AH20: N | AI20: 9799.56 | AK20: PREVINA CURSOS E EQUIPAMENTOS LTDA | AL20: S | AM20: S | AN20: D | AO20: N/D | AP20: N/D | AR20: Liberado | AS20: 46147 | AT20: =Calculo!AQ20 -> 9 | AU20: =Calculo!AV20 -> SEM-RISCO | AV20: =Calculo!AW20 -> LIBERADO | AW20: =Calculo!AX20 -> SOLICITAR PED COMPRA | AX20: =Calculo!K20 -> SOLIC CONTRATO DE ENTREGA | AY20: =Calculo!AY20 -> N/A | AZ20: =Calculo!AZ20 -> N/A
A21: ='Parâmetros'!$A$19 -> Rel. Básico PJ | B21: 186 | C21: 25163 | D21: Metalpleno | E21: 144343 | F21: 1794 | G21: OK | H21: S | I21: N | J21: N | K21: N | L21: N | M21: S | N21: SP | O21: 5 | P21: N | Q21: 100 | R21: N | S21: S | T21: N | U21: S | V21: S | W21: S | X21: S | Y21: N | Z21: N | AA21: S | AB21: 42496 | AC21: N | AD21: R$1.000.000,00 | AE21: S | AF21: N | AG21: N | AH21: S | AI21: 11488.72 | AJ21: 623 | AK21: CLINICA MEDICA DE NEFROLOGIA DE JUNDIAI LTDA | AL21: S | AM21: S | AN21: D | AO21: N/D | AP21: N/D | AR21: Liberado | AS21: 46147 | AT21: =Calculo!AQ21 -> 12 | AU21: =Calculo!AV21 -> SEM-RISCO | AV21: =Calculo!AW21 -> LIBERADO | AW21: =Calculo!AX21 -> N/A | AX21: =Calculo!K21 -> N/A | AY21: =Calculo!AY21 -> N/A | AZ21: =Calculo!AZ21 -> N/A
A22: ='Parâmetros'!$A$19 -> Rel. Básico PJ | B22: 187 | C22: 25247 | D22: Metalpleno | E22: 144160 | F22: 6402 | G22: OK | H22: S | I22: N | J22: N | K22: N | L22: S | M22: 0 | N22: MG | O22: - | P22: N | Q22: 100 | R22: N | S22: S | T22: N | U22: S | V22: S | W22: N | X22: S | Y22: S | Z22: N | AA22: S | AB22: 45125 | AC22: N | AD22: R$ 150.000,00 | AE22: S | AF22: N | AG22: N | AH22: N | AI22: 0 | AJ22: 699 | AK22: MD'ORE FERRAMENTAS E FIXACAO LTDA | AL22: S | AM22: S | AN22: D | AO22: N/D | AP22: N/D | AR22: Liberado | AS22: 46148 | AT22: =Calculo!AQ22 -> 30 | AU22: =Calculo!AV22 -> SEM-RISCO | AV22: =Calculo!AW22 -> LIBERADO | AW22: =Calculo!AX22 -> SOLICITAR PED COMPRA | AX22: =Calculo!K22 -> SOLIC CONTRATO DE ENTREGA | AY22: =Calculo!AY22 -> CHECAGEM REVERSA | AZ22: =Calculo!AZ22 -> N/A
A23: ='Parâmetros'!$A$19 -> Rel. Básico PJ | B23: 188 | C23: 25125 | D23: Metalpleno | E23: 144504 | F23: 4175.93 | G23: OK | H23: S | I23: N | J23: N | K23: N | L23: S | M23: S | N23: DF | O23: - | P23: N | Q23: 100 | R23: N | S23: N | T23: N | U23: S | V23: S | W23: S | X23: N | Y23: N | Z23: S | AA23: S | AB23: 42835 | AC23: N | AD23: R$ 20.000,00 | AE23: S | AF23: N | AG23: N | AH23: N | AI23: 0 | AJ23: 598 | AK23: INEB CLINICA MEDICA DE NEFROLOGIA LTDA | AL23: S | AM23: S | AN23: D | AO23: N/D | AP23: N/D | AR23: Liberado | AS23: 46149 | AT23: =Calculo!AQ23 -> 6 | AU23: =Calculo!AV23 -> SEM-RISCO | AV23: =Calculo!AW23 -> LIBERADO | AW23: =Calculo!AX23 -> N/A | AX23: =Calculo!K23 -> SOLIC CONTRATO DE ENTREGA | AY23: =Calculo!AY23 -> N/A | AZ23: =Calculo!AZ23 -> N/A
A24: ='Parâmetros'!$A$19 -> Rel. Básico PJ | B24: - | C24: - | D24: Metalpleno | E24: - | F24: 6402 | G24: OK | H24: S | I24: N | J24: N | K24: N | L24: S | M24: 0 | N24: SP | O24: - | P24: N | Q24: 100 | R24: N | S24: N | T24: N | U24: S | V24: S | W24: N | X24: S | Y24: N | Z24: N | AA24: S | AB24: 33695 | AC24: N | AD24: R$ 8.000.000,00 | AE24: S | AF24: N | AG24: N | AH24: N | AI24: 0 | AJ24: 868 | AK24: INFORMOV LTDA | AL24: S | AM24: S | AN24: D | AO24: N/D | AP24: N/D | AQ24: Pré análise Andrea | AR24: Liberado | AS24: 46150 | AT24: =Calculo!AQ24 -> 29 | AU24: =Calculo!AV24 -> SEM-RISCO | AV24: =Calculo!AW24 -> LIBERADO | AW24: =Calculo!AX24 -> SOLICITAR PED COMPRA | AX24: =Calculo!K24 -> SOLIC CONTRATO DE ENTREGA | AY24: =Calculo!AY24 -> CHECAGEM REVERSA | AZ24: =Calculo!AZ24 -> N/A
A25: ='Parâmetros'!$A$19 -> Rel. Básico PJ | B25: 1866 | C25: 25227 | D25: GsiBW | E25: 016801 | F25: 965 | G25: OK | H25: S | I25: N | J25: N | K25: N | L25: N | M25: S | N25: RS | O25: - | P25: S | Q25: 100 | R25: N | S25: S | T25: S | U25: S | V25: S | W25: N | X25: S | Y25: S | Z25: N | AA25: S | AB25: 24343 | AC25: S | AD25: R$ 39.249.899,97 | AE25: S | AF25: S | AG25: N | AH25: S | AI25: 30122330 | AK25: COMPANHIA MINUANO DE ALIMENTOS | AL25: S | AM25: S | AN25: N | AO25: N/D | AP25: N/D | AR25: Liberado | AS25: 46150 | AT25: =Calculo!AQ25 -> 28 | AU25: =Calculo!AV25 -> SEM-RISCO | AV25: =Calculo!AW25 -> LIBERADO | AW25: =Calculo!AX25 -> N/A | AX25: =Calculo!K25 -> N/A | AY25: =Calculo!AY25 -> N/A | AZ25: =Calculo!AZ25 -> N/A
A26: ='Parâmetros'!$A$19 -> Rel. Básico PJ | B26: 191 | C26: 25203 | D26: Metalpleno | E26: 143436 | F26: 7003 | G26: OK | H26: S | I26: N | J26: N | K26: N | L26: S | M26: S | N26: PR | O26: 5 | P26: N | Q26: 100 | R26: N | S26: S | T26: N | U26: S | V26: S | W26: N | X26: S | Y26: S | Z26: N | AA26: S | AB26: 42964 | AC26: N | AD26: R$ 99.800,00 | AE26: S | AF26: N | AG26: N | AH26: N | AI26: 0 | AJ26: 791 | AK26: NUTRIGENES INDUSTRIA DE PRODS NATURAIS E NUTRACEUTIC | AL26: S | AM26: S | AN26: D | AO26: N/D | AP26: N/D | AR26: Liberado | AS26: 46150 | AT26: =Calculo!AQ26 -> 54 | AU26: =Calculo!AV26 -> SEM-RISCO | AV26: =Calculo!AW26 -> LIBERADO | AW26: =Calculo!AX26 -> SOLICITAR PED COMPRA | AX26: =Calculo!K26 -> SOLIC CONTRATO DE ENTREGA | AY26: =Calculo!AY26 -> N/A | AZ26: =Calculo!AZ26 -> N/A
A27: ='Parâmetros'!$A$19 -> Rel. Básico PJ | B27: 193 | C27: 25285 | D27: Metalpleno | E27: 144160 | F27: 6402 | G27: OK | H27: S | I27: N | J27: N | K27: N | L27: S | M27: 0 | N27: MG | O27: - | P27: N | Q27: 100 | R27: N | S27: S | T27: N | U27: S | V27: S | W27: N | X27: S | Y27: S | Z27: N | AA27: S | AB27: 45125 | AC27: N | AD27: R$ 150.000,00 | AE27: S | AF27: N | AG27: N | AH27: N | AI27: 0 | AJ27: 699 | AK27: MD'ORE FERRAMENTAS E FIXACAO LTDA | AL27: S | AM27: S | AN27: D | AO27: N/D | AP27: N/D | AR27: Liberado | AS27: 46150 | AT27: =Calculo!AQ27 -> 30 | AU27: =Calculo!AV27 -> SEM-RISCO | AV27: =Calculo!AW27 -> LIBERADO | AW27: =Calculo!AX27 -> SOLICITAR PED COMPRA | AX27: =Calculo!K27 -> SOLIC CONTRATO DE ENTREGA | AY27: =Calculo!AY27 -> CHECAGEM REVERSA | AZ27: =Calculo!AZ27 -> N/A
A28: ='Parâmetros'!$A$19 -> Rel. Básico PJ | B28: 487 | C28: 25181 | D28: Oaco | E28: 144512 | F28: 614 | G28: OK | H28: S | I28: N | J28: N | K28: N | L28: N | M28: S | N28: RS | O28: - | P28: S | Q28: 100 | R28: N | S28: S | T28: S | U28: S | V28: S | W28: N | X28: S | Y28: N | Z28: N | AA28: S | AB28: 40639 | AC28: S | AD28: R$ 205.046.507,00 | AE28: S | AF28: N | AG28: N | AH28: S | AI28: 33000 | AJ28: 757 | AK28: CALZEDONIA BRASIL COMERCIO DE MODA E ACESSORIOS LTDA | AL28: S | AM28: S | AN28: D | AO28: N/D | AP28: N/D | AR28: Liberado | AS28: 46150 | AT28: =Calculo!AQ28 -> 47 | AU28: =Calculo!AV28 -> SEM-RISCO | AV28: =Calculo!AW28 -> LIBERADO | AW28: =Calculo!AX28 -> N/A | AX28: =Calculo!K28 -> N/A | AY28: =Calculo!AY28 -> N/A | AZ28: =Calculo!AZ28 -> N/A
A29: ='Parâmetros'!$A$19 -> Rel. Básico PJ | B29: 488 | C29: 25183 | D29: Oaco | E29: 144513 | F29: 614 | G29: OK | H29: S | I29: N | J29: N | K29: N | L29: N | M29: S | N29: RS | O29: - | P29: S | Q29: 100 | R29: N | S29: S | T29: S | U29: S | V29: S | W29: N | X29: S | Y29: N | Z29: N | AA29: S | AB29: 40639 | AC29: S | AD29: R$ 205.046.507,00 | AE29: S | AF29: N | AG29: N | AH29: S | AI29: 33000 | AJ29: 757 | AK29: CALZEDONIA BRASIL COMERCIO DE MODA E ACESSORIOS LTDA | AL29: S | AM29: S | AN29: D | AO29: N/D | AP29: N/D | AR29: Liberado | AS29: 46150 | AT29: =Calculo!AQ29 -> 47 | AU29: =Calculo!AV29 -> SEM-RISCO | AV29: =Calculo!AW29 -> LIBERADO | AW29: =Calculo!AX29 -> N/A | AX29: =Calculo!K29 -> N/A | AY29: =Calculo!AY29 -> N/A | AZ29: =Calculo!AZ29 -> N/A
A30: ='Parâmetros'!$A$19 -> Rel. Básico PJ | B30: 496 | C30: 25286 | D30: Oaco | E30: 144520 | F30: 614 | G30: OK | H30: S | I30: N | J30: N | K30: N | L30: N | M30: S | N30: RS | O30: - | P30: S | Q30: 100 | R30: N | S30: S | T30: S | U30: S | V30: S | W30: N | X30: S | Y30: N | Z30: N | AA30: S | AB30: 40639 | AC30: S | AD30: R$ 205.046.507,00 | AE30: S | AF30: N | AG30: N | AH30: S | AI30: 33000 | AJ30: 757 | AK30: CALZEDONIA BRASIL COMERCIO DE MODA E ACESSORIOS LTDA | AL30: S | AM30: S | AN30: D | AO30: N/D | AP30: N/D | AR30: Liberado | AS30: 46153 | AT30: =Calculo!AQ30 -> 47 | AU30: =Calculo!AV30 -> SEM-RISCO | AV30: =Calculo!AW30 -> LIBERADO | AW30: =Calculo!AX30 -> N/A | AX30: =Calculo!K30 -> N/A | AY30: =Calculo!AY30 -> N/A | AZ30: =Calculo!AZ30 -> N/A
A31: ='Parâmetros'!$A$19 -> Rel. Básico PJ | B31: 499 | C31: 24507 | D31: Oaco | E31: 029288 | F31: 20400 | G31: OK | H31: S | I31: N | J31: N | K31: N | L31: S | M31: S | N31: SP | O31: - | P31: S | Q31: 100 | R31: N | S31: N | T31: N | U31: S | V31: S | W31: N | X31: S | Y31: S | Z31: N | AA31: S | AB31: 36426 | AC31: N | AE31: S | AF31: N | AG31: N | AH31: N | AI31: 0 | AJ31: 826 | AK31: COOPERATIVA VEILING HOLAMBRA | AL31: S | AM31: S | AN31: D | AO31: N/D | AP31: N/D | AR31: Liberado | AS31: 46153 | AT31: =Calculo!AQ31 -> 26 | AU31: =Calculo!AV31 -> SEM-RISCO | AV31: =Calculo!AW31 -> LIBERADO | AW31: =Calculo!AX31 -> SOLICITAR PED COMPRA | AX31: =Calculo!K31 -> SOLIC CONTRATO DE ENTREGA | AY31: =Calculo!AY31 -> N/A | AZ31: =Calculo!AZ31 -> N/A
A32: ='Parâmetros'!$A$19 -> Rel. Básico PJ | B32: 194 | C32: 24655 | D32: Metalpleno | E32: 027081 | F32: 3730.8 | G32: OK | H32: S | I32: N | J32: N | K32: N | L32: S | M32: N | N32: MG | O32: 0 | P32: S | Q32: 100 | R32: N | S32: S | T32: N | U32: S | V32: S | W32: N | X32: S | Y32: S | Z32: N | AA32: S | AB32: 36088 | AC32: S | AD32: R$ 56.186.394,00 | AE32: S | AF32: S | AG32: N | AH32: S | AI32: 54894.55 | AJ32: 641 | AK32: CIMED INDUSTRIA SA | AL32: S | AM32: S | AN32: D | AO32: N/D | AP32: N/D | AR32: Liberado | AS32: 46154 | AT32: =Calculo!AQ32 -> 17 | AU32: =Calculo!AV32 -> SEM-RISCO | AV32: =Calculo!AW32 -> LIBERADO | AW32: =Calculo!AX32 -> N/A | AX32: =Calculo!K32 -> SOLIC CONTRATO DE ENTREGA | AY32: =Calculo!AY32 -> CHECAGEM REVERSA | AZ32: =Calculo!AZ32 -> N/A
A33: ='Parâmetros'!$A$19 -> Rel. Básico PJ | B33: 507 | C33: 25335 | D33: Oaco | E33: 143764 | F33: 2320 | G33: OK | H33: S | I33: N | J33: N | K33: N | L33: S | M33: S | N33: DF | O33: - | P33: S | Q33: 100 | R33: N | S33: S | T33: N | U33: S | V33: S | W33: S | X33: S | Y33: S | Z33: N | AA33: S | AB33: 30568 | AC33: N | AE33: S | AF33: N | AG33: N | AH33: N | AI33: 0 | AJ33: 596 | AK33: CONSELHO NACIONAL DE SECRETARIOS DE SAUDE | AL33: S | AM33: S | AN33: D | AO33: N/D | AP33: N/D | AR33: Liberado | AS33: 46154 | AT33: =Calculo!AQ33 -> 32 | AU33: =Calculo!AV33 -> SEM-RISCO | AV33: =Calculo!AW33 -> LIBERADO | AW33: =Calculo!AX33 -> N/A | AX33: =Calculo!K33 -> SOLIC CONTRATO DE ENTREGA | AY33: =Calculo!AY33 -> N/A | AZ33: =Calculo!AZ33 -> N/A
A34: ='Parâmetros'!$A$19 -> Rel. Básico PJ | B34: 511 | C34: 25318 | D34: Oaco | E34: 144527 | F34: 4350 | G34: OK | H34: S | I34: N | J34: N | K34: N | L34: S | M34: S | N34: RJ | O34: 5 | P34: S | Q34: 100 | R34: N | S34: N | T34: N | U34: S | V34: S | W34: N | X34: S | Y34: S | Z34: N | AA34: S | AB34: 26156 | AC34: N | AD34: R$ 844.613.653,86 | AE34: S | AF34: S | AG34: N | AH34: S | AI34: 3607770.8 | AJ34: 757 | AK34: COMPANHIA ESTADUAL DE AGUAS E ESGOTO CEDAE | AL34: S | AM34: S | AN34: D | AO34: N/D | AP34: N/D | AR34: Liberado | AS34: 46155 | AT34: =Calculo!AQ34 -> 7 | AU34: =Calculo!AV34 -> SEM-RISCO | AV34: =Calculo!AW34 -> LIBERADO | AW34: =Calculo!AX34 -> N/A | AX34: =Calculo!K34 -> SOLIC CONTRATO DE ENTREGA | AY34: =Calculo!AY34 -> N/A | AZ34: =Calculo!AZ34 -> N/A
A35: ='Parâmetros'!$A$19 -> Rel. Básico PJ | B35: 210 | C35: 25339 | D35: Metalpleno | E35: 144552 | F35: 14810 | G35: OK | H35: S | I35: N | J35: N | K35: N | L35: S | M35: S | N35: SC | O35: 5 | P35: S | Q35: 100 | R35: N | S35: N | T35: N | U35: S | V35: S | W35: N | X35: S | Y35: N | Z35: N | AA35: S | AB35: 39093 | AC35: N | AD35: R$ 68.805.136,00 | AE35: S | AF35: N | AG35: N | AH35: N | AI35: 0 | AJ35: 978 | AK35: BOM JARDIM ENERGIA EOLICA SA | AL35: S | AM35: S | AN35: D | AO35: N/D | AP35: N/D | AR35: Liberado | AS35: 46164 | AT35: =Calculo!AQ35 -> 39 | AU35: =Calculo!AV35 -> SEM-RISCO | AV35: =Calculo!AW35 -> LIBERADO | AW35: =Calculo!AX35 -> SOLICITAR PED COMPRA | AX35: =Calculo!K35 -> SOLIC CONTRATO DE ENTREGA | AY35: =Calculo!AY35 -> N/A | AZ35: =Calculo!AZ35 -> N/A
A36: ='Parâmetros'!$A$19 -> Rel. Básico PJ | B36: 211 | C36: 25340 | D36: Metalpleno | E36: 141469 | F36: 15232 | G36: OK | H36: S | I36: N | J36: N | K36: N | L36: S | M36: S | N36: SC | O36: 5 | P36: S | Q36: 100 | R36: N | S36: N | T36: N | U36: S | V36: S | W36: N | X36: S | Y36: N | Z36: N | AA36: S | AB36: 39093 | AC36: N | AD36: R$ 67.599.702,00 | AE36: S | AF36: N | AG36: N | AH36: N | AI36: 0 | AJ36: 703 | AK36: AQUIBATA ENERGIA EOLICA SA | AL36: S | AM36: S | AN36: D | AO36: N/D | AP36: N/D | AR36: Liberado | AS36: 46164 | AT36: =Calculo!AQ36 -> 39 | AU36: =Calculo!AV36 -> SEM-RISCO | AV36: =Calculo!AW36 -> LIBERADO | AW36: =Calculo!AX36 -> SOLICITAR PED COMPRA | AX36: =Calculo!K36 -> SOLIC CONTRATO DE ENTREGA | AY36: =Calculo!AY36 -> N/A | AZ36: =Calculo!AZ36 -> N/A
A37: ='Parâmetros'!$A$19 -> Rel. Básico PJ | B37: 195 | C37: 25207 | D37: Metalpleno | E37: 144528 | F37: 13704 | G37: OK | H37: S | I37: N | J37: N | K37: N | L37: S | M37: S | N37: SP | O37: 5 | P37: S | Q37: 100 | R37: N | S37: N | T37: N | U37: S | V37: S | W37: N | X37: S | Y37: S | Z37: N | AA37: S | AB37: 29619 | AC37: N | AD37: R$ 34.403.499,00 | AE37: S | AF37: S | AG37: N | AH37: N | AI37: 70.37 | AJ37: 906 | AK37: TRUMPF MAQUINAS INDUSTRIA E COMERCIO LTDA | AL37: S | AM37: S | AN37: D | AO37: N/D | AP37: N/D | AR37: Liberado | AS37: 46155 | AT37: =Calculo!AQ37 -> 44 | AU37: =Calculo!AV37 -> SEM-RISCO | AV37: =Calculo!AW37 -> LIBERADO | AW37: =Calculo!AX37 -> SOLICITAR PED COMPRA | AX37: =Calculo!K37 -> SOLIC CONTRATO DE ENTREGA | AY37: =Calculo!AY37 -> N/A | AZ37: =Calculo!AZ37 -> N/A
A38: ='Parâmetros'!$A$19 -> Rel. Básico PJ | B38: 196 | C38: 25348 | D38: Metalpleno | E38: 144306 | F38: 7030 | G38: OK | H38: S | I38: N | J38: N | K38: N | L38: S | M38: S | N38: SP | O38: 5 | P38: S | Q38: 100 | R38: N | S38: S | T38: S | U38: S | V38: S | W38: N | X38: S | Y38: N | Z38: N | AA38: S | AB38: 26835 | AC38: S | AE38: S | AF38: S | AG38: N | AH38: N | AI38: 6000.01 | AJ38: 799 | AK38: UNIMED DE ARARAQUARA COOPERATIVA DE TRABALHO MEDICO | AL38: S | AM38: S | AN38: D | AO38: N/D | AP38: N/D | AR38: Liberado | AS38: 46155 | AT38: =Calculo!AQ38 -> 60 | AU38: =Calculo!AV38 -> SEM-RISCO | AV38: =Calculo!AW38 -> LIBERADO | AW38: =Calculo!AX38 -> SOLICITAR PED COMPRA | AX38: =Calculo!K38 -> SOLIC CONTRATO DE ENTREGA | AY38: =Calculo!AY38 -> N/A | AZ38: =Calculo!AZ38 -> N/A
A39: ='Parâmetros'!$A$19 -> Rel. Básico PJ | B39: 197 | C39: 25303 | D39: Metalpleno | E39: 144199 | F39: 6402 | G39: OK | H39: S | I39: N | J39: N | K39: N | L39: S | M39: N | N39: SP | O39: 0 | P39: S | Q39: 100 | R39: N | S39: S | T39: N | U39: S | V39: S | W39: N | X39: S | Y39: S | Z39: N | AA39: S | AB39: 43796 | AC39: N | AD39: R$ 823.920.411,76 | AE39: S | AF39: N | AG39: N | AH39: N | AI39: 0 | AJ39: 739 | AK39: LINS AGROINDUSTRIAL SA | AL39: S | AM39: S | AN39: D | AO39: N/D | AP39: N/D | AR39: Liberado | AS39: 46156 | AT39: =Calculo!AQ39 -> 43 | AU39: =Calculo!AV39 -> SEM-RISCO | AV39: =Calculo!AW39 -> LIBERADO | AW39: =Calculo!AX39 -> SOLICITAR PED COMPRA | AX39: =Calculo!K39 -> SOLIC CONTRATO DE ENTREGA | AY39: =Calculo!AY39 -> CHECAGEM REVERSA | AZ39: =Calculo!AZ39 -> N/A
A40: ='Parâmetros'!$A$19 -> Rel. Básico PJ | B40: 198 | C40: 24639 | D40: Metalpleno | E40: 143127 | F40: 6402 | G40: OK | H40: S | I40: S | J40: N | K40: N | L40: S | M40: N | N40: SP | O40: 0 | P40: S | Q40: 100 | R40: N | S40: S | T40: N | U40: S | V40: S | W40: N | X40: S | Y40: N | Z40: N | AA40: S | AB40: 44090 | AC40: N | AD40: R$ 2.000,00 | AE40: S | AF40: N | AG40: N | AH40: N | AI40: 0 | AJ40: 757 | AK40: JHV IMPORTACAO , EXPORTACAO INDUSTRIA E COMERCIO LTDA | AL40: S | AM40: N | AN40: D | AO40: N/D | AP40: N/D | AR40: Liberado | AS40: 46156 | AT40: =Calculo!AQ40 -> 42 | AU40: =Calculo!AV40 -> SEM-RISCO | AV40: =Calculo!AW40 -> LIBERADO | AW40: =Calculo!AX40 -> SOLICITAR PED COMPRA | AX40: =Calculo!K40 -> SOLIC CONTRATO DE ENTREGA | AY40: =Calculo!AY40 -> CHECAGEM REVERSA | AZ40: =Calculo!AZ40 -> N/A
A41: ='Parâmetros'!$A$19 -> Rel. Básico PJ | B41: 1868 | C41: 25362 | D41: GsiBW | E41: 011678 | F41: 906 | G41: OK | H41: S | I41: N | J41: N | K41: N | L41: N | M41: N | N41: SP | O41: 0 | P41: N | Q41: 100 | R41: N | S41: S | T41: S | U41: S | V41: S | W41: N | X41: S | Y41: S | Z41: N | AA41: S | AB41: 24596 | AC41: N | AE41: S | AF41: S | AG41: N | AH41: N | AI41: 5682788.9 | AJ41: 643 | AK41: MARCHESAN IMPLEMENTOS E MAQUINAS AGRICOLAS TATU SA | AL41: S | AM41: S | AN41: D | AO41: N/D | AP41: N/D | AR41: Liberado | AS41: 46156 | AT41: =Calculo!AQ41 -> 31 | AU41: =Calculo!AV41 -> SEM-RISCO | AV41: =Calculo!AW41 -> LIBERADO | AW41: =Calculo!AX41 -> N/A | AX41: =Calculo!K41 -> N/A | AY41: =Calculo!AY41 -> CHECAGEM REVERSA | AZ41: =Calculo!AZ41 -> N/A
A42: ='Parâmetros'!$A$19 -> Rel. Básico PJ | B42: 201 | C42: 25238 | D42: Metalpleno | E42: 144532 | F42: 4276 | G42: OK | H42: S | I42: N | J42: N | K42: N | L42: S | M42: S | N42: MG | O42: - | P42: S | Q42: 100 | R42: N | S42: N | T42: N | U42: S | V42: S | W42: S | X42: S | Y42: S | Z42: N | AA42: S | AB42: 44727 | AC42: S | AD42: R$ 250.007.946,00 | AE42: S | AF42: N | AG42: N | AH42: N | AI42: 0 | AJ42: 665 | AK42: BIONOW SA | AL42: S | AM42: S | AN42: D | AO42: N/D | AP42: N/D | AR42: Liberado | AS42: 46157 | AT42: =Calculo!AQ42 -> 28 | AU42: =Calculo!AV42 -> SEM-RISCO | AV42: =Calculo!AW42 -> LIBERADO | AW42: =Calculo!AX42 -> N/A | AX42: =Calculo!K42 -> SOLIC CONTRATO DE ENTREGA | AY42: =Calculo!AY42 -> N/A | AZ42: =Calculo!AZ42 -> N/A
A43: ='Parâmetros'!$A$19 -> Rel. Básico PJ | B43: 519 | C43: 25367 | D43: Oaco | E43: 144536 | F43: 2290 | G43: OK | H43: S | I43: N | J43: N | K43: N | L43: S | M43: S | N43: PR | O43: - | P43: S | Q43: 100 | R43: N | S43: N | T43: N | U43: S | V43: S | W43: N | X43: S | Y43: S | Z43: N | AA43: S | AB43: 35774 | AC43: N | AD43: R$ 37.046.710,00 | AE43: S | AF43: N | AG43: N | AH43: N | AI43: 0 | AJ43: 858 | AK43: INDUSTRIA MISSIATO DE BEBIDAS LTDA | AL43: S | AM43: S | AN43: D | AO43: N/D | AP43: N/D | AR43: Liberado | AS43: 46160 | AT43: =Calculo!AQ43 -> 43 | AU43: =Calculo!AV43 -> SEM-RISCO | AV43: =Calculo!AW43 -> LIBERADO | AW43: =Calculo!AX43 -> N/A | AX43: =Calculo!K43 -> SOLIC CONTRATO DE ENTREGA | AY43: =Calculo!AY43 -> N/A | AZ43: =Calculo!AZ43 -> N/A
A44: ='Parâmetros'!$A$19 -> Rel. Básico PJ | B44: 203 | C44: 25093 | D44: Metalpleno | E44: 144537 | F44: 8039 | G44: OK | H44: S | I44: N | J44: N | K44: N | L44: S | M44: S | N44: SP | O44: - | P44: N | Q44: 100 | R44: N | S44: N | T44: N | U44: S | V44: S | W44: N | X44: S | Y44: N | Z44: S | AA44: S | AB44: 28667 | AC44: N | AD44: R$ 30.000,00 | AE44: S | AF44: N | AG44: N | AH44: N | AI44: 0 | AJ44: 775 | AK44: ESTRELA DE OURO MATERIAIS ELETRICOS E HIDRAULICOS LTDA | AL44: S | AM44: S | AN44: D | AO44: N/D | AP44: N/D | AR44: Liberado | AS44: 46160 | AT44: =Calculo!AQ44 -> 30 | AU44: =Calculo!AV44 -> SEM-RISCO | AV44: =Calculo!AW44 -> LIBERADO | AW44: =Calculo!AX44 -> SOLICITAR PED COMPRA | AX44: =Calculo!K44 -> SOLIC CONTRATO DE ENTREGA | AY44: =Calculo!AY44 -> N/A | AZ44: =Calculo!AZ44 -> N/A
A45: ='Parâmetros'!$A$19 -> Rel. Básico PJ | B45: 204 | C45: 25312 | D45: Metalpleno | E45: 141474 | F45: 7290 | G45: OK | H45: S | I45: N | J45: N | K45: N | L45: S | M45: S | N45: BA | O45: - | P45: N | Q45: 100 | R45: N | S45: S | T45: N | U45: S | V45: S | W45: N | X45: S | Y45: S | Z45: N | AA45: S | AB45: 34709 | AC45: S | AD45: R$ 1.093.350.865,39 | AE45: S | AF45: S | AG45: N | AH45: S | AI45: 150043.54 | AJ45: 727 | AK45: LM TRANSPORTES INTERESTADUAIS SERVICOS E COMERCIO SA | AL45: S | AM45: S | AN45: D | AO45: N/D | AP45: N/D | AR45: Liberado | AS45: 46160 | AT45: =Calculo!AQ45 -> 33 | AU45: =Calculo!AV45 -> SEM-RISCO | AV45: =Calculo!AW45 -> LIBERADO | AW45: =Calculo!AX45 -> SOLICITAR PED COMPRA | AX45: =Calculo!K45 -> SOLIC CONTRATO DE ENTREGA | AY45: =Calculo!AY45 -> N/A | AZ45: =Calculo!AZ45 -> N/A
A46: ='Parâmetros'!$A$19 -> Rel. Básico PJ | B46: 523 | C46: 25299 | D46: Oaco | E46: 022550 | F46: 549 | G46: OK | H46: S | I46: N | J46: N | K46: N | L46: N | M46: S | N46: PR | O46: - | P46: N | Q46: 100 | R46: N | S46: N | T46: N | U46: S | V46: S | W46: N | X46: S | Y46: S | Z46: N | AA46: S | AB46: 40598 | AC46: S | AD46: R$ 230.820.090,44 | AE46: S | AF46: S | AG46: N | AH46: S | AI46: 12003.82 | AJ46: 671 | AK46: SUL IMPORT VEICULOS E SERVICOS SUL SA | AL46: S | AM46: S | AN46: D | AO46: N/D | AP46: N/D | AR46: Liberado | AS46: 46161 | AT46: =Calculo!AQ46 -> 9 | AU46: =Calculo!AV46 -> SEM-RISCO | AV46: =Calculo!AW46 -> LIBERADO | AW46: =Calculo!AX46 -> N/A | AX46: =Calculo!K46 -> N/A | AY46: =Calculo!AY46 -> N/A | AZ46: =Calculo!AZ46 -> N/A
A47: ='Parâmetros'!$A$19 -> Rel. Básico PJ | B47: 205 | C47: 25351 | D47: Metalpleno | E47: 141438 | F47: 3205 | G47: OK | H47: S | I47: N | J47: N | K47: N | L47: S | M47: S | N47: SP | O47: 5 | P47: S | Q47: 100 | R47: N | S47: N | T47: N | U47: S | V47: S | W47: N | X47: S | Y47: S | Z47: N | AA47: S | AB47: 31365 | AC47: N | AD47: R$ 18.600.000,00 | AE47: S | AF47: N | AG47: N | AH47: S | AI47: 1736.18 | AJ47: 393 | AK47: SEMINA INDUSTRIA E COMERCIO LTDA | AL47: S | AM47: S | AN47: D | AO47: N/D | AP47: N/D | AR47: Liberado | AS47: 46162 | AT47: =Calculo!AQ47 -> 23 | AU47: =Calculo!AV47 -> SEM-RISCO | AV47: =Calculo!AW47 -> LIBERADO | AW47: =Calculo!AX47 -> N/A | AX47: =Calculo!K47 -> SOLIC CONTRATO DE ENTREGA | AY47: =Calculo!AY47 -> N/A | AZ47: =Calculo!AZ47 -> N/A
A48: ='Parâmetros'!$A$19 -> Rel. Básico PJ | B48: 208 | C48: 25395 | D48: Metalpleno | E48: 144544 | F48: 4418.2 | G48: OK | H48: S | I48: N | J48: N | K48: N | L48: S | M48: S | N48: SP | O48: - | P48: S | Q48: 100 | R48: N | S48: N | T48: N | U48: S | V48: S | W48: N | X48: S | Y48: N | Z48: N | AA48: S | AB48: 37655 | AC48: S | AD48: R$ 3.000.000,00 | AE48: S | AF48: N | AG48: N | AH48: N | AI48: 0 | AJ48: 775 | AK48: INJEQUALY INDUSTRIA E COMERCIO LTDA | AL48: S | AM48: S | AN48: D | AO48: N/D | AP48: N/D | AR48: Liberado | AS48: 46162 | AT48: =Calculo!AQ48 -> 41 | AU48: =Calculo!AV48 -> SEM-RISCO | AV48: =Calculo!AW48 -> LIBERADO | AW48: =Calculo!AX48 -> N/A | AX48: =Calculo!K48 -> SOLIC CONTRATO DE ENTREGA | AY48: =Calculo!AY48 -> N/A | AZ48: =Calculo!AZ48 -> N/A
A49: ='Parâmetros'!$A$19 -> Rel. Básico PJ | B49: 209 | C49: 243118 | D49: Metalpleno | E49: 144076 | F49: 13720 | G49: OK | H49: S | I49: N | J49: N | K49: N | L49: S | M49: S | N49: SP | O49: - | P49: N | Q49: 100 | R49: N | S49: N | T49: N | U49: S | V49: S | W49: N | X49: S | Y49: N | Z49: N | AA49: S | AB49: 24469 | AC49: N | AE49: S | AF49: S | AG49: N | AH49: S | AI49: 1158674.5 | AJ49: 331 | AK49: ASSOCIACAO SAO LEOPOLDO MANDIC-SL MANDIC | AL49: S | AM49: S | AN49: D | AO49: N/D | AP49: N/D | AR49: Bloqueado | AS49: 46162 | AT49: =Calculo!AQ49 -> -20 | AU49: =Calculo!AV49 -> EMPRESINHA | AV49: =Calculo!AW49 -> VER E-MAIL CORPORATIVO SITE REFERENC COML NFE 3S ALTO VALOR FATURADO | AW49: =Calculo!AX49 -> SOLICITAR PED COMPRA | AX49: =Calculo!K49 -> SOLIC CONTRATO DE ENTREGA | AY49: =Calculo!AY49 -> N/A | AZ49: =Calculo!AZ49 -> N/A
A50: ='Parâmetros'!$A$19 -> Rel. Básico PJ | B50: 528 | C50: 25225 | D50: Oaco | E50: 027891 | F50: 4388 | G50: OK | H50: S | I50: N | J50: N | K50: N | L50: S | M50: S | N50: SP | O50: 5 | P50: S | Q50: 100 | R50: N | S50: N | T50: N | U50: S | V50: S | W50: N | X50: S | Y50: S | Z50: N | AA50: S | AB50: 37771 | AC50: N | AD50: R$ 102.000,00 | AE50: S | AF50: N | AG50: N | AH50: N | AI50: 0 | AJ50: 822 | AK50: LAR CONSTRUCOES E INCORPORACOES LTDA | AL50: S | AM50: S | AN50: D | AO50: N/D | AP50: N/D | AR50: Liberado | AS50: 46162 | AT50: =Calculo!AQ50 -> 46 | AU50: =Calculo!AV50 -> SEM-RISCO | AV50: =Calculo!AW50 -> LIBERADO | AW50: =Calculo!AX50 -> N/A | AX50: =Calculo!K50 -> SOLIC CONTRATO DE ENTREGA | AY50: =Calculo!AY50 -> N/A | AZ50: =Calculo!AZ50 -> N/A
A51: ='Parâmetros'!$A$19 -> Rel. Básico PJ | B51: 531 | C51: 25237 | D51: Oaco | E51: 144163 | F51: 19528 | G51: OK | H51: S | I51: N | J51: N | K51: N | L51: S | M51: S | N51: SP | O51: 5 | P51: N | Q51: 100 | R51: N | S51: S | T51: N | U51: S | V51: S | W51: N | X51: S | Y51: S | Z51: N | AA51: S | AB51: 24379 | AC51: S | AD51: R$ 138.446.361,00 | AE51: S | AF51: S | AG51: N | AH51: S | AI51: 36737.04 | AJ51: 731 | AK51: ATLAS COPCO BRASIL LTDA | AL51: S | AM51: S | AN51: D | AO51: N/D | AP51: N/D | AR51: Liberado | AS51: 46163 | AT51: =Calculo!AQ51 -> 46 | AU51: =Calculo!AV51 -> SEM-RISCO | AV51: =Calculo!AW51 -> LIBERADO | AW51: =Calculo!AX51 -> SOLICITAR PED COMPRA | AX51: =Calculo!K51 -> SOLIC CONTRATO DE ENTREGA | AY51: =Calculo!AY51 -> N/A | AZ51: =Calculo!AZ51 -> N/A
A52: ='Parâmetros'!$A$19 -> Rel. Básico PJ | B52: 212 | C52: 25424 | D52: Metalpleno | E52: 030585 | F52: 6819 | G52: OK | H52: S | I52: N | J52: N | K52: N | L52: S | M52: S | N52: SP | O52: 5 | P52: S | Q52: 100 | R52: N | S52: S | T52: N | U52: S | V52: S | W52: N | X52: S | Y52: S | Z52: N | AA52: S | AB52: 26064 | AC52: N | AE52: S | AF52: N | AG52: N | AH52: N | AI52: 0 | AJ52: 799 | AK52: MUSEU DE ARTE DE SAO PAULO ASSIS CHATEAUBRIAND-MASP | AL52: S | AM52: S | AN52: D | AO52: N/D | AP52: N/D | AR52: Liberado | AS52: 46164 | AT52: =Calculo!AQ52 -> 45 | AU52: =Calculo!AV52 -> SEM-RISCO | AV52: =Calculo!AW52 -> LIBERADO | AW52: =Calculo!AX52 -> SOLICITAR PED COMPRA | AX52: =Calculo!K52 -> SOLIC CONTRATO DE ENTREGA | AY52: =Calculo!AY52 -> N/A | AZ52: =Calculo!AZ52 -> N/A
A53: ='Parâmetros'!$A$19 -> Rel. Básico PJ | B53: 542 | C53: 25372 | D53: Oaco | E53: 143202 | F53: 2511 | G53: OK | H53: S | I53: N | J53: N | K53: N | L53: S | M53: S | N53: BA | O53: 5 | P53: S | Q53: 100 | R53: N | S53: S | T53: N | U53: S | V53: S | W53: S | X53: S | Y53: S | Z53: S | AA53: S | AB53: 26172 | AC53: S | AD53: R$ 140.000.000,00 | AE53: S | AF53: S | AG53: N | AH53: S | AI53: 1145924.2 | AJ53: 671 | AK53: RAMIRO CAMPELO COMERCIO DE ATIVIDADES LTDA | AL53: S | AM53: S | AN53: D | AO53: N/D | AP53: N/D | AR53: Liberado | AS53: 46168 | AT53: =Calculo!AQ53 -> 16 | AU53: =Calculo!AV53 -> SEM-RISCO | AV53: =Calculo!AW53 -> LIBERADO | AW53: =Calculo!AX53 -> N/A | AX53: =Calculo!K53 -> SOLIC CONTRATO DE ENTREGA | AY53: =Calculo!AY53 -> N/A | AZ53: =Calculo!AZ53 -> N/A
A54: ='Parâmetros'!$A$19 -> Rel. Básico PJ | B54: 217 | C54: 25421 | D54: Metalpleno | E54: 144562 | F54: 7475 | G54: OK | H54: S | I54: N | J54: N | K54: N | L54: S | M54: S | N54: PR | O54: - | P54: N | Q54: 100 | R54: N | S54: S | T54: N | U54: S | V54: S | W54: N | X54: S | Y54: S | Z54: N | AA54: S | AB54: 26591 | AC54: N | AD54: R$ 41.388.384,00 | AE54: S | AF54: N | AG54: N | AH54: N | AI54: 0 | AJ54: 797 | AK54: HELISUL TAXI AEREO LTDA | AL54: S | AM54: S | AN54: D | AO54: N/D | AP54: N/D | AR54: Liberado | AS54: 46169 | AT54: =Calculo!AQ54 -> 59 | AU54: =Calculo!AV54 -> SEM-RISCO | AV54: =Calculo!AW54 -> LIBERADO | AW54: =Calculo!AX54 -> SOLICITAR PED COMPRA | AX54: =Calculo!K54 -> SOLIC CONTRATO DE ENTREGA | AY54: =Calculo!AY54 -> N/A | AZ54: =Calculo!AZ54 -> N/A
A55: ='Parâmetros'!$A$19 -> Rel. Básico PJ | B55: 218 | C55: 25475 | D55: Metalpleno | E55: 144378 | F55: 14402.56 | G55: OK | H55: S | I55: N | J55: N | K55: N | L55: S | M55: N | N55: PR | O55: 0 | P55: S | Q55: 100 | R55: N | S55: S | T55: N | U55: S | V55: S | W55: N | X55: S | Y55: S | Z55: N | AA55: S | AB55: 37245 | AC55: N | AD55: R$ 16.106.000,00 | AE55: S | AF55: N | AG55: N | AH55: N | AI55: 0 | AJ55: 552 | AK55: SCHWAN COSMETICS DO BRASIL LTDA | AL55: S | AM55: S | AN55: D | AO55: N/D | AP55: N/D | AR55: Liberado | AS55: 46169 | AT55: =Calculo!AQ55 -> 43 | AU55: =Calculo!AV55 -> SEM-RISCO | AV55: =Calculo!AW55 -> LIBERADO | AW55: =Calculo!AX55 -> SOLICITAR PED COMPRA | AX55: =Calculo!K55 -> SOLIC CONTRATO DE ENTREGA | AY55: =Calculo!AY55 -> CHECAGEM REVERSA | AZ55: =Calculo!AZ55 -> N/A
A56: ='Parâmetros'!$A$19 -> Rel. Básico PJ | B56: 220 | C56: 25493 | D56: Metalpleno | E56: 144160 | F56: 43428 | G56: OK | H56: S | I56: N | J56: N | K56: N | L56: S | M56: N | N56: MG | O56: 0 | P56: - | Q56: 100 | R56: N | S56: S | T56: N | U56: S | V56: S | W56: N | X56: S | Y56: S | Z56: N | AA56: S | AB56: 45125 | AC56: N | AD56: R$ 150.000,00 | AE56: S | AF56: N | AG56: N | AH56: N | AI56: 0 | AJ56: 699 | AK56: MD'ORE FERRAMENTAS E FIXACAO LTDA | AL56: S | AM56: S | AN56: D | AO56: N/D | AP56: N/D | AR56: Liberado | AS56: 46170 | AT56: =Calculo!AQ56 -> 19 | AU56: =Calculo!AV56 -> SEM-RISCO | AV56: =Calculo!AW56 -> LIBERADO | AW56: =Calculo!AX56 -> SOLICITAR PED COMPRA | AX56: =Calculo!K56 -> SOLIC CONTRATO DE ENTREGA | AY56: =Calculo!AY56 -> CHECAGEM REVERSA | AZ56: =Calculo!AZ56 -> N/A
A57: ='Parâmetros'!$A$19 -> Rel. Básico PJ | B57: 549 | C57: 23969 | D57: Oaco | E57: 144566 | F57: 13452 | G57: OK | H57: S | I57: N | J57: N | K57: N | L57: S | M57: S | N57: SP | O57: 5 | P57: S | Q57: 100 | R57: N | S57: N | T57: N | U57: S | V57: S | W57: N | X57: S | Y57: S | Z57: N | AA57: S | AB57: 37330 | AC57: S | AD57: R$ 2.091.602.062,00 | AE57: S | AF57: N | AG57: N | AH57: S | AI57: 87342.22 | AJ57: 757 | AK57: FISERV DO BRASIL INSTITUICAO DE PAGAMENTO LTDA | AL57: S | AM57: S | AN57: D | AO57: N/D | AP57: N/D | AR57: Liberado | AS57: 46170 | AT57: =Calculo!AQ57 -> 26 | AU57: =Calculo!AV57 -> SEM-RISCO | AV57: =Calculo!AW57 -> LIBERADO | AW57: =Calculo!AX57 -> SOLICITAR PED COMPRA | AX57: =Calculo!K57 -> SOLIC CONTRATO DE ENTREGA | AY57: =Calculo!AY57 -> N/A | AZ57: =Calculo!AZ57 -> N/A
A58: ='Parâmetros'!$A$19 -> Rel. Básico PJ | B58: 550 | C58: 25502 | D58: Oaco | E58: 007661 | F58: 5806 | G58: OK | H58: S | I58: N | J58: N | K58: N | L58: S | M58: S | N58: SP | O58: 5 | P58: S | Q58: 100 | R58: N | S58: N | T58: N | U58: S | V58: S | W58: N | X58: S | Y58: S | Z58: N | AA58: S | AB58: 37330 | AC58: S | AD58: R$ 2.091.602.062,00 | AE58: S | AF58: N | AG58: N | AH58: S | AI58: 87342.22 | AJ58: 757 | AK58: FISERV DO BRASIL INSTITUICAO DE PAGAMENTO LTDA | AL58: S | AM58: S | AN58: D | AO58: N/D | AP58: N/D | AR58: Liberado | AS58: 46171 | AT58: =Calculo!AQ58 -> 26 | AU58: =Calculo!AV58 -> SEM-RISCO | AV58: =Calculo!AW58 -> LIBERADO | AW58: =Calculo!AX58 -> SOLICITAR PED COMPRA | AX58: =Calculo!K58 -> SOLIC CONTRATO DE ENTREGA | AY58: =Calculo!AY58 -> N/A | AZ58: =Calculo!AZ58 -> N/A
A59: ='Parâmetros'!$A$19 -> Rel. Básico PJ | B59: 222 | C59: 25448 | D59: Metalpleno | E59: 144568 | F59: 13198 | G59: OK | H59: S | I59: N | J59: N | K59: N | L59: S | M59: S | N59: SP | O59: - | P59: N | Q59: 100 | R59: N | S59: N | T59: N | U59: S | V59: S | W59: N | X59: S | Y59: S | Z59: N | AA59: S | AB59: 41380 | AC59: S | AD59: R$ 883.547.058,00 | AE59: S | AF59: N | AG59: N | AH59: S | AI59: 13904.54 | AJ59: 757 | AK59: SILGAN DISPENSING SYSTEMS DO BRASIL LTDA | AL59: S | AM59: S | AN59: D | AO59: N/D | AP59: N/D | AR59: Liberado | AS59: 46171 | AT59: =Calculo!AQ59 -> 29 | AU59: =Calculo!AV59 -> SEM-RISCO | AV59: =Calculo!AW59 -> LIBERADO | AW59: =Calculo!AX59 -> SOLICITAR PED COMPRA | AX59: =Calculo!K59 -> SOLIC CONTRATO DE ENTREGA | AY59: =Calculo!AY59 -> N/A | AZ59: =Calculo!AZ59 -> N/A
A60: ='Parâmetros'!$A$19 -> Rel. Básico PJ | B60: 224 | C60: 24998 | D60: Metalpleno | E60: 144570 | F60: 6822 | G60: OK | H60: S | I60: N | J60: N | K60: N | L60: S | M60: S | N60: SP | O60: - | P60: S | Q60: 100 | R60: N | S60: N | T60: N | U60: S | V60: S | W60: S | X60: S | Y60: S | Z60: N | AA60: S | AB60: 41142 | AC60: N | AD60: 3779963 | AE60: S | AF60: S | AG60: N | AH60: N | AI60: 575 | AJ60: 757 | AK60: PETFIVE BRANDS BRASIL S.A | AL60: S | AM60: S | AN60: D | AO60: N/D | AP60: N/D | AR60: Liberado | AS60: 46174 | AT60: =Calculo!AQ60 -> 21 | AU60: =Calculo!AV60 -> SEM-RISCO | AV60: =Calculo!AW60 -> LIBERADO | AW60: =Calculo!AX60 -> SOLICITAR PED COMPRA | AX60: =Calculo!K60 -> SOLIC CONTRATO DE ENTREGA | AY60: =Calculo!AY60 -> N/A | AZ60: =Calculo!AZ60 -> N/A
A61: ='Parâmetros'!$A$19 -> Rel. Básico PJ | B61: 560 | C61: 25430 | D61: Metalpleno | E61: 036273 | F61: 12540 | G61: OK | H61: S | I61: N | J61: S | K61: N | L61: N | M61: S | N61: PR | O61: 5 | P61: S | Q61: 100 | R61: N | S61: S | T61: N | U61: S | V61: S | W61: N | X61: S | Y61: S | Z61: N | AA61: S | AB61: 41558 | AC61: N | AD61: R$ 202.394.961,06 | AE61: S | AF61: S | AG61: N | AH61: S | AI61: 285856.34 | AJ61: 791 | AK61: MADERO INDUSTRIA E COMERCIO S.A | AL61: S | AM61: S | AN61: D | AO61: N/D | AP61: N/D | AR61: Liberado | AS61: 46175 | AT61: =Calculo!AQ61 -> 9 | AU61: =Calculo!AV61 -> SEM-RISCO | AV61: =Calculo!AW61 -> LIBERADO | AW61: =Calculo!AX61 -> SOLICITAR PED COMPRA | AX61: =Calculo!K61 -> N/A | AY61: =Calculo!AY61 -> N/A | AZ61: =Calculo!AZ61 -> N/A
A62: ='Parâmetros'!$A$19 -> Rel. Básico PJ | B62: 228 | C62: 25534 | D62: Metalpleno | E62: 068591 | F62: 7336 | G62: OK | H62: S | I62: N | J62: N | K62: N | L62: S | M62: S | N62: SP | O62: 5 | P62: N | Q62: 100 | R62: N | S62: S | T62: N | U62: S | V62: S | W62: N | X62: S | Y62: S | Z62: N | AA62: S | AB62: 44309 | AC62: N | AD62: R$ 1.252.880,00 | AE62: S | AF62: N | AG62: N | AH62: S | AI62: 2333.48 | AJ62: 548 | AK62: 55 FABRICA DE MOVEIS LTDA | AL62: S | AM62: N | AN62: D | AO62: N/D | AP62: N/D | AR62: Liberado | AS62: 46175 | AT62: =Calculo!AQ62 -> 19 | AU62: =Calculo!AV62 -> SEM-RISCO | AV62: =Calculo!AW62 -> LIBERADO | AW62: =Calculo!AX62 -> SOLICITAR PED COMPRA | AX62: =Calculo!K62 -> SOLIC CONTRATO DE ENTREGA | AY62: =Calculo!AY62 -> N/A | AZ62: =Calculo!AZ62 -> N/A
A63: ='Parâmetros'!$A$19 -> Rel. Básico PJ | B63: 231 | C63: 25132 | D63: Metalpleno | E63: 144579 | F63: 7418 | G63: OK | H63: S | I63: N | J63: N | K63: N | L63: S | M63: S | N63: RS | O63: 5 | P63: S | Q63: 100 | R63: N | S63: N | T63: N | U63: S | V63: S | W63: N | X63: S | Y63: S | Z63: N | AA63: S | AB63: 27848 | AC63: S | AD63: R$ 1.046.458.877,87 | AE63: S | AF63: S | AG63: N | AH63: S | AI63: 202466.03 | AJ63: 727 | AK63: DIMED SA DISTRIBUIDORA DE MEDICAMENTOS | AL63: S | AM63: S | AN63: D | AO63: N/D | AP63: N/D | AR63: Liberado | AS63: 46176 | AT63: =Calculo!AQ63 -> 24 | AU63: =Calculo!AV63 -> SEM-RISCO | AV63: =Calculo!AW63 -> LIBERADO | AW63: =Calculo!AX63 -> SOLICITAR PED COMPRA | AX63: =Calculo!K63 -> SOLIC CONTRATO DE ENTREGA | AY63: =Calculo!AY63 -> N/A | AZ63: =Calculo!AZ63 -> N/A
A64: ='Parâmetros'!$A$19 -> Rel. Básico PJ | B64: 232 | C64: 25219 | D64: Metalpleno | E64: 144580 | F64: 7350 | G64: OK | H64: S | I64: N | J64: N | K64: N | L64: S | M64: S | N64: PR | O64: 5 | P64: S | Q64: 100 | R64: N | S64: N | T64: N | U64: S | V64: S | W64: N | X64: S | Y64: S | Z64: N | AA64: S | AB64: 27848 | AC64: S | AD64: R$ 1.046.458.877,87 | AE64: S | AF64: S | AG64: N | AH64: S | AI64: 202466.03 | AJ64: 727 | AK64: DIMED SA DISTRIBUIDORA DE MEDICAMENTOS | AL64: S | AM64: S | AN64: D | AO64: N/D | AP64: N/D | AR64: Liberado | AS64: 46176 | AT64: =Calculo!AQ64 -> 24 | AU64: =Calculo!AV64 -> SEM-RISCO | AV64: =Calculo!AW64 -> LIBERADO | AW64: =Calculo!AX64 -> SOLICITAR PED COMPRA | AX64: =Calculo!K64 -> SOLIC CONTRATO DE ENTREGA | AY64: =Calculo!AY64 -> N/A | AZ64: =Calculo!AZ64 -> N/A
A65: ='Parâmetros'!$A$19 -> Rel. Básico PJ | B65: 1873 | C65: 11678 | D65: GsiBW | E65: 011678 | F65: 906 | G65: OK | H65: S | I65: N | J65: N | K65: N | L65: N | M65: N | N65: SP | O65: 0 | P65: N | Q65: 100 | R65: N | S65: S | T65: S | U65: S | V65: S | W65: N | X65: S | Y65: S | Z65: N | AA65: S | AB65: 24596 | AC65: N | AE65: S | AF65: S | AG65: N | AH65: N | AI65: 5682788.9 | AJ65: 643 | AK65: MARCHESAN IMPLEMENTOS E MAQUINAS AGRICOLAS TATU SA | AL65: S | AM65: S | AN65: D | AO65: N/D | AP65: N/D | AR65: Liberado | AS65: 46181 | AT65: =Calculo!AQ65 -> 31 | AU65: =Calculo!AV65 -> SEM-RISCO | AV65: =Calculo!AW65 -> LIBERADO | AW65: =Calculo!AX65 -> N/A | AX65: =Calculo!K65 -> N/A | AY65: =Calculo!AY65 -> CHECAGEM REVERSA | AZ65: =Calculo!AZ65 -> N/A
A66: ='Parâmetros'!$A$19 -> Rel. Básico PJ | B66: 233 | C66: 25551 | D66: Metalpleno | E66: 144585 | F66: 7165 | G66: OK | H66: S | I66: S | J66: N | K66: N | L66: S | M66: S | N66: MG | O66: - | P66: N | Q66: 100 | R66: N | S66: N | T66: N | U66: S | V66: S | W66: N | X66: S | Y66: S | Z66: N | AA66: S | AB66: 42165 | AC66: N | AD66: R$ 20.000,00 | AE66: S | AF66: N | AG66: N | AH66: N | AI66: 0 | AJ66: 542 | AK66: AMBAR AUTOMACAO LTDA | AL66: S | AM66: S | AN66: D | AO66: N/D | AP66: N/D | AR66: Liberado | AS66: 46181 | AT66: =Calculo!AQ66 -> 51 | AU66: =Calculo!AV66 -> SEM-RISCO | AV66: =Calculo!AW66 -> LIBERADO | AW66: =Calculo!AX66 -> SOLICITAR PED COMPRA | AX66: =Calculo!K66 -> SOLIC CONTRATO DE ENTREGA | AY66: =Calculo!AY66 -> N/A | AZ66: =Calculo!AZ66 -> N/A
A67: ='Parâmetros'!$A$19 -> Rel. Básico PJ | B67: 234 | C67: 25397 | D67: Metalpleno | E67: 144586 | F67: 21987 | G67: OK | H67: S | I67: N | J67: N | K67: N | L67: S | M67: S | N67: DF | O67: - | P67: S | Q67: 100 | R67: N | S67: S | T67: N | U67: S | V67: S | W67: N | X67: S | Y67: S | Z67: N | AA67: S | AB67: 31827 | AC67: S | AD67: R$ 105.579.160,85 | AE67: S | AF67: S | AG67: N | AH67: S | AI67: 402881.44 | AJ67: 727 | AK67: SAMEDIL-SERVICOS DE ATENDIMENTO MEDICO SA | AL67: S | AM67: S | AN67: D | AO67: N/D | AP67: N/D | AR67: Liberado | AS67: 46182 | AT67: =Calculo!AQ67 -> 25 | AU67: =Calculo!AV67 -> SEM-RISCO | AV67: =Calculo!AW67 -> LIBERADO | AW67: =Calculo!AX67 -> SOLICITAR PED COMPRA | AX67: =Calculo!K67 -> SOLIC CONTRATO DE ENTREGA | AY67: =Calculo!AY67 -> N/A | AZ67: =Calculo!AZ67 -> N/A
A68: ='Parâmetros'!$A$19 -> Rel. Básico PJ | B68: - | C68: - | D68: Metalpleno | E68: - | F68: 12804 | G68: OK | H68: S | I68: N | J68: N | K68: N | L68: S | M68: S | N68: SP | O68: 5 | P68: N | Q68: 100 | R68: N | S68: N | T68: N | U68: S | V68: S | W68: N | X68: S | Y68: S | Z68: N | AA68: S | AB68: 42520 | AC68: N | AD68: R$ 10.511.211,00 | AE68: S | AF68: S | AG68: N | AH68: S | AI68: 2628.56 | AJ68: 773 | AK68: ECOTAUBATE AMBIENTAL SA | AL68: S | AM68: S | AN68: D | AO68: N/D | AP68: N/D | AQ68: Pré-análise Andrea | AR68: Liberado | AS68: 46182 | AT68: =Calculo!AQ68 -> 21 | AU68: =Calculo!AV68 -> SEM-RISCO | AV68: =Calculo!AW68 -> LIBERADO | AW68: =Calculo!AX68 -> SOLICITAR PED COMPRA | AX68: =Calculo!K68 -> SOLIC CONTRATO DE ENTREGA | AY68: =Calculo!AY68 -> N/A | AZ68: =Calculo!AZ68 -> N/A
A69: ='Parâmetros'!$A$19 -> Rel. Básico PJ | B69: 237 | C69: 25173 | D69: Metalpleno | E69: 144589 | F69: 4305 | G69: OK | H69: S | I69: N | J69: N | K69: N | L69: S | M69: S | N69: SP | O69: 5 | P69: S | Q69: 100 | R69: N | S69: N | T69: N | U69: S | V69: S | W69: N | X69: S | Y69: S | Z69: N | AA69: S | AB69: 28633 | AC69: N | AD69: R$ 5.460.000,00 | AE69: S | AF69: S | AG69: N | AH69: S | AI69: 34478.86 | AJ69: 900 | AK69: FRIGOSTRELLA DO BRASIL IND DE REFRIGERACAO LTDA | AL69: S | AM69: S | AN69: D | AO69: N/D | AP69: N/D | AR69: Liberado | AS69: 46182 | AT69: =Calculo!AQ69 -> 19 | AU69: =Calculo!AV69 -> SEM-RISCO | AV69: =Calculo!AW69 -> LIBERADO | AW69: =Calculo!AX69 -> N/A | AX69: =Calculo!K69 -> SOLIC CONTRATO DE ENTREGA | AY69: =Calculo!AY69 -> N/A | AZ69: =Calculo!AZ69 -> N/A
A70: ='Parâmetros'!$A$19 -> Rel. Básico PJ | B70: 1874 | C70: 25585 | D70: Metalpleno | E70: 144590 | F70: 689 | G70: OK | H70: S | I70: N | J70: N | K70: N | L70: S | M70: S | N70: DF | O70: - | P70: S | Q70: 100 | R70: N | S70: S | T70: N | U70: S | V70: S | W70: N | X70: S | Y70: S | Z70: N | AA70: S | AB70: 25590 | AC70: S | AD70: R$ 786.865.196,00 | AE70: S | AF70: S | AG70: N | AH70: S | AI70: 193830.16 | AJ70: 727 | AK70: PROSEGUR BRASIL SA TRANSPORTADORA DE VALORES E SEGURAN | AL70: S | AM70: S | AN70: D | AO70: N/D | AP70: N/D | AR70: Liberado | AS70: 46182 | AT70: =Calculo!AQ70 -> 33 | AU70: =Calculo!AV70 -> SEM-RISCO | AV70: =Calculo!AW70 -> LIBERADO | AW70: =Calculo!AX70 -> N/A | AX70: =Calculo!K70 -> SOLIC CONTRATO DE ENTREGA | AY70: =Calculo!AY70 -> N/A | AZ70: =Calculo!AZ70 -> N/A
A71: ='Parâmetros'!$A$19 -> Rel. Básico PJ | B71: 571 | C71: 25577 | D71: Oaco | E71: 144591 | F71: 8921 | G71: OK | H71: S | I71: N | J71: N | K71: N | L71: S | M71: S | N71: PR | O71: - | P71: N | Q71: 100 | R71: N | S71: S | T71: N | U71: S | V71: S | W71: N | X71: S | Y71: S | Z71: N | AA71: S | AB71: 39129 | AC71: S | AD71: R$ 192.106.977,00 | AE71: S | AF71: S | AG71: N | AH71: S | AI71: 134991.76 | AJ71: 406 | AK71: MSC MEDITERRANEAN LOGISTICA LTDA | AL71: S | AM71: S | AN71: D | AO71: N/D | AP71: N/D | AR71: Liberado | AS71: 46183 | AT71: =Calculo!AQ71 -> 17 | AU71: =Calculo!AV71 -> SEM-RISCO | AV71: =Calculo!AW71 -> LIBERADO | AW71: =Calculo!AX71 -> SOLICITAR PED COMPRA | AX71: =Calculo!K71 -> SOLIC CONTRATO DE ENTREGA | AY71: =Calculo!AY71 -> N/A | AZ71: =Calculo!AZ71 -> N/A
A72: ='Parâmetros'!$A$19 -> Rel. Básico PJ | B72: 572 | C72: 25596 | D72: Oaco | E72: 144591 | F72: 4247 | G72: OK | H72: S | I72: N | J72: N | K72: N | L72: S | M72: S | N72: PR | O72: - | P72: N | Q72: 100 | R72: N | S72: S | T72: N | U72: S | V72: S | W72: N | X72: S | Y72: S | Z72: N | AA72: S | AB72: 39129 | AC72: S | AD72: R$ 192.106.977,00 | AE72: S | AF72: S | AG72: N | AH72: S | AI72: 134991.76 | AJ72: 406 | AK72: MSC MEDITERRANEAN LOGISTICA LTDA | AL72: S | AM72: S | AN72: D | AO72: N/D | AP72: N/D | AR72: Liberado | AS72: 46183 | AT72: =Calculo!AQ72 -> 17 | AU72: =Calculo!AV72 -> SEM-RISCO | AV72: =Calculo!AW72 -> LIBERADO | AW72: =Calculo!AX72 -> N/A | AX72: =Calculo!K72 -> SOLIC CONTRATO DE ENTREGA | AY72: =Calculo!AY72 -> N/A | AZ72: =Calculo!AZ72 -> N/A
A73: ='Parâmetros'!$A$19 -> Rel. Básico PJ | B73: 238 | C73: 25236 | D73: Metalpleno | E73: 144592 | F73: 4103.1 | G73: OK | H73: S | I73: N | J73: N | K73: N | L73: S | M73: N | N73: SP | O73: 0 | P73: S | Q73: 100 | R73: N | S73: N | T73: N | U73: S | V73: S | W73: N | X73: S | Y73: S | Z73: N | AA73: S | AB73: 40259 | AC73: N | AD73: R$ 30.000.000,00 | AE73: S | AF73: S | AG73: N | AH73: N | AI73: 11936.49 | AJ73: 435 | AK73: ALUCOMAXX BRASIL INDUSTRIA E COMERCIO DE REVESTIMENTO | AL73: S | AM73: S | AN73: D | AO73: N/D | AP73: N/D | AR73: Liberado | AS73: 46184 | AT73: =Calculo!AQ73 -> 7 | AU73: =Calculo!AV73 -> SEM-RISCO | AV73: =Calculo!AW73 -> LIBERADO | AW73: =Calculo!AX73 -> N/A | AX73: =Calculo!K73 -> SOLIC CONTRATO DE ENTREGA | AY73: =Calculo!AY73 -> CHECAGEM REVERSA | AZ73: =Calculo!AZ73 -> N/A
A74: ='Parâmetros'!$A$19 -> Rel. Básico PJ | B74: 240 | C74: 25609 | D74: Metalpleno | E74: 020698 | F74: 3145 | G74: OK | H74: S | I74: N | J74: N | K74: N | L74: S | M74: S | N74: SP | O74: 5 | P74: N | Q74: 100 | R74: N | S74: N | T74: N | U74: S | V74: S | W74: N | X74: S | Y74: S | Z74: N | AA74: S | AB74: 42083 | AC74: N | AD74: R$ 95.400,00 | AE74: S | AF74: N | AG74: N | AH74: N | AI74: 0 | AJ74: 409 | AK74: MS SUPRIMENTOS LTDA | AL74: S | AM74: S | AN74: D | AO74: N/D | AP74: N/D | AR74: Liberado | AS74: 46184 | AT74: =Calculo!AQ74 -> 30 | AU74: =Calculo!AV74 -> SEM-RISCO | AV74: =Calculo!AW74 -> LIBERADO | AW74: =Calculo!AX74 -> N/A | AX74: =Calculo!K74 -> SOLIC CONTRATO DE ENTREGA | AY74: =Calculo!AY74 -> N/A | AZ74: =Calculo!AZ74 -> N/A
A75: ='Parâmetros'!$A$19 -> Rel. Básico PJ | B75: 241 | C75: 25472 | D75: Metalpleno | E75: 144594 | F75: 7691 | G75: OK | H75: S | I75: N | J75: N | K75: N | L75: S | M75: S | N75: SP | O75: 5 | P75: S | Q75: 100 | R75: N | S75: N | T75: N | U75: S | V75: S | W75: N | X75: S | Y75: S | Z75: N | AA75: S | AB75: 25366 | AC75: S | AD75: R$169.466.620,00 | AE75: S | AF75: N | AG75: N | AH75: S | AI75: 1985.8 | AJ75: 344 | AK75: GREIF EMBALAGENS INDUSTRIAIS DO BRASIL LTDA | AL75: S | AM75: S | AN75: D | AO75: N/D | AP75: N/D | AR75: Liberado | AS75: 46185 | AT75: =Calculo!AQ75 -> 28 | AU75: =Calculo!AV75 -> SEM-RISCO | AV75: =Calculo!AW75 -> LIBERADO | AW75: =Calculo!AX75 -> SOLICITAR PED COMPRA | AX75: =Calculo!K75 -> SOLIC CONTRATO DE ENTREGA | AY75: =Calculo!AY75 -> N/A | AZ75: =Calculo!AZ75 -> N/A
A76: ='Parâmetros'!$A$19 -> Rel. Básico PJ | B76: 577 | C76: 25589 | D76: Oaco | E76: 027891 | F76: 1040 | G76: OK | H76: S | I76: N | J76: N | K76: N | L76: N | M76: S | N76: SP | O76: 5 | P76: S | Q76: 100 | R76: S | S76: S | T76: N | U76: S | V76: S | W76: N | X76: S | Y76: S | Z76: N | AA76: S | AB76: 37771 | AC76: N | AD76: R$ 102.000,00 | AE76: S | AF76: N | AG76: N | AH76: N | AI76: 0 | AJ76: 822 | AK76: LAR CONSTRUCOES E INCORPORACOES LTDA | AL76: S | AM76: S | AN76: D | AO76: N/D | AP76: N/D | AR76: Liberado | AS76: 46188 | AT76: =Calculo!AQ76 -> 54 | AU76: =Calculo!AV76 -> SEM-RISCO | AV76: =Calculo!AW76 -> LIBERADO | AW76: =Calculo!AX76 -> N/A | AX76: =Calculo!K76 -> N/A | AY76: =Calculo!AY76 -> N/A | AZ76: =Calculo!AZ76 -> N/A
A77: ='Parâmetros'!$A$19 -> Rel. Básico PJ | B77: 242 | C77: 25617 | D77: Metalpleno | E77: 144071 | F77: 3045 | G77: OK | H77: S | I77: N | J77: N | K77: N | L77: N | M77: N | N77: SP | O77: 0 | P77: S | Q77: 100 | R77: N | S77: S | T77: N | U77: S | V77: S | W77: N | X77: S | Y77: S | Z77: N | AA77: S | AB77: 34612 | AC77: S | AD77: R$ 1.134.339.481,70 | AE77: S | AF77: S | AG77: N | AH77: S | AI77: 961326.61 | AJ77: 603 | AK77: ARMAC LOCACAO, LOGISTICA E SERVICOS SA | AL77: S | AM77: S | AN77: D | AO77: N/D | AP77: N/D | AR77: Liberado | AS77: 46188 | AT77: =Calculo!AQ77 -> 21 | AU77: =Calculo!AV77 -> SEM-RISCO | AV77: =Calculo!AW77 -> LIBERADO | AW77: =Calculo!AX77 -> N/A | AX77: =Calculo!K77 -> N/A | AY77: =Calculo!AY77 -> CHECAGEM REVERSA | AZ77: =Calculo!AZ77 -> N/A
A78: ='Parâmetros'!$A$19 -> Rel. Básico PJ | B78: 579 | C78: 24736 | D78: Oaco | E78: 144598 | F78: 4239 | G78: OK | H78: S | I78: N | J78: N | K78: N | L78: S | M78: S | N78: SP | O78: 5 | P78: S | Q78: 100 | R78: N | S78: N | T78: N | U78: S | V78: S | W78: N | X78: S | Y78: S | Z78: N | AA78: S | AB78: 22666 | AC78: N | AD78: R$ 24.730.000,00 | AE78: S | AF78: S | AG78: N | AH78: N | AI78: 1110 | AJ78: 512 | AK78: MACRON INDUSTRIA GRAFICA LTDA | AL78: S | AM78: S | AN78: D | AO78: N/D | AP78: N/D | AR78: Liberado | AS78: 46189 | AT78: =Calculo!AQ78 -> 40 | AU78: =Calculo!AV78 -> SEM-RISCO | AV78: =Calculo!AW78 -> LIBERADO | AW78: =Calculo!AX78 -> N/A | AX78: =Calculo!K78 -> SOLIC CONTRATO DE ENTREGA | AY78: =Calculo!AY78 -> N/A | AZ78: =Calculo!AZ78 -> N/A
A79: ='Parâmetros'!$A$19 -> Rel. Básico PJ | B79: 580 | C79: 25581 | D79: Oaco | E79: 139192 | F79: 1070 | G79: OK | H79: S | I79: N | J79: N | K79: N | L79: N | M79: S | N79: GO | O79: - | P79: N | Q79: 100 | R79: N | S79: S | T79: S | U79: S | V79: S | W79: S | X79: S | Y79: S | Z79: N | AA79: S | AB79: 31876 | AC79: S | AD79: R$ 370.483.000,00 | AE79: S | AF79: N | AG79: N | AH79: N | AI79: 0 | AJ79: 651 | AK79: ARAGUAIA SA | AL79: S | AM79: S | AN79: D | AO79: N/D | AP79: N/D | AR79: Liberado | AS79: 46189 | AT79: =Calculo!AQ79 -> 77 | AU79: =Calculo!AV79 -> SEM-RISCO | AV79: =Calculo!AW79 -> LIBERADO | AW79: =Calculo!AX79 -> N/A | AX79: =Calculo!K79 -> N/A | AY79: =Calculo!AY79 -> N/A | AZ79: =Calculo!AZ79 -> N/A
A80: ='Parâmetros'!$A$19 -> Rel. Básico PJ | B80: 588 | C80: 25666 | D80: Oaco | E80: 144604 | F80: 2899 | G80: OK | H80: S | I80: N | J80: N | K80: N | L80: S | M80: S | N80: SP | O80: 5 | P80: S | Q80: 100 | R80: N | S80: N | T80: N | U80: S | V80: S | W80: N | X80: S | Y80: S | Z80: N | AA80: S | AB80: 26967 | AC80: N | AD80: R$ 597.430.629,00 | AE80: S | AF80: S | AG80: N | AH80: S | AI80: 73178.38 | AJ80: 590 | AK80: GRABER SEGURANCA LTDA | AL80: S | AM80: S | AN80: D | AO80: N/D | AP80: N/D | AR80: Liberado | AS80: 46190 | AT80: =Calculo!AQ80 -> 15 | AU80: =Calculo!AV80 -> SEM-RISCO | AV80: =Calculo!AW80 -> LIBERADO | AW80: =Calculo!AX80 -> N/A | AX80: =Calculo!K80 -> SOLIC CONTRATO DE ENTREGA | AY80: =Calculo!AY80 -> N/A | AZ80: =Calculo!AZ80 -> N/A
A81: ='Parâmetros'!$A$19 -> Rel. Básico PJ | B81: 245 | C81: 24866 | D81: Metalpleno | E81: 144605 | F81: 4771 | G81: OK | H81: S | I81: N | J81: N | K81: N | L81: S | M81: S | N81: MG | O81: - | P81: N | Q81: 100 | R81: N | S81: N | T81: N | U81: S | V81: S | W81: N | X81: S | Y81: S | Z81: N | AA81: S | AB81: 45079 | AC81: S | AD81: R$ 36.624.684,00 | AE81: S | AF81: N | AG81: N | AH81: N | AI81: 0 | AJ81: 511 | AK81: BEONE MEDICINES BRASIL LTDA | AL81: S | AM81: S | AN81: D | AO81: N/D | AP81: N/D | AR81: Liberado | AS81: 46190 | AT81: =Calculo!AQ81 -> 34 | AU81: =Calculo!AV81 -> SEM-RISCO | AV81: =Calculo!AW81 -> LIBERADO | AW81: =Calculo!AX81 -> N/A | AX81: =Calculo!K81 -> SOLIC CONTRATO DE ENTREGA | AY81: =Calculo!AY81 -> N/A | AZ81: =Calculo!AZ81 -> N/A
A82: ='Parâmetros'!$A$19 -> Rel. Básico PJ | B82: 246 | C82: 25648 | D82: Metalpleno | E82: 144607 | F82: 4333.1 | G82: OK | H82: S | I82: S | J82: N | K82: N | L82: S | M82: S | N82: SP | O82: 5 | P82: N | Q82: 100 | R82: N | S82: N | T82: N | U82: S | V82: S | W82: N | X82: S | Y82: S | Z82: N | AA82: S | AB82: 33480 | AC82: N | AD82: R$ 242.406,01 | AE82: S | AF82: N | AG82: N | AH82: N | AI82: 0 | AJ82: 599 | AK82: LENNOX CONSTRUCOES E PINTURAS TECNICAS LTDA | AL82: S | AM82: S | AN82: D | AO82: N/D | AP82: N/D | AR82: Liberado | AS82: 46191 | AT82: =Calculo!AQ82 -> 62 | AU82: =Calculo!AV82 -> SEM-RISCO | AV82: =Calculo!AW82 -> LIBERADO | AW82: =Calculo!AX82 -> N/A | AX82: =Calculo!K82 -> SOLIC CONTRATO DE ENTREGA | AY82: =Calculo!AY82 -> N/A | AZ82: =Calculo!AZ82 -> N/A
A83: ='Parâmetros'!$A$19 -> Rel. Básico PJ | B83: 594 | C83: 25602 | D83: Metalpleno | E83: 026262 | F83: 6366 | G83: OK | H83: S | I83: N | J83: N | K83: N | L83: S | M83: S | N83: SP | O83: 5 | P83: N | Q83: 100 | R83: S | S83: S | T83: N | U83: S | V83: S | W83: N | X83: S | Y83: S | Z83: N | AA83: S | AB83: 24379 | AC83: S | AD83: R$ 138.446.361,00 | AE83: S | AF83: S | AG83: N | AH83: S | AI83: 36737.04 | AJ83: 731 | AK83: ATLAS COPCO BRASIL LTDA | AL83: S | AM83: S | AN83: D | AO83: N/D | AP83: N/D | AR83: Liberado | AS83: 46191 | AT83: =Calculo!AQ83 -> 32 | AU83: =Calculo!AV83 -> SEM-RISCO | AV83: =Calculo!AW83 -> LIBERADO | AW83: =Calculo!AX83 -> SOLICITAR PED COMPRA | AX83: =Calculo!K83 -> SOLIC CONTRATO DE ENTREGA | AY83: =Calculo!AY83 -> N/A | AZ83: =Calculo!AZ83 -> N/A
A84: ='Parâmetros'!$A$19 -> Rel. Básico PJ | B84: 248 | C84: 24325 | D84: Metalpleno | E84: 144612 | F84: 7868 | G84: OK | H84: S | I84: N | J84: N | K84: N | L84: S | M84: S | N84: PA | O84: - | P84: S | Q84: 100 | R84: N | S84: N | T84: N | U84: S | V84: S | W84: N | X84: S | Y84: S | Z84: N | AA84: S | AB84: 45960 | AC84: S | AE84: S | AF84: S | AG84: N | AH84: S | AI84: 39684.93 | AJ84: 613 | AK84: IC TRANSPORTES LTDA | AL84: S | AM84: S | AN84: D | AO84: N/D | AP84: N/D | AR84: Bloqueado | AS84: 46192 | AT84: =Calculo!AQ84 -> -14 | AU84: =Calculo!AV84 -> GOLPE | AV84: =Calculo!AW84 -> ENTRADA OU A VISTA | AW84: =Calculo!AX84 -> SOLICITAR PED COMPRA | AX84: =Calculo!K84 -> SOLIC CONTRATO DE ENTREGA | AY84: =Calculo!AY84 -> N/A | AZ84: =Calculo!AZ84 -> N/A
A85: ='Parâmetros'!$A$19 -> Rel. Básico PJ | B85: 595 | C85: 25678 | D85: Oaco | E85: 036260 | F85: 1098 | G85: OK | H85: S | I85: N | J85: N | K85: N | L85: N | M85: N | N85: SP | O85: 0 | P85: N | Q85: 100 | R85: N | S85: S | T85: N | U85: S | V85: S | W85: N | X85: S | Y85: S | Z85: N | AA85: S | AB85: 36242 | AC85: N | AD85: R$ 217.622.008,00 | AE85: S | AF85: S | AG85: N | AH85: N | AI85: 4975.23 | AJ85: 640 | AK85: TRANS KOTHE TRANSPORTES RODOVIARIOS SA | AL85: S | AM85: S | AN85: D | AO85: N/D | AP85: N/D | AR85: Liberado | AS85: 46192 | AT85: =Calculo!AQ85 -> 21 | AU85: =Calculo!AV85 -> SEM-RISCO | AV85: =Calculo!AW85 -> LIBERADO | AW85: =Calculo!AX85 -> N/A | AX85: =Calculo!K85 -> N/A | AY85: =Calculo!AY85 -> CHECAGEM REVERSA | AZ85: =Calculo!AZ85 -> N/A
A86: ='Parâmetros'!$A$19 -> Rel. Básico PJ | B86: 249 | C86: 25684 | D86: Metalpleno | E86: 015451 | F86: 6929 | G86: OK | H86: S | I86: N | J86: N | K86: N | L86: S | M86: S | N86: SP | O86: 5 | P86: S | Q86: 100 | R86: N | S86: S | T86: S | U86: S | V86: S | W86: N | X86: S | Y86: S | Z86: N | AA86: S | AB86: 24709 | AC86: S | AE86: S | AF86: N | AG86: N | AH86: S | AI86: 2690.14 | AJ86: 711 | AK86: SERVICO SOCIAL DA CONSTRUCAO CIVIL DO ESTADO DE SAO PAU | AL86: S | AM86: S | AN86: D | AO86: N/D | AP86: N/D | AR86: Liberado | AS86: 46192 | AT86: =Calculo!AQ86 -> 58 | AU86: =Calculo!AV86 -> SEM-RISCO | AV86: =Calculo!AW86 -> LIBERADO | AW86: =Calculo!AX86 -> SOLICITAR PED COMPRA | AX86: =Calculo!K86 -> SOLIC CONTRATO DE ENTREGA | AY86: =Calculo!AY86 -> N/A | AZ86: =Calculo!AZ86 -> N/A
A87: ='Parâmetros'!$A$19 -> Rel. Básico PJ | B87: 596 | C87: 25677 | D87: Oaco | E87: 144613 | F87: 2280 | G87: OK | H87: S | I87: N | J87: N | K87: N | L87: S | M87: S | N87: SP | O87: 5 | P87: N | Q87: 100 | R87: N | S87: N | T87: N | U87: S | V87: S | W87: S | X87: S | Y87: S | Z87: N | AA87: S | AB87: 43404 | AC87: N | AD87: R$ 110.000,00 | AE87: S | AF87: N | AG87: N | AH87: N | AI87: 0 | AJ87: 536 | AK87: ROCKET CONSTRUCOES E INCORPORACOES LTDA | AL87: S | AM87: S | AN87: D | AO87: N/D | AP87: N/D | AR87: Liberado | AS87: 46192 | AT87: =Calculo!AQ87 -> 32 | AU87: =Calculo!AV87 -> SEM-RISCO | AV87: =Calculo!AW87 -> LIBERADO | AW87: =Calculo!AX87 -> N/A | AX87: =Calculo!K87 -> SOLIC CONTRATO DE ENTREGA | AY87: =Calculo!AY87 -> N/A | AZ87: =Calculo!AZ87 -> N/A
A88: ='Parâmetros'!$A$19 -> Rel. Básico PJ | B88: 250 | C88: 25489 | D88: Metalpleno | E88: 143547 | F88: 6439.94 | G88: OK | H88: S | I88: N | J88: N | K88: N | L88: S | M88: S | N88: MG | O88: 5 | P88: N | Q88: 100 | R88: N | S88: S | T88: S | U88: S | V88: S | W88: N | X88: S | Y88: S | Z88: N | AA88: S | AB88: 44455 | AC88: N | AD88: R$ 525.724.114,00 | AE88: S | AF88: N | AG88: N | AH88: S | AI88: 41845.77 | AJ88: 431 | AK88: MIDEA INDUSTRIA E COMERCIO DO BRASIL LTDA | AL88: S | AM88: S | AN88: D | AO88: N/D | AP88: N/D | AR88: Liberado | AS88: 46195 | AT88: =Calculo!AQ88 -> 34 | AU88: =Calculo!AV88 -> SEM-RISCO | AV88: =Calculo!AW88 -> LIBERADO | AW88: =Calculo!AX88 -> SOLICITAR PED COMPRA | AX88: =Calculo!K88 -> SOLIC CONTRATO DE ENTREGA | AY88: =Calculo!AY88 -> N/A | AZ88: =Calculo!AZ88 -> N/A
A89: ='Parâmetros'!$A$19 -> Rel. Básico PJ | B89: 251 | C89: 25702 | D89: Metalpleno | E89: 144562 | F89: 7475 | G89: OK | H89: S | I89: N | J89: N | K89: N | L89: S | M89: S | N89: PR | O89: - | P89: N | Q89: 100 | R89: N | S89: S | T89: N | U89: S | V89: S | W89: N | X89: S | Y89: S | Z89: N | AA89: S | AB89: 26591 | AC89: N | AD89: R$ 41.388.384,00 | AE89: S | AF89: N | AG89: N | AH89: N | AI89: 0 | AJ89: 797 | AK89: HELISUL TAXI AEREO LTDA | AL89: S | AM89: S | AN89: D | AO89: N/D | AP89: N/D | AR89: Liberado | AS89: 46195 | AT89: =Calculo!AQ89 -> 59 | AU89: =Calculo!AV89 -> SEM-RISCO | AV89: =Calculo!AW89 -> LIBERADO | AW89: =Calculo!AX89 -> SOLICITAR PED COMPRA | AX89: =Calculo!K89 -> SOLIC CONTRATO DE ENTREGA | AY89: =Calculo!AY89 -> N/A | AZ89: =Calculo!AZ89 -> N/A
A90: ='Parâmetros'!$A$19 -> Rel. Básico PJ | B90: 600 | C90: 25709 | D90: Oaco | E90: 050424 | F90: 1079 | G90: OK | H90: S | I90: N | J90: N | K90: N | L90: N | M90: S | N90: SC | O90: - | P90: N | Q90: 100 | R90: N | S90: S | T90: S | U90: S | V90: S | W90: N | X90: S | Y90: S | Z90: N | AA90: S | AB90: 44074 | AC90: N | AD90: R$ 95.100.731,45 | AE90: S | AF90: N | AG90: N | AH90: S | AI90: 625.45 | AJ90: 641 | AK90: OKEAN ESTALEIRO SA | AL90: S | AM90: S | AN90: D | AO90: N/D | AP90: N/D | AR90: Liberado | AS90: 46195 | AT90: =Calculo!AQ90 -> 55 | AU90: =Calculo!AV90 -> SEM-RISCO | AV90: =Calculo!AW90 -> LIBERADO | AW90: =Calculo!AX90 -> N/A | AX90: =Calculo!K90 -> N/A | AY90: =Calculo!AY90 -> N/A | AZ90: =Calculo!AZ90 -> N/A
A91: ='Parâmetros'!$A$19 -> Rel. Básico PJ | B91: 253 | C91: 25700 | D91: Metalpleno | E91: 144528 | F91: 1197 | G91: OK | H91: S | I91: N | J91: N | K91: N | L91: N | M91: S | N91: SP | O91: 5 | P91: S | Q91: 100 | R91: N | S91: S | T91: N | U91: S | V91: S | W91: N | X91: S | Y91: S | Z91: N | AA91: S | AB91: 29619 | AC91: N | AD91: R$ 34.403.499,00 | AE91: S | AF91: S | AG91: N | AH91: N | AI91: 70.37 | AJ91: 906 | AK91: TRUMPF MAQUINAS INDUSTRIA E COMERCIO LTDA | AL91: S | AM91: S | AN91: D | AO91: N/D | AP91: N/D | AR91: Liberado | AS91: 46195 | AT91: =Calculo!AQ91 -> 56 | AU91: =Calculo!AV91 -> SEM-RISCO | AV91: =Calculo!AW91 -> LIBERADO | AW91: =Calculo!AX91 -> N/A | AX91: =Calculo!K91 -> N/A | AY91: =Calculo!AY91 -> N/A | AZ91: =Calculo!AZ91 -> N/A
A92: ='Parâmetros'!$A$19 -> Rel. Básico PJ | B92: 255 | C92: 25646 | D92: Metalpleno | E92: 144619 | F92: 4103.1 | G92: OK | H92: S | I92: N | J92: N | K92: N | L92: S | M92: N | N92: MG | O92: 0 | P92: S | Q92: 100 | R92: N | S92: N | T92: N | U92: S | V92: S | W92: N | X92: S | Y92: S | Z92: N | AA92: S | AB92: 35825 | AC92: N | AD92: R$ 99.068.656,00 | AE92: S | AF92: S | AG92: N | AH92: N | AI92: 54.16 | AJ92: 474 | AK92: SGS GEOSOL LABORATORIOS SA | AL92: S | AM92: S | AN92: D | AO92: N/D | AP92: N/D | AR92: Liberado | AS92: 46196 | AT92: =Calculo!AQ92 -> 17 | AU92: =Calculo!AV92 -> SEM-RISCO | AV92: =Calculo!AW92 -> LIBERADO | AW92: =Calculo!AX92 -> N/A | AX92: =Calculo!K92 -> SOLIC CONTRATO DE ENTREGA | AY92: =Calculo!AY92 -> CHECAGEM REVERSA | AZ92: =Calculo!AZ92 -> N/A
A93: ='Parâmetros'!$A$19 -> Rel. Básico PJ | B93: 254 | C93: 25073 | D93: Metalpleno | E93: 029928 | F93: 9292 | G93: OK | H93: S | I93: N | J93: N | K93: N | L93: S | M93: S | N93: MG | O93: - | P93: S | Q93: 100 | R93: N | S93: N | T93: N | U93: S | V93: S | W93: N | X93: S | Y93: S | Z93: N | AA93: S | AB93: 29179 | AC93: N | AE93: S | AF93: N | AG93: N | AH93: N | AI93: 0 | AJ93: 663 | AK93: FUNDACAO ARTHUR BERNARDES | AL93: S | AM93: S | AN93: D | AO93: N/D | AP93: N/D | AR93: Liberado | AS93: 46196 | AT93: =Calculo!AQ93 -> 26 | AU93: =Calculo!AV93 -> SEM-RISCO | AV93: =Calculo!AW93 -> LIBERADO | AW93: =Calculo!AX93 -> SOLICITAR PED COMPRA | AX93: =Calculo!K93 -> SOLIC CONTRATO DE ENTREGA | AY93: =Calculo!AY93 -> N/A | AZ93: =Calculo!AZ93 -> N/A
A94: ='Parâmetros'!$A$19 -> Rel. Básico PJ | B94: 608 | C94: 25630 | D94: Oaco | E94: 144622 | F94: 9053 | G94: OK | H94: S | I94: S | J94: N | K94: N | L94: S | M94: S | N94: AM | O94: - | P94: S | Q94: 100 | R94: N | S94: N | T94: N | U94: S | V94: S | W94: S | X94: S | Y94: S | Z94: N | AA94: S | AB94: 35235 | AC94: S | AD94: 21280155 | AE94: S | AF94: S | AG94: N | AH94: S | AI94: 129038.38 | AJ94: 421 | AK94: 3P BRASIL- CONSULTORIA E PROJETOS DE INSTALACAO P | AL94: S | AM94: S | AN94: D | AO94: N/D | AP94: N/D | AR94: Liberado | AS94: 46197 | AT94: =Calculo!AQ94 -> 15 | AU94: =Calculo!AV94 -> SEM-RISCO | AV94: =Calculo!AW94 -> LIBERADO | AW94: =Calculo!AX94 -> SOLICITAR PED COMPRA | AX94: =Calculo!K94 -> SOLIC CONTRATO DE ENTREGA | AY94: =Calculo!AY94 -> N/A | AZ94: =Calculo!AZ94 -> N/A
A95: ='Parâmetros'!$A$19 -> Rel. Básico PJ | B95: 610 | C95: 25749 | D95: Oaco | E95: 035764 | F95: 2255.22 | G95: OK | H95: S | I95: N | J95: N | K95: N | L95: N | M95: S | N95: SP | O95: - | P95: N | Q95: 100 | R95: N | S95: S | T95: S | U95: S | V95: S | W95: N | X95: S | Y95: S | Z95: N | AA95: S | AB95: 44103 | AC95: N | AD95: R$ 5.000,00 | AE95: S | AF95: N | AG95: N | AH95: S | AI95: 91.01 | AJ95: 760 | AK95: JR2 COMERCIO DE VARIEDADES LTDA | AL95: S | AM95: S | AN95: D | AO95: N/D | AP95: N/D | AR95: Liberado | AS95: 46197 | AT95: =Calculo!AQ95 -> 59 | AU95: =Calculo!AV95 -> SEM-RISCO | AV95: =Calculo!AW95 -> LIBERADO | AW95: =Calculo!AX95 -> N/A | AX95: =Calculo!K95 -> N/A | AY95: =Calculo!AY95 -> N/A | AZ95: =Calculo!AZ95 -> N/A
A96: ='Parâmetros'!$A$19 -> Rel. Básico PJ | B96: 611 | C96: 25750 | D96: Oaco | E96: 035764 | F96: 14250 | G96: OK | H96: S | I96: N | J96: S | K96: N | L96: N | M96: N | N96: SP | O96: 0 | P96: N | Q96: 100 | R96: N | S96: S | T96: S | U96: S | V96: S | W96: N | X96: S | Y96: S | Z96: N | AA96: S | AB96: 44103 | AC96: N | AD96: R$ 5.000,00 | AE96: S | AF96: N | AG96: N | AH96: S | AI96: 91.01 | AJ96: 760 | AK96: JR2 COMERCIO DE VARIEDADES LTDA | AL96: S | AM96: S | AN96: D | AO96: N/D | AP96: N/D | AR96: Liberado | AS96: 46198 | AT96: =Calculo!AQ96 -> 31 | AU96: =Calculo!AV96 -> SEM-RISCO | AV96: =Calculo!AW96 -> LIBERADO | AW96: =Calculo!AX96 -> SOLICITAR PED COMPRA | AX96: =Calculo!K96 -> N/A | AY96: =Calculo!AY96 -> CHECAGEM REVERSA | AZ96: =Calculo!AZ96 -> N/A
A97: ='Parâmetros'!$A$19 -> Rel. Básico PJ | B97: 258 | C97: 25758 | D97: Metalpleno | E97: 144625 | F97: 7184 | G97: OK | H97: S | I97: S | J97: N | K97: N | L97: S | M97: S | N97: RJ | O97: 5 | P97: N | Q97: 100 | R97: N | S97: N | T97: N | U97: S | V97: S | W97: N | X97: S | Y97: N | Z97: S | AA97: S | AB97: 32225 | AC97: N | AD97: R$ 7.747.460,00 | AE97: S | AF97: N | AG97: N | AH97: S | AI97: 41973.11 | AJ97: 796 | AK97: HOSPITAL SAO LOURENCO LTDA | AL97: S | AM97: S | AN97: D | AO97: N/D | AP97: N/D | AR97: Liberado | AS97: 46198 | AT97: =Calculo!AQ97 -> 12 | AU97: =Calculo!AV97 -> SEM-RISCO | AV97: =Calculo!AW97 -> LIBERADO | AW97: =Calculo!AX97 -> SOLICITAR PED COMPRA | AX97: =Calculo!K97 -> SOLIC CONTRATO DE ENTREGA | AY97: =Calculo!AY97 -> N/A | AZ97: =Calculo!AZ97 -> N/A
A98: ='Parâmetros'!$A$19 -> Rel. Básico PJ | B98: 257 | C98: 25716 | D98: Metalpleno | E98: 005501 | F98: 15143 | G98: OK | H98: S | I98: N | J98: N | K98: N | L98: S | M98: S | N98: SP | O98: 5 | P98: S | Q98: 100 | R98: N | S98: N | T98: N | U98: S | V98: S | W98: N | X98: S | Y98: S | Z98: N | AA98: S | AB98: 31385 | AC98: S | AE98: S | AF98: S | AG98: N | AH98: S | AI98: 317597.34 | AK98: UNIAO CENTRAL BRASILEIRA DA IGREJA DO SETIMO | AL98: S | AM98: S | AN98: D | AO98: N/D | AP98: N/D | AQ98: Pré-análise Andrea | AR98: Bloqueado | AS98: 46199 | AT98: =Calculo!AQ98 -> -21 | AU98: =Calculo!AV98 -> GOLPE | AV98: =Calculo!AW98 -> ENTRADA OU A VISTA | AW98: =Calculo!AX98 -> SOLICITAR PED COMPRA | AX98: =Calculo!K98 -> SOLIC CONTRATO DE ENTREGA | AY98: =Calculo!AY98 -> N/A | AZ98: =Calculo!AZ98 -> N/A
A99: ='Parâmetros'!$A$19 -> Rel. Básico PJ | B99: 259 | C99: 25590 | D99: Metalpleno | E99: 144628 | F99: 19662 | G99: OK | H99: S | I99: N | J99: N | K99: N | L99: S | M99: S | N99: MS | O99: - | P99: S | Q99: 100 | R99: N | S99: N | T99: N | U99: S | V99: S | W99: N | X99: S | Y99: S | Z99: N | AA99: S | AB99: 44795 | AC99: N | AD99: R$ 21.005.711.779,95 | AE99: S | AF99: S | AG99: N | AH99: N | AI99: 2450.46 | AJ99: 565 | AK99: ARAUCO CELULOSE DO BRASIL SA | AL99: S | AM99: S | AN99: D | AO99: N/D | AP99: N/D | AR99: Liberado | AS99: 46199 | AT99: =Calculo!AQ99 -> 23 | AU99: =Calculo!AV99 -> SEM-RISCO | AV99: =Calculo!AW99 -> LIBERADO | AW99: =Calculo!AX99 -> SOLICITAR PED COMPRA | AX99: =Calculo!K99 -> SOLIC CONTRATO DE ENTREGA | AY99: =Calculo!AY99 -> N/A | AZ99: =Calculo!AZ99 -> N/A
A100: ='Parâmetros'!$A$19 -> Rel. Básico PJ | B100: 1877 | C100: 25770 | D100: GsiBW | E100: 019694 | F100: 1199 | G100: OK | H100: S | I100: N | J100: N | K100: N | L100: N | M100: S | N100: SP | O100: - | P100: N | Q100: 100 | R100: N | S100: S | T100: S | U100: S | V100: S | W100: N | X100: S | Y100: S | Z100: N | AA100: S | AB100: 35608 | AC100: N | AD100: R$ 10.000,00 | AE100: S | AF100: N | AG100: N | AH100: N | AI100: 0 | AJ100: 634 | AK100: PERFUMARIA YUJI LTDA | AL100: S | AM100: S | AN100: D | AO100: N/D | AP100: N/D | AR100: Liberado | AS100: 46202 | AT100: =Calculo!AQ100 -> 74 | AU100: =Calculo!AV100 -> SEM-RISCO | AV100: =Calculo!AW100 -> LIBERADO | AW100: =Calculo!AX100 -> N/A | AX100: =Calculo!K100 -> N/A | AY100: =Calculo!AY100 -> N/A | AZ100: =Calculo!AZ100 -> N/A
...

Sheet AJUDA
A1: 1414 | B1: Se for antecipado ou simples faturamento para recebermos antes de despachar, não precisa fazer análise. Se for pedido de revendedor que compra direto, não precisa fazer a consulta e preencher a planilha. Só bloqueie se tiver pagamentos em atraso. Coloca no follow: Cliente revenda conhecida, liberado sem análise.
A2: Consulta | B2: https://web2.bvsnet.com.br/transacional/login.php Login: AC098902 | BW@2022 .... > Pessoa Jurídica > Outros Produtos para Crédito > Define Risco (Imagem======================================================>>>
A3: PED | B3: Número do pedido do Protheus | C3: AC098902
A4: 2-Empresa | B4: Nossa empresa: BN, S4T, OW ou GS
A5: 3-Cliente | B5: Código do Cliente
A6: 4-Total Ped. R$ | B6: Total do pedido com frete e tudo. Valor que aparece no pedido
A7: Desconto Ped | B7: Verificar se o vendedor respeitou o limite. Máx: 3% Faturado ou 6% antecipado. Dar um F3 em cima do código do produto. Revenda tem 10% de desconto.
A8: 5-Faturado | B8: S | N - Se tiver algum pagamento depois de despacharmos o produto.
A9: 6-Entrada | B9: S | N - Se tiver algum BA ou depósito antecipado.
A10: 7-Quant. Grande? | B10: S | N - Se tiver + DE 10 Cofres, + DE 5 Armário Corta Fogo, + DE 5 Fragmentadoras ou acima de 30 pacotes/rolos de suprimentos
A11: 8-Prod. Q Ñ Combinam? | B11: S = sim tem ptrodutos que não combinam | N - não tem produto que não combinam. Exemplo: o cliente compra fragmentadoras e cofres.
A12: Armário ou Cofre > 2.000 | B12: S | N - Se tem algum produto que exija contrato de entrega.
A13: Entrega=Cadastro | B13: S | N - Se for CLIENTE RETIRA = N | Se constar endereço de entrega diferente na Obs da NF = N | Se não houver nenhuma informação na Mensagem pra Nota informando local diferente = S
A14: UF do Cliente | B14: Preencher com a sigla do estado dele, exemplo: RJ ou SP ou PB... (sempre 2 letras MAIÚSCULAS).
A15: Google Maps 0|5|10 | B15: 0 | 5 | 10 - Se for CLIENTE RETIRA = 0 | Usar o endereço de entrega. Se não tiver end. de entrega usar o do cadastro mesmo. Se for um local ruim, 0, se for razoável 5 e se for um lugar muito bom 10, se não localizar coloca um TRAÇO -
... A32: 25-SalvarPDFConsltRede | B32: Fazer a consulta no Boa Vista e salva a consulta na rede dentro de G:\Drives compartilhados\Financeiro Consulta\Consultas salve com o nome da empresa sem / e se for repetido, coloque a data no final 2021-04-30
A33: 24-PFIN | B33: S | N - Na consulta Boa Vista mostra (em 23.06.2023 CONSULTAMOS ATUALMENTE PELO SERASA. LOGON É=76582187 E SENHA É=Bwe@2022 )https://empresas.serasaexperian.com.br/meus-produtos/login | C33: https://web2.bvsnet.com.br/transacional/login.php
A34: 23-Ch s/ Fundo | B34: S | N - Na consulta Boa Vista mostra | C34: AC098902
A35: 21-Protestos | B35: S | N - Na consulta Boa Vista mostra
A36: 22-Vlr Prot. | B36: Coloca o valor total dos protestos em R$
A37: 28 - SCORE Serasa | B37: Coloca o Score que a consulta do Serasa dá. Se aparecer Default coloca 0.
A38: Nome que consta na REGULARIDADE DO FGTS | B38: Cole o nome que aparece no site - Acesse o site https://consulta-crf.caixa.gov.br/consultacrf/pages/consultaEmpregador.jsf > Coloque o CNPJ sem números e preencha o Captcha.
A39: Situação Regular? | B39: S | N - Se constar: "A EMPRESA abaixo identificada está REGULAR" = S. Mas se constar: "As informações disponíveis não são suficientes para a comprovação..." = N "EMPREGADOR NÃO CADASTRADO" = N
A40: 33-RAZÃO E FGTS IGUAL?S/N | B40: S | N - O nome que aparece está igual ao do cadastro do Protheus?
A41: 34-Certid Trib Federais | B41: S (Sim emitiu e não constam debitos | N (Não foi possível emitir) | D (Emitiu mas constam Débitos)- http://servicos.receita.fazenda.gov.br/Servicos/certidaointernet/PJ/Emitir
A42: 30-3 NF Conf. | B42: Use em caso de cliente que está próximo ao score 0 ou que vc desconfie que é golpe. Solicite uma Nfe recente de valor igual ou maior ao pedido que ele esta fazendo.
A43: 31 - Conta de Luz | B43: Use em caso que vc desconfie que é golpe. Solicite uma conta recente de luz do endereço de entrega. Se for apresentdo uma conta com valor baixo = golpe.
A44: OBS | B44: Coloque aqui por exemplo: Pedi uma Nf, liberado só se... avisei o vendedor..., etc
A45: Final: Lib/Entrada/Bloqu. só AV | B45: Coloque: Liberado | Entrada | Bloqueado onde Liberado OK, Entrada é só com entrada e Bloqueado é quando o cadastro é ruim mesmo.
A46: Data | B46: Data de hoje
A47: Total Score | B47: Automático. Menor que 0 = Bloqueia ou pede entrada ou antecipado ou sugere link de pagamento. De 1 a 5 = Pede uma NF ou conta de luz. De 6 acima liberado. Cola as celulas amarelas no follow do pedido.
A48: Risco
A49: Sugestão | B49: A planilha vai lhe dizer o que ela acha.
A50: Obs: | B50: Ela vai lhe avise se é necessário pedir o PC pelo valor do pedido.
A51: Contratato Entrega | B51: Ela vai lhe avisar se é pra pedir Contrato de Entrega.
A53: Ao terminar as análises, dá uma olhada em pedidos antigos e tenta empurrar, cobrando contratos de entregas, PC, depósitos e etc.
A54: Tela de análise, seleciona o pedido e sempre clica em Manual:
A65: Se o pedido vai ficar parado na análise, pois estamos esperando algo ou alguma resposta clica em Cancelar.
A66: Se o pedido não passou e não tem jeito, clica em Rejeitar
A67: Se o pedido passou na análise, clica em Lib. Todos.
A68: Nunca em OK

Sheet Calculo
A1: =Consultas!A1 -> Tipo | B1: PED | C1: 2-Empresa | D1: 3-Cliente | E1: 19-Idade | F1: 4-Total Ped. R$ | G1: 5-Faturado | H1: 6-Entrada | I1: 7-Muitos Itens | J1: 8-Prod. Variados | K1: Armário ou Cofre > 1800 | L1: 9-Pgtos Abertos | M1: 10-Já Comprou e Pagou 2X ou +? | N1: 10-Comprou e pagou +5X? | O1: 11-Cadastro=Receita | P1: 12-CNPJ Ativo | Q1: 13-Entrega=Cadastro | R1: UF do Cliente | S1: Google Maps 0|5|10 | T1: Registro.Br | U1: ScamAdvizer | V1: 14-Casa/Sala/Conj no end. | W1: EmailSiteReceita=@corporativo? | X1: Existe Mail Financeiro Diferente? | Y1: 15-Mail gratuito | Z1: 16-Possui Site | AA1: 18-Fundação Matriz | AB1: 19-IdadeScore | AC1: 20-MUITO Grande /Conhecida | AD1: 21-Protestos | AE1: 22-Vlr Prot. | AF1: 22-Prot.XCapit | AG1: 23-Ch s/ Fundo | AH1: 24-Pend. Fin. | AI1: 28 - SCORE Serasa | AJ1: 29-Capital Soc. | AK1: 30-3 Boletos Conf. | AL1: 31-Ref. Comercial | AM1: Situação Regular? | AN1: 33-RAZÃO E FGTS IGUAL?S/N | AO1: 34-Certid Trib Mobiliaros | AQ1: Total Score | AR1: EMPRESINHA | AS1: GOLPE | AT1: GRANDE-FALINDO | AU1: Menor Valor | AV1: Risco | AW1: Sugestão | AX1: Obs | AY1: Retira e Faturado | AZ1: Cadastro = Receita
A2: Define Risco | B2: =Consultas!B2 -> 162 | C2: =Consultas!D2 -> Metalpleno | D2: =Consultas!E2 -> 034331 | E2: =IF(Consultas!AB2>0,YEAR('Parâmetros'!$B$1)-YEAR(Consultas!AB2),"NA") -> 31 | F2: =IF(Consultas!F2>'Parâmetros'!$B$2,-8,0) -> 0 | G2: =IF(Consultas!H2='Parâmetros'!$E$1,100,0) -> 0 | H2: =IF(Consultas!I2='Parâmetros'!$E$1,-4,12) -> -4 | I2: =IF(Consultas!J2='Parâmetros'!$E$1,1,-13) -> 1 | J2: =IF(Consultas!K2='Parâmetros'!$E$1,2,-5) -> 2 | K2: =IF(Consultas!L2='Parâmetros'!$D$1,"SOLIC CONTRATO DE ENTREGA","N/A") -> SOLIC CONTRATO DE ENTREGA | L2: =IF(Consultas!R2='Parâmetros'!$E$1,1,-3) -> 1 | M2: =IF(Consultas!S2>1,(IF(Consultas!S2='Parâmetros'!$E$1,-3,9))) -> 9 | N2: =IF(Consultas!T2="S",23,0) -> 0 | O2: =IF(Consultas!U2='Parâmetros'!$E$1,-3,3) -> 3 | P2: =IF(Consultas!V2='Parâmetros'!$E$1,-100,2) -> 2 | Q2: =IF(Consultas!M2='Parâmetros'!$D$1,2,-9) -> -9 | R2: =IF(Consultas!N2="RJ",-12,0) -> 0 | S2: =IF(Consultas!O2="-",-3,IF(Consultas!O2=0,-6,IF(Consultas!O2=5,0,IF(Consultas!O2=10,6)))) -> -6 | T2: =IF(Consultas!M2="S",0,(IF(Consultas!P2="S",6,0))) -> 0 | U2: =IF(Consultas!Q2>97,9,IF(Consultas!Q2>75,0,-7)) -> 9 | V2: =IF(Consultas!W2='Parâmetros'!$E$1,1,-5) -> 1 | W2: =IF(Consultas!X2="S",3,-3) -> 3 | X2: =IF(Consultas!Y2="S",0,-7) -> 0 | Y2: =IF(Consultas!Z2='Parâmetros'!$E$1,2,-8) -> 2 | Z2: =IF(Consultas!AA2='Parâmetros'!$E$1,-15,1) -> 1 | AA2: - | AB2: =IF(E2="NA","NA",IF(E2>'Parâmetros'!$A$9,8,IF(E2>'Parâmetros'!$A$8,4,IF(E2>'Parâmetros'!$A$7,0,-6)))) -> 8 | AC2: =IF(Consultas!AC2='Parâmetros'!$E$1,0,5) -> 0 | AD2: =IF(Consultas!AH2='Parâmetros'!$D$1,-10,5) -> 5 | AE2: =IF(Consultas!AI2>(Consultas!F2*2),-10,0) -> 0 | AF2: =IF(Consultas!AD2>1,(IF(Consultas!AI2>(Consultas!AD2),-20,4))) -> 4 | AG2: =IF(Consultas!AG2='Parâmetros'!$E$1,0,-6) -> 0 | AH2: =IF(Consultas!AF2='Parâmetros'!$E$1,1,-5) -> 1 | AI2: =IF(Consultas!AJ2>700,8,IF(Consultas!AJ2>500,4,IF(Consultas!AJ2>200,-4,IF(Consultas!AJ2>1,-15,-20)))) -> 8 | AJ2: =IF(Consultas!AD2='Parâmetros'!$E$10,0,IF(Consultas!AD2>'Parâmetros'!$A$30,12,IF(Consultas!AD2>'Parâmetros'!$A$31,6,IF(Consultas!AD2>'Parâmetros'!$A$32,0,IF(Consultas!AD2>'Parâmetros'!$A$33,0,IF(Consultas!AD2>'Parâmetros'!$A$34,-3,IF(Consultas!AD2>'Parâmetros'!$A$35,-7,-1))))))) -> 12 | AK2: =IF(Consultas!AO2='Parâmetros'!$D$1,3,-3) -> -3 | AL2: =IF(Consultas!AP2='Parâmetros'!$D$1,5,-3) -> -3 | AM2: =IF(Consultas!AL2="N",-6,0) -> 0 | AN2: =IF(Consultas!AM2="N",-10,0) -> 0 | AO2: =IF(Consultas!AN2="S",4,-2) -> -2 | AQ2: =IF(Consultas!F2>1,(SUM(F2:AO2)),"N/A") -> 45 | AR2: =IF((Consultas!AD2>'Parâmetros'!$A$31),"X",AJ2+Y2+V2+AC2) -> X | AS2: =IF((Consultas!AD2>'Parâmetros'!$A$31),"X",(H2+I2+J2+Q2+T2+Y2+Z2+AJ2+AN2)) -> X | AT2: =IF((Consultas!AD2<'Parâmetros'!$A$31),"X",(AD2+AC2+AB2)) -> 13 | AU2: =SMALL(AR2:AT2,1) -> 13 | AV2: =IF(AQ2="N/A","N/A",IF(AQ2>5,'Parâmetros'!$A$15,(IF(AU2=AR2,'Parâmetros'!$A$17,IF(AU2=AS2,'Parâmetros'!$A$16,'Parâmetros'!$A$14))))) -> SEM-RISCO | AW2: =IF(AQ2="N/A","N/A",IF(AV2='Parâmetros'!$A$15,'Parâmetros'!$C$15,(IF(AV2='Parâmetros'!$A$17,'Parâmetros'!$C$17,IF(AV2='Parâmetros'!$A$16,'Parâmetros'!$C$16,IF(AV2='Parâmetros'!$A$14,'Parâmetros'!$C$12)))))) -> LIBERADO | AX2: =IF(Consultas!F2>1,(IF(Consultas!F2>5000,"SOLICITAR PED COMPRA","N/A"))) -> SOLICITAR PED COMPRA | AY2: =IF(AND(Consultas!M2<>"S", Consultas!H2="S"), "CHECAGEM REVERSA", "N/A") -> CHECAGEM REVERSA | AZ2: =IF(Consultas!U2="N","PRECISA CORRIGIR END DIVERGENTE","N/A") -> N/A
A3: Define Risco | B3: =Consultas!B3 -> 166 | C3: =Consultas!D3 -> Metalpleno | D3: =Consultas!E3 -> 141660 | E3: =IF(Consultas!AB3>0,YEAR('Parâmetros'!$B$1)-YEAR(Consultas!AB3),"NA") -> 60 | F3: =IF(Consultas!F3>'Parâmetros'!$B$2,-8,0) -> 0 | G3: =IF(Consultas!H3='Parâmetros'!$E$1,100,0) -> 0 | H3: =IF(Consultas!I3='Parâmetros'!$E$1,-4,12) -> 12 | I3: =IF(Consultas!J3='Parâmetros'!$E$1,1,-13) -> 1 | J3: =IF(Consultas!K3='Parâmetros'!$E$1,2,-5) -> 2 | K3: =IF(Consultas!L3='Parâmetros'!$D$1,"SOLIC CONTRATO DE ENTREGA","N/A") -> SOLIC CONTRATO DE ENTREGA | L3: =IF(Consultas!R3='Parâmetros'!$E$1,1,-3) -> 1 | M3: =IF(Consultas!S3>1,(IF(Consultas!S3='Parâmetros'!$E$1,-3,9))) -> -3 | N3: =IF(Consultas!T3="S",23,0) -> 0 | O3: =IF(Consultas!U3='Parâmetros'!$E$1,-3,3) -> 3 | P3: =IF(Consultas!V3='Parâmetros'!$E$1,-100,2) -> 2 | Q3: =IF(Consultas!M3='Parâmetros'!$D$1,2,-9) -> 2 | R3: =IF(Consultas!N3="RJ",-12,0) -> 0 | S3: =IF(Consultas!O3="-",-3,IF(Consultas!O3=0,-6,IF(Consultas!O3=5,0,IF(Consultas!O3=10,6)))) -> 0 | T3: =IF(Consultas!M3="S",0,(IF(Consultas!P3="S",6,0))) -> 0 | U3: =IF(Consultas!Q3>97,9,IF(Consultas!Q3>75,0,-7)) -> 9 | V3: =IF(Consultas!W3='Parâmetros'!$E$1,1,-5) -> 1 | W3: =IF(Consultas!X3="S",3,-3) -> 3 | X3: =IF(Consultas!Y3="S",0,-7) -> 0 | Y3: =IF(Consultas!Z3='Parâmetros'!$E$1,2,-8) -> 2 | Z3: =IF(Consultas!AA3='Parâmetros'!$E$1,-15,1) -> 1 | AA3: - | AB3: =IF(E3="NA","NA",IF(E3>'Parâmetros'!$A$9,8,IF(E3>'Parâmetros'!$A$8,4,IF(E3>'Parâmetros'!$A$7,0,-6)))) -> 8 | AC3: =IF(Consultas!AC3='Parâmetros'!$E$1,0,5) -> 0 | AD3: =IF(Consultas!AH3='Parâmetros'!$D$1,-10,5) -> 5 | AE3: =IF(Consultas!AI3>(Consultas!F3*2),-10,0) -> 0 | AF3: =IF(Consultas!AD3>1,(IF(Consultas!AI3>(Consultas!AD3),-20,4))) -> 4 | AG3: =IF(Consultas!AG3='Parâmetros'!$E$1,0,-6) -> 0 | AH3: =IF(Consultas!AF3='Parâmetros'!$E$1,1,-5) -> -5 | AI3: =IF(Consultas!AJ3>700,8,IF(Consultas!AJ3>500,4,IF(Consultas!AJ3>200,-4,IF(Consultas!AJ3>1,-15,-20)))) -> 4 | AJ3: =IF(Consultas!AD3='Parâmetros'!$E$10,0,IF(Consultas!AD3>'Parâmetros'!$A$30,12,IF(Consultas!AD3>'Parâmetros'!$A$31,6,IF(Consultas!AD3>'Parâmetros'!$A$32,0,IF(Consultas!AD3>'Parâmetros'!$A$33,0,IF(Consultas!AD3>'Parâmetros'!$A$34,-3,IF(Consultas!AD3>'Parâmetros'!$A$35,-7,-1))))))) -> 12 | AK3: =IF(Consultas!AO3='Parâmetros'!$D$1,3,-3) -> -3 | AL3: =IF(Consultas!AP3='Parâmetros'!$D$1,5,-3) -> -3 | AM3: =IF(Consultas!AL3="N",-6,0) -> 0 | AN3: =IF(Consultas!AM3="N",-10,0) -> 0 | AO3: =IF(Consultas!AN3="S",4,-2) -> -2 | AQ3: =IF(Consultas!F3>1,(SUM(F3:AO3)),"N/A") -> 56 | AR3: =IF((Consultas!AD3>'Parâmetros'!$A$31),"X",AJ3+Y3+V3+AC3) -> X | AS3: =IF((Consultas!AD3>'Parâmetros'!$A$31),"X",(H3+I3+J3+Q3+T3+Y3+Z3+AJ3+AN3)) -> X | AT3: =IF((Consultas!AD3<'Parâmetros'!$A$31),"X",(AD3+AC3+AB3)) -> 13 | AU3: =SMALL(AR3:AT3,1) -> 13 | AV3: =IF(AQ3="N/A","N/A",IF(AQ3>5,'Parâmetros'!$A$15,(IF(AU3=AR3,'Parâmetros'!$A$17,IF(AU3=AS3,'Parâmetros'!$A$16,'Parâmetros'!$A$14))))) -> SEM-RISCO | AW3: =IF(AQ3="N/A","N/A",IF(AV3='Parâmetros'!$A$15,'Parâmetros'!$C$15,(IF(AV3='Parâmetros'!$A$17,'Parâmetros'!$C$17,IF(AV3='Parâmetros'!$A$16,'Parâmetros'!$C$16,IF(AV3='Parâmetros'!$A$14,'Parâmetros'!$C$12)))))) -> LIBERADO | AX3: =IF(Consultas!F3>1,(IF(Consultas!F3>5000,"SOLICITAR PED COMPRA","N/A"))) -> SOLICITAR PED COMPRA | AY3: =IF(AND(Consultas!M3<>"S", Consultas!H3="S"), "CHECAGEM REVERSA", "N/A") -> N/A | AZ3: =IF(Consultas!U3="N","PRECISA CORRIGIR END DIVERGENTE","N/A") -> N/A
A4: Define Risco | B4: =Consultas!B4 -> 167 | C4: =Consultas!D4 -> Metalpleno | D4: =Consultas!E4 -> 144468 | E4: =IF(Consultas!AB4>0,YEAR('Parâmetros'!$B$1)-YEAR(Consultas!AB4),"NA") -> 21 | F4: =IF(Consultas!F4>'Parâmetros'!$B$2,-8,0) -> 0 | G4: =IF(Consultas!H4='Parâmetros'!$E$1,100,0) -> 0 | H4: =IF(Consultas!I4='Parâmetros'!$E$1,-4,12) -> 12 | I4: =IF(Consultas!J4='Parâmetros'!$E$1,1,-13) -> 1 | J4: =IF(Consultas!K4='Parâmetros'!$E$1,2,-5) -> 2 | K4: =IF(Consultas!L4='Parâmetros'!$D$1,"SOLIC CONTRATO DE ENTREGA","N/A") -> SOLIC CONTRATO DE ENTREGA | L4: =IF(Consultas!R4='Parâmetros'!$E$1,1,-3) -> 1 | M4: =IF(Consultas!S4>1,(IF(Consultas!S4='Parâmetros'!$E$1,-3,9))) -> -3 | N4: =IF(Consultas!T4="S",23,0) -> 0 | O4: =IF(Consultas!U4='Parâmetros'!$E$1,-3,3) -> 3 | P4: =IF(Consultas!V4='Parâmetros'!$E$1,-100,2) -> 2 | Q4: =IF(Consultas!M4='Parâmetros'!$D$1,2,-9) -> 2 | R4: =IF(Consultas!N4="RJ",-12,0) -> 0 | S4: =IF(Consultas!O4="-",-3,IF(Consultas!O4=0,-6,IF(Consultas!O4=5,0,IF(Consultas!O4=10,6)))) -> 0 | T4: =IF(Consultas!M4="S",0,(IF(Consultas!P4="S",6,0))) -> 0 | U4: =IF(Consultas!Q4>97,9,IF(Consultas!Q4>75,0,-7)) -> 9 | V4: =IF(Consultas!W4='Parâmetros'!$E$1,1,-5) -> -5 | W4: =IF(Consultas!X4="S",3,-3) -> 3 | X4: =IF(Consultas!Y4="S",0,-7) -> -7 | Y4: =IF(Consultas!Z4='Parâmetros'!$E$1,2,-8) -> 2 | Z4: =IF(Consultas!AA4='Parâmetros'!$E$1,-15,1) -> 1 | AA4: - | AB4: =IF(E4="NA","NA",IF(E4>'Parâmetros'!$A$9,8,IF(E4>'Parâmetros'!$A$8,4,IF(E4>'Parâmetros'!$A$7,0,-6)))) -> 4 | AC4: =IF(Consultas!AC4='Parâmetros'!$E$1,0,5) -> 0 | AD4: =IF(Consultas!AH4='Parâmetros'!$D$1,-10,5) -> 5 | AE4: =IF(Consultas!AI4>(Consultas!F4*2),-10,0) -> 0 | AF4: =IF(Consultas!AD4>1,(IF(Consultas!AI4>(Consultas!AD4),-20,4))) -> 4 | AG4: =IF(Consultas!AG4='Parâmetros'!$E$1,0,-6) -> 0 | AH4: =IF(Consultas!AF4='Parâmetros'!$E$1,1,-5) -> 1 | AI4: =IF(Consultas!AJ4>700,8,IF(Consultas!AJ4>500,4,IF(Consultas!AJ4>200,-4,IF(Consultas!AJ4>1,-15,-20)))) -> 4 | AJ4: =IF(Consultas!AD4='Parâmetros'!$E$10,0,IF(Consultas!AD4>'Parâmetros'!$A$30,12,IF(Consultas!AD4>'Parâmetros'!$A$31,6,IF(Consultas!AD4>'Parâmetros'!$A$32,0,IF(Consultas!AD4>'Parâmetros'!$A$33,0,IF(Consultas!AD4>'Parâmetros'!$A$34,-3,IF(Consultas!AD4>'Parâmetros'!$A$35,-7,-1))))))) -> 12 | AK4: =IF(Consultas!AO4='Parâmetros'!$D$1,3,-3) -> -3 | AL4: =IF(Consultas!AP4='Parâmetros'!$D$1,5,-3) -> -3 | AM4: =IF(Consultas!AL4="N",-6,0) -> 0 | AN4: =IF(Consultas!AM4="N",-10,0) -> 0 | AO4: =IF(Consultas!AN4="S",4,-2) -> -2 | AQ4: =IF(Consultas!F4>1,(SUM(F4:AO4)),"N/A") -> 45 | AR4: =IF((Consultas!AD4>'Parâmetros'!$A$31),"X",AJ4+Y4+V4+AC4) -> X | AS4: =IF((Consultas!AD4>'Parâmetros'!$A$31),"X",(H4+I4+J4+Q4+T4+Y4+Z4+AJ4+AN4)) -> X | AT4: =IF((Consultas!AD4<'Parâmetros'!$A$31),"X",(AD4+AC4+AB4)) -> 9 | AU4: =SMALL(AR4:AT4,1) -> 9 | AV4: =IF(AQ4="N/A","N/A",IF(AQ4>5,'Parâmetros'!$A$15,(IF(AU4=AR4,'Parâmetros'!$A$17,IF(AU4=AS4,'Parâmetros'!$A$16,'Parâmetros'!$A$14))))) -> SEM-RISCO | AW4: =IF(AQ4="N/A","N/A",IF(AV4='Parâmetros'!$A$15,'Parâmetros'!$C$15,(IF(AV4='Parâmetros'!$A$17,'Parâmetros'!$C$17,IF(AV4='Parâmetros'!$A$16,'Parâmetros'!$C$16,IF(AV4='Parâmetros'!$A$14,'Parâmetros'!$C$12)))))) -> LIBERADO | AX4: =IF(Consultas!F4>1,(IF(Consultas!F4>5000,"SOLICITAR PED COMPRA","N/A"))) -> N/A | AY4: =IF(AND(Consultas!M4<>"S", Consultas!H4="S"), "CHECAGEM REVERSA", "N/A") -> N/A | AZ4: =IF(Consultas!U4="N","PRECISA CORRIGIR END DIVERGENTE","N/A") -> N/A
A5: Define Risco | B5: =Consultas!B5 -> 1864 | C5: =Consultas!D5 -> GsiBW | D5: =Consultas!E5 -> 021332 | E5: =IF(Consultas!AB5>0,YEAR('Parâmetros'!$B$1)-YEAR(Consultas!AB5),"NA") -> 43 | F5: =IF(Consultas!F5>'Parâmetros'!$B$2,-8,0) -> 0 | G5: =IF(Consultas!H5='Parâmetros'!$E$1,100,0) -> 0 | H5: =IF(Consultas!I5='Parâmetros'!$E$1,-4,12) -> -4 | I5: =IF(Consultas!J5='Parâmetros'!$E$1,1,-13) -> 1 | J5: =IF(Consultas!K5='Parâmetros'!$E$1,2,-5) -> 2 | K5: =IF(Consultas!L5='Parâmetros'!$D$1,"SOLIC CONTRATO DE ENTREGA","N/A") -> N/A | L5: =IF(Consultas!R5='Parâmetros'!$E$1,1,-3) -> 1 | M5: =IF(Consultas!S5>1,(IF(Consultas!S5='Parâmetros'!$E$1,-3,9))) -> 9 | N5: =IF(Consultas!T5="S",23,0) -> 0 | O5: =IF(Consultas!U5='Parâmetros'!$E$1,-3,3) -> 3 | P5: =IF(Consultas!V5='Parâmetros'!$E$1,-100,2) -> 2 | Q5: =IF(Consultas!M5='Parâmetros'!$D$1,2,-9) -> 2 | R5: =IF(Consultas!N5="RJ",-12,0) -> 0 | S5: =IF(Consultas!O5="-",-3,IF(Consultas!O5=0,-6,IF(Consultas!O5=5,0,IF(Consultas!O5=10,6)))) -> -3 | T5: =IF(Consultas!M5="S",0,(IF(Consultas!P5="S",6,0))) -> 0 | U5: =IF(Consultas!Q5>97,9,IF(Consultas!Q5>75,0,-7)) -> 9 | V5: =IF(Consultas!W5='Parâmetros'!$E$1,1,-5) -> 1 | W5: =IF(Consultas!X5="S",3,-3) -> 3 | X5: =IF(Consultas!Y5="S",0,-7) -> 0 | Y5: =IF(Consultas!Z5='Parâmetros'!$E$1,2,-8) -> 2 | Z5: =IF(Consultas!AA5='Parâmetros'!$E$1,-15,1) -> 1 | AA5: - | AB5: =IF(E5="NA","NA",IF(E5>'Parâmetros'!$A$9,8,IF(E5>'Parâmetros'!$A$8,4,IF(E5>'Parâmetros'!$A$7,0,-6)))) -> 8 | AC5: =IF(Consultas!AC5='Parâmetros'!$E$1,0,5) -> 0 | AD5: =IF(Consultas!AH5='Parâmetros'!$D$1,-10,5) -> 5 | AE5: =IF(Consultas!AI5>(Consultas!F5*2),-10,0) -> 0 | AF5: =IF(Consultas!AD5>1,(IF(Consultas!AI5>(Consultas!AD5),-20,4))) -> 4 | AG5: =IF(Consultas!AG5='Parâmetros'!$E$1,0,-6) -> 0 | AH5: =IF(Consultas!AF5='Parâmetros'!$E$1,1,-5) -> 1 | AI5: =IF(Consultas!AJ5>700,8,IF(Consultas!AJ5>500,4,IF(Consultas!AJ5>200,-4,IF(Consultas!AJ5>1,-15,-20)))) -> 8 | AJ5: =IF(Consultas!AD5='Parâmetros'!$E$10,0,IF(Consultas!AD5>'Parâmetros'!$A$30,12,IF(Consultas!AD5>'Parâmetros'!$A$31,6,IF(Consultas!AD5>'Parâmetros'!$A$32,0,IF(Consultas!AD5>'Parâmetros'!$A$33,0,IF(Consultas!AD5>'Parâmetros'!$A$34,-3,IF(Consultas!AD5>'Parâmetros'!$A$35,-7,-1))))))) -> 12 | AK5: =IF(Consultas!AO5='Parâmetros'!$D$1,3,-3) -> -3 | AL5: =IF(Consultas!AP5='Parâmetros'!$D$1,5,-3) -> -3 | AM5: =IF(Consultas!AL5="N",-6,0) -> 0 | AN5: =IF(Consultas!AM5="N",-10,0) -> 0 | AO5: =IF(Consultas!AN5="S",4,-2) -> -2 | AQ5: =IF(Consultas!F5>1,(SUM(F5:AO5)),"N/A") -> 59 | AR5: =IF((Consultas!AD5>'Parâmetros'!$A$31),"X",AJ5+Y5+V5+AC5) -> X | AS5: =IF((Consultas!AD5>'Parâmetros'!$A$31),"X",(H5+I5+J5+Q5+T5+Y5+Z5+AJ5+AN5)) -> X | AT5: =IF((Consultas!AD5<'Parâmetros'!$A$31),"X",(AD5+AC5+AB5)) -> 13 | AU5: =SMALL(AR5:AT5,1) -> 13 | AV5: =IF(AQ5="N/A","N/A",IF(AQ5>5,'Parâmetros'!$A$15,(IF(AU5=AR5,'Parâmetros'!$A$17,IF(AU5=AS5,'Parâmetros'!$A$16,'Parâmetros'!$A$14))))) -> SEM-RISCO | AW5: =IF(AQ5="N/A","N/A",IF(AV5='Parâmetros'!$A$15,'Parâmetros'!$C$15,(IF(AV5='Parâmetros'!$A$17,'Parâmetros'!$C$17,IF(AV5='Parâmetros'!$A$16,'Parâmetros'!$C$16,IF(AV5='Parâmetros'!$A$14,'Parâmetros'!$C$12)))))) -> LIBERADO | AX5: =IF(Consultas!F5>1,(IF(Consultas!F5>5000,"SOLICITAR PED COMPRA","N/A"))) -> N/A | AY5: =IF(AND(Consultas!M5<>"S", Consultas!H5="S"), "CHECAGEM REVERSA", "N/A") -> N/A | AZ5: =IF(Consultas!U5="N","PRECISA CORRIGIR END DIVERGENTE","N/A") -> N/A
A6: Define Risco | B6: =Consultas!B6 -> 442 | C6: =Consultas!D6 -> Oaco | D6: =Consultas!E6 -> 144469 | E6: =IF(Consultas!AB6>0,YEAR('Parâmetros'!$B$1)-YEAR(Consultas!AB6),"NA") -> 9 | F6: =IF(Consultas!F6>'Parâmetros'!$B$2,-8,0) -> 0 | G6: =IF(Consultas!H6='Parâmetros'!$E$1,100,0) -> 0 | H6: =IF(Consultas!I6='Parâmetros'!$E$1,-4,12) -> -4 | I6: =IF(Consultas!J6='Parâmetros'!$E$1,1,-13) -> 1 | J6: =IF(Consultas!K6='Parâmetros'!$E$1,2,-5) -> 2 | K6: =IF(Consultas!L6='Parâmetros'!$D$1,"SOLIC CONTRATO DE ENTREGA","N/A") -> N/A | L6: =IF(Consultas!R6='Parâmetros'!$E$1,1,-3) -> 1 | M6: =IF(Consultas!S6>1,(IF(Consultas!S6='Parâmetros'!$E$1,-3,9))) -> -3 | N6: =IF(Consultas!T6="S",23,0) -> 0 | O6: =IF(Consultas!U6='Parâmetros'!$E$1,-3,3) -> 3 | P6: =IF(Consultas!V6='Parâmetros'!$E$1,-100,2) -> 2 | Q6: =IF(Consultas!M6='Parâmetros'!$D$1,2,-9) -> 2 | R6: =IF(Consultas!N6="RJ",-12,0) -> 0 | S6: =IF(Consultas!O6="-",-3,IF(Consultas!O6=0,-6,IF(Consultas!O6=5,0,IF(Consultas!O6=10,6)))) -> -3 | T6: =IF(Consultas!M6="S",0,(IF(Consultas!P6="S",6,0))) -> 0 | U6: =IF(Consultas!Q6>97,9,IF(Consultas!Q6>75,0,-7)) -> 9 | V6: =IF(Consultas!W6='Parâmetros'!$E$1,1,-5) -> 1 | W6: =IF(Consultas!X6="S",3,-3) -> 3 | X6: =IF(Consultas!Y6="S",0,-7) -> 0 | Y6: =IF(Consultas!Z6='Parâmetros'!$E$1,2,-8) -> 2 | Z6: =IF(Consultas!AA6='Parâmetros'!$E$1,-15,1) -> 1 | AA6: - | AB6: =IF(E6="NA","NA",IF(E6>'Parâmetros'!$A$9,8,IF(E6>'Parâmetros'!$A$8,4,IF(E6>'Parâmetros'!$A$7,0,-6)))) -> 0 | AC6: =IF(Consultas!AC6='Parâmetros'!$E$1,0,5) -> 5 | AD6: =IF(Consultas!AH6='Parâmetros'!$D$1,-10,5) -> -10 | AE6: =IF(Consultas!AI6>(Consultas!F6*2),-10,0) -> -10 | AF6: =IF(Consultas!AD6>1,(IF(Consultas!AI6>(Consultas!AD6),-20,4))) -> 4 | AG6: =IF(Consultas!AG6='Parâmetros'!$E$1,0,-6) -> 0 | AH6: =IF(Consultas!AF6='Parâmetros'!$E$1,1,-5) -> -5 | AI6: =IF(Consultas!AJ6>700,8,IF(Consultas!AJ6>500,4,IF(Consultas!AJ6>200,-4,IF(Consultas!AJ6>1,-15,-20)))) -> 8 | AJ6: =IF(Consultas!AD6='Parâmetros'!$E$10,0,IF(Consultas!AD6>'Parâmetros'!$A$30,12,IF(Consultas!AD6>'Parâmetros'!$A$31,6,IF(Consultas!AD6>'Parâmetros'!$A$32,0,IF(Consultas!AD6>'Parâmetros'!$A$33,0,IF(Consultas!AD6>'Parâmetros'!$A$34,-3,IF(Consultas!AD6>'Parâmetros'!$A$35,-7,-1))))))) -> 12 | AK6: =IF(Consultas!AO6='Parâmetros'!$D$1,3,-3) -> -3 | AL6: =IF(Consultas!AP6='Parâmetros'!$D$1,5,-3) -> -3 | AM6: =IF(Consultas!AL6="N",-6,0) -> 0 | AN6: =IF(Consultas!AM6="N",-10,0) -> 0 | AO6: =IF(Consultas!AN6="S",4,-2) -> -2 | AQ6: =IF(Consultas!F6>1,(SUM(F6:AO6)),"N/A") -> 13 | AR6: =IF((Consultas!AD6>'Parâmetros'!$A$31),"X",AJ6+Y6+V6+AC6) -> X | AS6: =IF((Consultas!AD6>'Parâmetros'!$A$31),"X",(H6+I6+J6+Q6+T6+Y6+Z6+AJ6+AN6)) -> X | AT6: =IF((Consultas!AD6<'Parâmetros'!$A$31),"X",(AD6+AC6+AB6)) -> -5 | AU6: =SMALL(AR6:AT6,1) -> -5 | AV6: =IF(AQ6="N/A","N/A",IF(AQ6>5,'Parâmetros'!$A$15,(IF(AU6=AR6,'Parâmetros'!$A$17,IF(AU6=AS6,'Parâmetros'!$A$16,'Parâmetros'!$A$14))))) -> SEM-RISCO | AW6: =IF(AQ6="N/A","N/A",IF(AV6='Parâmetros'!$A$15,'Parâmetros'!$C$15,(IF(AV6='Parâmetros'!$A$17,'Parâmetros'!$C$17,IF(AV6='Parâmetros'!$A$16,'Parâmetros'!$C$16,IF(AV6='Parâmetros'!$A$14,'Parâmetros'!$C$12)))))) -> LIBERADO | AX6: =IF(Consultas!F6>1,(IF(Consultas!F6>5000,"SOLICITAR PED COMPRA","N/A"))) -> N/A | AY6: =IF(AND(Consultas!M6<>"S", Consultas!H6="S"), "CHECAGEM REVERSA", "N/A") -> N/A | AZ6: =IF(Consultas!U6="N","PRECISA CORRIGIR END DIVERGENTE","N/A") -> N/A
A7: Define Risco | B7: =Consultas!B7 -> 444 | C7: =Consultas!D7 -> Oaco | D7: =Consultas!E7 -> 144471 | E7: =IF(Consultas!AB7>0,YEAR('Parâmetros'!$B$1)-YEAR(Consultas!AB7),"NA") -> 9 | F7: =IF(Consultas!F7>'Parâmetros'!$B$2,-8,0) -> 0 | G7: =IF(Consultas!H7='Parâmetros'!$E$1,100,0) -> 0 | H7: =IF(Consultas!I7='Parâmetros'!$E$1,-4,12) -> -4 | I7: =IF(Consultas!J7='Parâmetros'!$E$1,1,-13) -> 1 | J7: =IF(Consultas!K7='Parâmetros'!$E$1,2,-5) -> 2 | K7: =IF(Consultas!L7='Parâmetros'!$D$1,"SOLIC CONTRATO DE ENTREGA","N/A") -> N/A | L7: =IF(Consultas!R7='Parâmetros'!$E$1,1,-3) -> 1 | M7: =IF(Consultas!S7>1,(IF(Consultas!S7='Parâmetros'!$E$1,-3,9))) -> -3 | N7: =IF(Consultas!T7="S",23,0) -> 0 | O7: =IF(Consultas!U7='Parâmetros'!$E$1,-3,3) -> 3 | P7: =IF(Consultas!V7='Parâmetros'!$E$1,-100,2) -> 2 | Q7: =IF(Consultas!M7='Parâmetros'!$D$1,2,-9) -> 2 | R7: =IF(Consultas!N7="RJ",-12,0) -> 0 | S7: =IF(Consultas!O7="-",-3,IF(Consultas!O7=0,-6,IF(Consultas!O7=5,0,IF(Consultas!O7=10,6)))) -> -3 | T7: =IF(Consultas!M7="S",0,(IF(Consultas!P7="S",6,0))) -> 0 | U7: =IF(Consultas!Q7>97,9,IF(Consultas!Q7>75,0,-7)) -> 9 | V7: =IF(Consultas!W7='Parâmetros'!$E$1,1,-5) -> 1 | W7: =IF(Consultas!X7="S",3,-3) -> 3 | X7: =IF(Consultas!Y7="S",0,-7) -> 0 | Y7: =IF(Consultas!Z7='Parâmetros'!$E$1,2,-8) -> 2 | Z7: =IF(Consultas!AA7='Parâmetros'!$E$1,-15,1) -> 1 | AA7: - | AB7: =IF(E7="NA","NA",IF(E7>'Parâmetros'!$A$9,8,IF(E7>'Parâmetros'!$A$8,4,IF(E7>'Parâmetros'!$A$7,0,-6)))) -> 0 | AC7: =IF(Consultas!AC7='Parâmetros'!$E$1,0,5) -> 5 | AD7: =IF(Consultas!AH7='Parâmetros'!$D$1,-10,5) -> -10 | AE7: =IF(Consultas!AI7>(Consultas!F7*2),-10,0) -> -10 | AF7: =IF(Consultas!AD7>1,(IF(Consultas!AI7>(Consultas!AD7),-20,4))) -> 4 | AG7: =IF(Consultas!AG7='Parâmetros'!$E$1,0,-6) -> 0 | AH7: =IF(Consultas!AF7='Parâmetros'!$E$1,1,-5) -> -5 | AI7: =IF(Consultas!AJ7>700,8,IF(Consultas!AJ7>500,4,IF(Consultas!AJ7>200,-4,IF(Consultas!AJ7>1,-15,-20)))) -> 8 | AJ7: =IF(Consultas!AD7='Parâmetros'!$E$10,0,IF(Consultas!AD7>'Parâmetros'!$A$30,12,IF(Consultas!AD7>'Parâmetros'!$A$31,6,IF(Consultas!AD7>'Parâmetros'!$A$32,0,IF(Consultas!AD7>'Parâmetros'!$A$33,0,IF(Consultas!AD7>'Parâmetros'!$A$34,-3,IF(Consultas!AD7>'Parâmetros'!$A$35,-7,-1))))))) -> 12 | AK7: =IF(Consultas!AO7='Parâmetros'!$D$1,3,-3) -> -3 | AL7: =IF(Consultas!AP7='Parâmetros'!$D$1,5,-3) -> -3 | AM7: =IF(Consultas!AL7="N",-6,0) -> 0 | AN7: =IF(Consultas!AM7="N",-10,0) -> 0 | AO7: =IF(Consultas!AN7="S",4,-2) -> -2 | AQ7: =IF(Consultas!F7>1,(SUM(F7:AO7)),"N/A") -> 13 | AR7: =IF((Consultas!AD7>'Parâmetros'!$A$31),"X",AJ7+Y7+V7+AC7) -> X | AS7: =IF((Consultas!AD7>'Parâmetros'!$A$31),"X",(H7+I7+J7+Q7+T7+Y7+Z7+AJ7+AN7)) -> X | AT7: =IF((Consultas!AD7<'Parâmetros'!$A$31),"X",(AD7+AC7+AB7)) -> -5 | AU7: =SMALL(AR7:AT7,1) -> -5 | AV7: =IF(AQ7="N/A","N/A",IF(AQ7>5,'Parâmetros'!$A$15,(IF(AU7=AR7,'Parâmetros'!$A$17,IF(AU7=AS7,'Parâmetros'!$A$16,'Parâmetros'!$A$14))))) -> SEM-RISCO | AW7: =IF(AQ7="N/A","N/A",IF(AV7='Parâmetros'!$A$15,'Parâmetros'!$C$15,(IF(AV7='Parâmetros'!$A$17,'Parâmetros'!$C$17,IF(AV7='Parâmetros'!$A$16,'Parâmetros'!$C$16,IF(AV7='Parâmetros'!$A$14,'Parâmetros'!$C$12)))))) -> LIBERADO | AX7: =IF(Consultas!F7>1,(IF(Consultas!F7>5000,"SOLICITAR PED COMPRA","N/A"))) -> N/A | AY7: =IF(AND(Consultas!M7<>"S", Consultas!H7="S"), "CHECAGEM REVERSA", "N/A") -> N/A | AZ7: =IF(Consultas!U7="N","PRECISA CORRIGIR END DIVERGENTE","N/A") -> N/A
A8: Define Risco | B8: =Consultas!B8 | C8: =Consultas!D8 -> Metalpleno | D8: =Consultas!E8 | E8: =IF(Consultas!AB8>0,YEAR('Parâmetros'!$B$1)-YEAR(Consultas!AB8),"NA") -> 18 | F8: =IF(Consultas!F8>'Parâmetros'!$B$2,-8,0) -> 0 | G8: =IF(Consultas!H8='Parâmetros'!$E$1,100,0) -> 0 | H8: =IF(Consultas!I8='Parâmetros'!$E$1,-4,12) -> -4 | I8: =IF(Consultas!J8='Parâmetros'!$E$1,1,-13) -> 1 | J8: =IF(Consultas!K8='Parâmetros'!$E$1,2,-5) -> 2 | K8: =IF(Consultas!L8='Parâmetros'!$D$1,"SOLIC CONTRATO DE ENTREGA","N/A") -> SOLIC CONTRATO DE ENTREGA | L8: =IF(Consultas!R8='Parâmetros'!$E$1,1,-3) -> 1 | M8: =IF(Consultas!S8>1,(IF(Consultas!S8='Parâmetros'!$E$1,-3,9))) -> -3 | N8: =IF(Consultas!T8="S",23,0) -> 0 | O8: =IF(Consultas!U8='Parâmetros'!$E$1,-3,3) -> 3 | P8: =IF(Consultas!V8='Parâmetros'!$E$1,-100,2) -> 2 | Q8: =IF(Consultas!M8='Parâmetros'!$D$1,2,-9) -> -9 | R8: =IF(Consultas!N8="RJ",-12,0) -> 0 | S8: =IF(Consultas!O8="-",-3,IF(Consultas!O8=0,-6,IF(Consultas!O8=5,0,IF(Consultas!O8=10,6)))) -> -6 | T8: =IF(Consultas!M8="S",0,(IF(Consultas!P8="S",6,0))) -> 6 | U8: =IF(Consultas!Q8>97,9,IF(Consultas!Q8>75,0,-7)) -> 9 | V8: =IF(Consultas!W8='Parâmetros'!$E$1,1,-5) -> -5 | W8: =IF(Consultas!X8="S",3,-3) -> 3 | X8: =IF(Consultas!Y8="S",0,-7) -> -7 | Y8: =IF(Consultas!Z8='Parâmetros'!$E$1,2,-8) -> 2 | Z8: =IF(Consultas!AA8='Parâmetros'!$E$1,-15,1) -> 1 | AA8: - | AB8: =IF(E8="NA","NA",IF(E8>'Parâmetros'!$A$9,8,IF(E8>'Parâmetros'!$A$8,4,IF(E8>'Parâmetros'!$A$7,0,-6)))) -> 4 | AC8: =IF(Consultas!AC8='Parâmetros'!$E$1,0,5) -> 5 | AD8: =IF(Consultas!AH8='Parâmetros'!$D$1,-10,5) -> 5 | AE8: =IF(Consultas!AI8>(Consultas!F8*2),-10,0) -> 0 | AF8: =IF(Consultas!AD8>1,(IF(Consultas!AI8>(Consultas!AD8),-20,4))) -> 4 | AG8: =IF(Consultas!AG8='Parâmetros'!$E$1,0,-6) -> 0 | AH8: =IF(Consultas!AF8='Parâmetros'!$E$1,1,-5) -> -5 | AI8: =IF(Consultas!AJ8>700,8,IF(Consultas!AJ8>500,4,IF(Consultas!AJ8>200,-4,IF(Consultas!AJ8>1,-15,-20)))) -> 8 | AJ8: =IF(Consultas!AD8='Parâmetros'!$E$10,0,IF(Consultas!AD8>'Parâmetros'!$A$30,12,IF(Consultas!AD8>'Parâmetros'!$A$31,6,IF(Consultas!AD8>'Parâmetros'!$A$32,0,IF(Consultas!AD8>'Parâmetros'!$A$33,0,IF(Consultas!AD8>'Parâmetros'!$A$34,-3,IF(Consultas!AD8>'Parâmetros'!$A$35,-7,-1))))))) -> 12 | AK8: =IF(Consultas!AO8='Parâmetros'!$D$1,3,-3) -> -3 | AL8: =IF(Consultas!AP8='Parâmetros'!$D$1,5,-3) -> -3 | AM8: =IF(Consultas!AL8="N",-6,0) -> 0 | AN8: =IF(Consultas!AM8="N",-10,0) -> 0 | AO8: =IF(Consultas!AN8="S",4,-2) -> -2 | AQ8: =IF(Consultas!F8>1,(SUM(F8:AO8)),"N/A") -> 21 | AR8: =IF((Consultas!AD8>'Parâmetros'!$A$31),"X",AJ8+Y8+V8+AC8) -> X | AS8: =IF((Consultas!AD8>'Parâmetros'!$A$31),"X",(H8+I8+J8+Q8+T8+Y8+Z8+AJ8+AN8)) -> X | AT8: =IF((Consultas!AD8<'Parâmetros'!$A$31),"X",(AD8+AC8+AB8)) -> 14 | AU8: =SMALL(AR8:AT8,1) -> 14 | AV8: =IF(AQ8="N/A","N/A",IF(AQ8>5,'Parâmetros'!$A$15,(IF(AU8=AR8,'Parâmetros'!$A$17,IF(AU8=AS8,'Parâmetros'!$A$16,'Parâmetros'!$A$14))))) -> SEM-RISCO | AW8: =IF(AQ8="N/A","N/A",IF(AV8='Parâmetros'!$A$15,'Parâmetros'!$C$15,(IF(AV8='Parâmetros'!$A$17,'Parâmetros'!$C$17,IF(AV8='Parâmetros'!$A$16,'Parâmetros'!$C$16,IF(AV8='Parâmetros'!$A$14,'Parâmetros'!$C$12)))))) -> LIBERADO | AX8: =IF(Consultas!F8>1,(IF(Consultas!F8>5000,"SOLICITAR PED COMPRA","N/A"))) -> SOLICITAR PED COMPRA | AY8: =IF(AND(Consultas!M8<>"S", Consultas!H8="S"), "CHECAGEM REVERSA", "N/A") -> CHECAGEM REVERSA | AZ8: =IF(Consultas!U8="N","PRECISA CORRIGIR END DIVERGENTE","N/A") -> N/A
A9: Define Risco | B9: =Consultas!B9 -> 446 | C9: =Consultas!D9 -> Oaco | D9: =Consultas!E9 -> 144472 | E9: =IF(Consultas!AB9>0,YEAR('Parâmetros'!$B$1)-YEAR(Consultas!AB9),"NA") -> 2 | F9: =IF(Consultas!F9>'Parâmetros'!$B$2,-8,0) -> 0 | G9: =IF(Consultas!H9='Parâmetros'!$E$1,100,0) -> 0 | H9: =IF(Consultas!I9='Parâmetros'!$E$1,-4,12) -> -4 | I9: =IF(Consultas!J9='Parâmetros'!$E$1,1,-13) -> 1 | J9: =IF(Consultas!K9='Parâmetros'!$E$1,2,-5) -> 2 | K9: =IF(Consultas!L9='Parâmetros'!$D$1,"SOLIC CONTRATO DE ENTREGA","N/A") -> SOLIC CONTRATO DE ENTREGA | L9: =IF(Consultas!R9='Parâmetros'!$E$1,1,-3) -> 1 | M9: =IF(Consultas!S9>1,(IF(Consultas!S9='Parâmetros'!$E$1,-3,9))) -> -3 | N9: =IF(Consultas!T9="S",23,0) -> 0 | O9: =IF(Consultas!U9='Parâmetros'!$E$1,-3,3) -> 3 | P9: =IF(Consultas!V9='Parâmetros'!$E$1,-100,2) -> 2 | Q9: =IF(Consultas!M9='Parâmetros'!$D$1,2,-9) -> 2 | R9: =IF(Consultas!N9="RJ",-12,0) -> -12 | S9: =IF(Consultas!O9="-",-3,IF(Consultas!O9=0,-6,IF(Consultas!O9=5,0,IF(Consultas!O9=10,6)))) -> 0 | T9: =IF(Consultas!M9="S",0,(IF(Consultas!P9="S",6,0))) -> 0 | U9: =IF(Consultas!Q9>97,9,IF(Consultas!Q9>75,0,-7)) -> 9 | V9: =IF(Consultas!W9='Parâmetros'!$E$1,1,-5) -> 1 | W9: =IF(Consultas!X9="S",3,-3) -> 3 | X9: =IF(Consultas!Y9="S",0,-7) -> 0 | Y9: =IF(Consultas!Z9='Parâmetros'!$E$1,2,-8) -> 2 | Z9: =IF(Consultas!AA9='Parâmetros'!$E$1,-15,1) -> 1 | AA9: - | AB9: =IF(E9="NA","NA",IF(E9>'Parâmetros'!$A$9,8,IF(E9>'Parâmetros'!$A$8,4,IF(E9>'Parâmetros'!$A$7,0,-6)))) -> -6 | AC9: =IF(Consultas!AC9='Parâmetros'!$E$1,0,5) -> 0 | AD9: =IF(Consultas!AH9='Parâmetros'!$D$1,-10,5) -> -10 | AE9: =IF(Consultas!AI9>(Consultas!F9*2),-10,0) -> -10 | AF9: =IF(Consultas!AD9>1,(IF(Consultas!AI9>(Consultas!AD9),-20,4))) -> 4 | AG9: =IF(Consultas!AG9='Parâmetros'!$E$1,0,-6) -> 0 | AH9: =IF(Consultas!AF9='Parâmetros'!$E$1,1,-5) -> 1 | AI9: =IF(Consultas!AJ9>700,8,IF(Consultas!AJ9>500,4,IF(Consultas!AJ9>200,-4,IF(Consultas!AJ9>1,-15,-20)))) -> -20 | AJ9: =IF(Consultas!AD9='Parâmetros'!$E$10,0,IF(Consultas!AD9>'Parâmetros'!$A$30,12,IF(Consultas!AD9>'Parâmetros'!$A$31,6,IF(Consultas!AD9>'Parâmetros'!$A$32,0,IF(Consultas!AD9>'Parâmetros'!$A$33,0,IF(Consultas!AD9>'Parâmetros'!$A$34,-3,IF(Consultas!AD9>'Parâmetros'!$A$35,-7,-1))))))) -> 12 | AK9: =IF(Consultas!AO9='Parâmetros'!$D$1,3,-3) -> -3 | AL9: =IF(Consultas!AP9='Parâmetros'!$D$1,5,-3) -> -3 | AM9: =IF(Consultas!AL9="N",-6,0) -> 0 | AN9: =IF(Consultas!AM9="N",-10,0) -> 0 | AO9: =IF(Consultas!AN9="S",4,-2) -> -2 | AQ9: =IF(Consultas!F9>1,(SUM(F9:AO9)),"N/A") -> -29 | AR9: =IF((Consultas!AD9>'Parâmetros'!$A$31),"X",AJ9+Y9+V9+AC9) -> X | AS9: =IF((Consultas!AD9>'Parâmetros'!$A$31),"X",(H9+I9+J9+Q9+T9+Y9+Z9+AJ9+AN9)) -> X | AT9: =IF((Consultas!AD9<'Parâmetros'!$A$31),"X",(AD9+AC9+AB9)) -> -16 | AU9: =SMALL(AR9:AT9,1) -> -16 | AV9: =IF(AQ9="N/A","N/A",IF(AQ9>5,'Parâmetros'!$A$15,(IF(AU9=AR9,'Parâmetros'!$A$17,IF(AU9=AS9,'Parâmetros'!$A$16,'Parâmetros'!$A$14))))) -> GRANDE-OU-FALINDO: | AW9: =IF(AQ9="N/A","N/A",IF(AV9='Parâmetros'!$A$15,'Parâmetros'!$C$15,(IF(AV9='Parâmetros'!$A$17,'Parâmetros'!$C$17,IF(AV9='Parâmetros'!$A$16,'Parâmetros'!$C$16,IF(AV9='Parâmetros'!$A$14,'Parâmetros'!$C$12)))))) -> SE FALINDO SÓ ANTECIPADO | SE GRANDE BUROCR PEGAR CONTATOS FINANCEIRO | AX9: =IF(Consultas!F9>1,(IF(Consultas!F9>5000,"SOLICITAR PED COMPRA","N/A"))) -> N/A | AY9: =IF(AND(Consultas!M9<>"S", Consultas!H9="S"), "CHECAGEM REVERSA", "N/A") -> N/A | AZ9: =IF(Consultas!U9="N","PRECISA CORRIGIR END DIVERGENTE","N/A") -> N/A
A10: Define Risco | B10: =Consultas!B10 -> 170 | C10: =Consultas!D10 -> Metalpleno | D10: =Consultas!E10 -> 144477 | E10: =IF(Consultas!AB10>0,YEAR('Parâmetros'!$B$1)-YEAR(Consultas!AB10),"NA") -> 44 | F10: =IF(Consultas!F10>'Parâmetros'!$B$2,-8,0) -> 0 | G10: =IF(Consultas!H10='Parâmetros'!$E$1,100,0) -> 0 | H10: =IF(Consultas!I10='Parâmetros'!$E$1,-4,12) -> 12 | I10: =IF(Consultas!J10='Parâmetros'!$E$1,1,-13) -> 1 | J10: =IF(Consultas!K10='Parâmetros'!$E$1,2,-5) -> 2 | K10: =IF(Consultas!L10='Parâmetros'!$D$1,"SOLIC CONTRATO DE ENTREGA","N/A") -> SOLIC CONTRATO DE ENTREGA | L10: =IF(Consultas!R10='Parâmetros'!$E$1,1,-3) -> 1 | M10: =IF(Consultas!S10>1,(IF(Consultas!S10='Parâmetros'!$E$1,-3,9))) -> -3 | N10: =IF(Consultas!T10="S",23,0) -> 0 | O10: =IF(Consultas!U10='Parâmetros'!$E$1,-3,3) -> 3 | P10: =IF(Consultas!V10='Parâmetros'!$E$1,-100,2) -> 2 | Q10: =IF(Consultas!M10='Parâmetros'!$D$1,2,-9) -> 2 | R10: =IF(Consultas!N10="RJ",-12,0) -> 0 | S10: =IF(Consultas!O10="-",-3,IF(Consultas!O10=0,-6,IF(Consultas!O10=5,0,IF(Consultas!O10=10,6)))) -> 0 | T10: =IF(Consultas!M10="S",0,(IF(Consultas!P10="S",6,0))) -> 0 | U10: =IF(Consultas!Q10>97,9,IF(Consultas!Q10>75,0,-7)) -> 9 | V10: =IF(Consultas!W10='Parâmetros'!$E$1,1,-5) -> 1 | W10: =IF(Consultas!X10="S",3,-3) -> 3 | X10: =IF(Consultas!Y10="S",0,-7) -> 0 | Y10: =IF(Consultas!Z10='Parâmetros'!$E$1,2,-8) -> 2 | Z10: =IF(Consultas!AA10='Parâmetros'!$E$1,-15,1) -> 1 | AA10: - | AB10: =IF(E10="NA","NA",IF(E10>'Parâmetros'!$A$9,8,IF(E10>'Parâmetros'!$A$8,4,IF(E10>'Parâmetros'!$A$7,0,-6)))) -> 8 | AC10: =IF(Consultas!AC10='Parâmetros'!$E$1,0,5) -> 5 | AD10: =IF(Consultas!AH10='Parâmetros'!$D$1,-10,5) -> -10 | AE10: =IF(Consultas!AI10>(Consultas!F10*2),-10,0) -> -10 | AF10: =IF(Consultas!AD10>1,(IF(Consultas!AI10>(Consultas!AD10),-20,4))) -> 4 | AG10: =IF(Consultas!AG10='Parâmetros'!$E$1,0,-6) -> 0 | AH10: =IF(Consultas!AF10='Parâmetros'!$E$1,1,-5) -> -5 | AI10: =IF(Consultas!AJ10>700,8,IF(Consultas!AJ10>500,4,IF(Consultas!AJ10>200,-4,IF(Consultas!AJ10>1,-15,-20)))) -> -20 | AJ10: =IF(Consultas!AD10='Parâmetros'!$E$10,0,IF(Consultas!AD10>'Parâmetros'!$A$30,12,IF(Consultas!AD10>'Parâmetros'!$A$31,6,IF(Consultas!AD10>'Parâmetros'!$A$32,0,IF(Consultas!AD10>'Parâmetros'!$A$33,0,IF(Consultas!AD10>'Parâmetros'!$A$34,-3,IF(Consultas!AD10>'Parâmetros'!$A$35,-7,-1))))))) -> 12 | AK10: =IF(Consultas!AO10='Parâmetros'!$D$1,3,-3) -> -3 | AL10: =IF(Consultas!AP10='Parâmetros'!$D$1,5,-3) -> -3 | AM10: =IF(Consultas!AL10="N",-6,0) -> 0 | AN10: =IF(Consultas!AM10="N",-10,0) -> 0 | AO10: =IF(Consultas!AN10="S",4,-2) -> -2 | AQ10: =IF(Consultas!F10>1,(SUM(F10:AO10)),"N/A") -> 12 | AR10: =IF((Consultas!AD10>'Parâmetros'!$A$31),"X",AJ10+Y10+V10+AC10) -> X | AS10: =IF((Consultas!AD10>'Parâmetros'!$A$31),"X",(H10+I10+J10+Q10+T10+Y10+Z10+AJ10+AN10)) -> X | AT10: =IF((Consultas!AD10<'Parâmetros'!$A$31),"X",(AD10+AC10+AB10)) -> 3 | AU10: =SMALL(AR10:AT10,1) -> 3 | AV10: =IF(AQ10="N/A","N/A",IF(AQ10>5,'Parâmetros'!$A$15,(IF(AU10=AR10,'Parâmetros'!$A$17,IF(AU10=AS10,'Parâmetros'!$A$16,'Parâmetros'!$A$14))))) -> SEM-RISCO | AW10: =IF(AQ10="N/A","N/A",IF(AV10='Parâmetros'!$A$15,'Parâmetros'!$C$15,(IF(AV10='Parâmetros'!$A$17,'Parâmetros'!$C$17,IF(AV10='Parâmetros'!$A$16,'Parâmetros'!$C$16,IF(AV10='Parâmetros'!$A$14,'Parâmetros'!$C$12)))))) -> LIBERADO | AX10: =IF(Consultas!F10>1,(IF(Consultas!F10>5000,"SOLICITAR PED COMPRA","N/A"))) -> SOLICITAR PED COMPRA | AY10: =IF(AND(Consultas!M10<>"S", Consultas!H10="S"), "CHECAGEM REVERSA", "N/A") -> N/A | AZ10: =IF(Consultas!U10="N","PRECISA CORRIGIR END DIVERGENTE","N/A") -> N/A
A11: Define Risco | B11: =Consultas!B11 -> 172 | C11: =Consultas!D11 -> Metalpleno | D11: =Consultas!E11 -> 144481 | E11: =IF(Consultas!AB11>0,YEAR('Parâmetros'!$B$1)-YEAR(Consultas!AB11),"NA") -> 19 | F11: =IF(Consultas!F11>'Parâmetros'!$B$2,-8,0) -> 0 | G11: =IF(Consultas!H11='Parâmetros'!$E$1,100,0) -> 0 | H11: =IF(Consultas!I11='Parâmetros'!$E$1,-4,12) -> -4 | I11: =IF(Consultas!J11='Parâmetros'!$E$1,1,-13) -> 1 | J11: =IF(Consultas!K11='Parâmetros'!$E$1,2,-5) -> 2 | K11: =IF(Consultas!L11='Parâmetros'!$D$1,"SOLIC CONTRATO DE ENTREGA","N/A") -> SOLIC CONTRATO DE ENTREGA | L11: =IF(Consultas!R11='Parâmetros'!$E$1,1,-3) -> 1 | M11: =IF(Consultas!S11>1,(IF(Consultas!S11='Parâmetros'!$E$1,-3,9))) -> -3 | N11: =IF(Consultas!T11="S",23,0) -> 0 | O11: =IF(Consultas!U11='Parâmetros'!$E$1,-3,3) -> 3 | P11: =IF(Consultas!V11='Parâmetros'!$E$1,-100,2) -> 2 | Q11: =IF(Consultas!M11='Parâmetros'!$D$1,2,-9) -> -9 | R11: =IF(Consultas!N11="RJ",-12,0) -> 0 | S11: =IF(Consultas!O11="-",-3,IF(Consultas!O11=0,-6,IF(Consultas!O11=5,0,IF(Consultas!O11=10,6)))) -> -6 | T11: =IF(Consultas!M11="S",0,(IF(Consultas!P11="S",6,0))) -> 6 | U11: =IF(Consultas!Q11>97,9,IF(Consultas!Q11>75,0,-7)) -> 9 | V11: =IF(Consultas!W11='Parâmetros'!$E$1,1,-5) -> 1 | W11: =IF(Consultas!X11="S",3,-3) -> 3 | X11: =IF(Consultas!Y11="S",0,-7) -> -7 | Y11: =IF(Consultas!Z11='Parâmetros'!$E$1,2,-8) -> 2 | Z11: =IF(Consultas!AA11='Parâmetros'!$E$1,-15,1) -> 1 | AA11: - | AB11: =IF(E11="NA","NA",IF(E11>'Parâmetros'!$A$9,8,IF(E11>'Parâmetros'!$A$8,4,IF(E11>'Parâmetros'!$A$7,0,-6)))) -> 4 | AC11: =IF(Consultas!AC11='Parâmetros'!$E$1,0,5) -> 0 | AD11: =IF(Consultas!AH11='Parâmetros'!$D$1,-10,5) -> 5 | AE11: =IF(Consultas!AI11>(Consultas!F11*2),-10,0) -> 0 | AF11: =IF(Consultas!AD11>1,(IF(Consultas!AI11>(Consultas!AD11),-20,4))) -> 4 | AG11: =IF(Consultas!AG11='Parâmetros'!$E$1,0,-6) -> 0 | AH11: =IF(Consultas!AF11='Parâmetros'!$E$1,1,-5) -> -5 | AI11: =IF(Consultas!AJ11>700,8,IF(Consultas!AJ11>500,4,IF(Consultas!AJ11>200,-4,IF(Consultas!AJ11>1,-15,-20)))) -> 8 | AJ11: =IF(Consultas!AD11='Parâmetros'!$E$10,0,IF(Consultas!AD11>'Parâmetros'!$A$30,12,IF(Consultas!AD11>'Parâmetros'!$A$31,6,IF(Consultas!AD11>'Parâmetros'!$A$32,0,IF(Consultas!AD11>'Parâmetros'!$A$33,0,IF(Consultas!AD11>'Parâmetros'!$A$34,-3,IF(Consultas!AD11>'Parâmetros'!$A$35,-7,-1))))))) -> 12 | AK11: =IF(Consultas!AO11='Parâmetros'!$D$1,3,-3) -> -3 | AL11: =IF(Consultas!AP11='Parâmetros'!$D$1,5,-3) -> -3 | AM11: =IF(Consultas!AL11="N",-6,0) -> 0 | AN11: =IF(Consultas!AM11="N",-10,0) -> 0 | AO11: =IF(Consultas!AN11="S",4,-2) -> -2 | AQ11: =IF(Consultas!F11>1,(SUM(F11:AO11)),"N/A") -> 22 | AR11: =IF((Consultas!AD11>'Parâmetros'!$A$31),"X",AJ11+Y11+V11+AC11) -> X | AS11: =IF((Consultas!AD11>'Parâmetros'!$A$31),"X",(H11+I11+J11+Q11+T11+Y11+Z11+AJ11+AN11)) -> X | AT11: =IF((Consultas!AD11<'Parâmetros'!$A$31),"X",(AD11+AC11+AB11)) -> 9 | AU11: =SMALL(AR11:AT11,1) -> 9 | AV11: =IF(AQ11="N/A","N/A",IF(AQ11>5,'Parâmetros'!$A$15,(IF(AU11=AR11,'Parâmetros'!$A$17,IF(AU11=AS11,'Parâmetros'!$A$16,'Parâmetros'!$A$14))))) -> SEM-RISCO | AW11: =IF(AQ11="N/A","N/A",IF(AV11='Parâmetros'!$A$15,'Parâmetros'!$C$15,(IF(AV11='Parâmetros'!$A$17,'Parâmetros'!$C$17,IF(AV11='Parâmetros'!$A$16,'Parâmetros'!$C$16,IF(AV11='Parâmetros'!$A$14,'Parâmetros'!$C$12)))))) -> LIBERADO | AX11: =IF(Consultas!F11>1,(IF(Consultas!F11>5000,"SOLICITAR PED COMPRA","N/A"))) -> N/A | AY11: =IF(AND(Consultas!M11<>"S", Consultas!H11="S"), "CHECAGEM REVERSA", "N/A") -> CHECAGEM REVERSA | AZ11: =IF(Consultas!U11="N","PRECISA CORRIGIR END DIVERGENTE","N/A") -> N/A
A12: Define Risco | B12: =Consultas!B12 -> 171 | C12: =Consultas!D12 -> Metalpleno | D12: =Consultas!E12 -> 144480 | E12: =IF(Consultas!AB12>0,YEAR('Parâmetros'!$B$1)-YEAR(Consultas!AB12),"NA") -> 18 | F12: =IF(Consultas!F12>'Parâmetros'!$B$2,-8,0) -> 0 | G12: =IF(Consultas!H12='Parâmetros'!$E$1,100,0) -> 0 | H12: =IF(Consultas!I12='Parâmetros'!$E$1,-4,12) -> -4 | I12: =IF(Consultas!J12='Parâmetros'!$E$1,1,-13) -> 1 | J12: =IF(Consultas!K12='Parâmetros'!$E$1,2,-5) -> 2 | K12: =IF(Consultas!L12='Parâmetros'!$D$1,"SOLIC CONTRATO DE ENTREGA","N/A") -> SOLIC CONTRATO DE ENTREGA | L12: =IF(Consultas!R12='Parâmetros'!$E$1,1,-3) -> 1 | M12: =IF(Consultas!S12>1,(IF(Consultas!S12='Parâmetros'!$E$1,-3,9))) -> -3 | N12: =IF(Consultas!T12="S",23,0) -> 0 | O12: =IF(Consultas!U12='Parâmetros'!$E$1,-3,3) -> 3 | P12: =IF(Consultas!V12='Parâmetros'!$E$1,-100,2) -> 2 | Q12: =IF(Consultas!M12='Parâmetros'!$D$1,2,-9) -> -9 | R12: =IF(Consultas!N12="RJ",-12,0) -> 0 | S12: =IF(Consultas!O12="-",-3,IF(Consultas!O12=0,-6,IF(Consultas!O12=5,0,IF(Consultas!O12=10,6)))) -> -6 | T12: =IF(Consultas!M12="S",0,(IF(Consultas!P12="S",6,0))) -> 0 | U12: =IF(Consultas!Q12>97,9,IF(Consultas!Q12>75,0,-7)) -> 9 | V12: =IF(Consultas!W12='Parâmetros'!$E$1,1,-5) -> 1 | W12: =IF(Consultas!X12="S",3,-3) -> 3 | X12: =IF(Consultas!Y12="S",0,-7) -> 0 | Y12: =IF(Consultas!Z12='Parâmetros'!$E$1,2,-8) -> 2 | Z12: =IF(Consultas!AA12='Parâmetros'!$E$1,-15,1) -> 1 | AA12: - | AB12: =IF(E12="NA","NA",IF(E12>'Parâmetros'!$A$9,8,IF(E12>'Parâmetros'!$A$8,4,IF(E12>'Parâmetros'!$A$7,0,-6)))) -> 4 | AC12: =IF(Consultas!AC12='Parâmetros'!$E$1,0,5) -> 0 | AD12: =IF(Consultas!AH12='Parâmetros'!$D$1,-10,5) -> 5 | AE12: =IF(Consultas!AI12>(Consultas!F12*2),-10,0) -> 0 | AF12: =IF(Consultas!AD12>1,(IF(Consultas!AI12>(Consultas!AD12),-20,4))) -> 4 | AG12: =IF(Consultas!AG12='Parâmetros'!$E$1,0,-6) -> 0 | AH12: =IF(Consultas!AF12='Parâmetros'!$E$1,1,-5) -> 1 | AI12: =IF(Consultas!AJ12>700,8,IF(Consultas!AJ12>500,4,IF(Consultas!AJ12>200,-4,IF(Consultas!AJ12>1,-15,-20)))) -> 8 | AJ12: =IF(Consultas!AD12='Parâmetros'!$E$10,0,IF(Consultas!AD12>'Parâmetros'!$A$30,12,IF(Consultas!AD12>'Parâmetros'!$A$31,6,IF(Consultas!AD12>'Parâmetros'!$A$32,0,IF(Consultas!AD12>'Parâmetros'!$A$33,0,IF(Consultas!AD12>'Parâmetros'!$A$34,-3,IF(Consultas!AD12>'Parâmetros'!$A$35,-7,-1))))))) -> 12 | AK12: =IF(Consultas!AO12='Parâmetros'!$D$1,3,-3) -> -3 | AL12: =IF(Consultas!AP12='Parâmetros'!$D$1,5,-3) -> -3 | AM12: =IF(Consultas!AL12="N",-6,0) -> 0 | AN12: =IF(Consultas!AM12="N",-10,0) -> 0 | AO12: =IF(Consultas!AN12="S",4,-2) -> -2 | AQ12: =IF(Consultas!F12>1,(SUM(F12:AO12)),"N/A") -> 29 | AR12: =IF((Consultas!AD12>'Parâmetros'!$A$31),"X",AJ12+Y12+V12+AC12) -> X | AS12: =IF((Consultas!AD12>'Parâmetros'!$A$31),"X",(H12+I12+J12+Q12+T12+Y12+Z12+AJ12+AN12)) -> X | AT12: =IF((Consultas!AD12<'Parâmetros'!$A$31),"X",(AD12+AC12+AB12)) -> 9 | AU12: =SMALL(AR12:AT12,1) -> 9 | AV12: =IF(AQ12="N/A","N/A",IF(AQ12>5,'Parâmetros'!$A$15,(IF(AU12=AR12,'Parâmetros'!$A$17,IF(AU12=AS12,'Parâmetros'!$A$16,'Parâmetros'!$A$14))))) -> SEM-RISCO | AW12: =IF(AQ12="N/A","N/A",IF(AV12='Parâmetros'!$A$15,'Parâmetros'!$C$15,(IF(AV12='Parâmetros'!$A$17,'Parâmetros'!$C$17,IF(AV12='Parâmetros'!$A$16,'Parâmetros'!$C$16,IF(AV12='Parâmetros'!$A$14,'Parâmetros'!$C$12)))))) -> LIBERADO | AX12: =IF(Consultas!F12>1,(IF(Consultas!F12>5000,"SOLICITAR PED COMPRA","N/A"))) -> N/A | AY12: =IF(AND(Consultas!M12<>"S", Consultas!H12="S"), "CHECAGEM REVERSA", "N/A") -> CHECAGEM REVERSA | AZ12: =IF(Consultas!U12="N","PRECISA CORRIGIR END DIVERGENTE","N/A") -> N/A
A13: Define Risco | B13: =Consultas!B13 -> 460 | C13: =Consultas!D13 -> Oaco | D13: =Consultas!E13 -> 144485 | E13: =IF(Consultas!AB13>0,YEAR('Parâmetros'!$B$1)-YEAR(Consultas!AB13),"NA") -> 21 | F13: =IF(Consultas!F13>'Parâmetros'!$B$2,-8,0) -> 0 | G13: =IF(Consultas!H13='Parâmetros'!$E$1,100,0) -> 0 | H13: =IF(Consultas!I13='Parâmetros'!$E$1,-4,12) -> -4 | I13: =IF(Consultas!J13='Parâmetros'!$E$1,1,-13) -> 1 | J13: =IF(Consultas!K13='Parâmetros'!$E$1,2,-5) -> 2 | K13: =IF(Consultas!L13='Parâmetros'!$D$1,"SOLIC CONTRATO DE ENTREGA","N/A") -> SOLIC CONTRATO DE ENTREGA | L13: =IF(Consultas!R13='Parâmetros'!$E$1,1,-3) -> 1 | M13: =IF(Consultas!S13>1,(IF(Consultas!S13='Parâmetros'!$E$1,-3,9))) -> -3 | N13: =IF(Consultas!T13="S",23,0) -> 0 | O13: =IF(Consultas!U13='Parâmetros'!$E$1,-3,3) -> 3 | P13: =IF(Consultas!V13='Parâmetros'!$E$1,-100,2) -> 2 | Q13: =IF(Consultas!M13='Parâmetros'!$D$1,2,-9) -> -9 | R13: =IF(Consultas!N13="RJ",-12,0) -> 0 | S13: =IF(Consultas!O13="-",-3,IF(Consultas!O13=0,-6,IF(Consultas!O13=5,0,IF(Consultas!O13=10,6)))) -> -6 | T13: =IF(Consultas!M13="S",0,(IF(Consultas!P13="S",6,0))) -> 6 | U13: =IF(Consultas!Q13>97,9,IF(Consultas!Q13>75,0,-7)) -> 9 | V13: =IF(Consultas!W13='Parâmetros'!$E$1,1,-5) -> 1 | W13: =IF(Consultas!X13="S",3,-3) -> 3 | X13: =IF(Consultas!Y13="S",0,-7) -> 0 | Y13: =IF(Consultas!Z13='Parâmetros'!$E$1,2,-8) -> 2 | Z13: =IF(Consultas!AA13='Parâmetros'!$E$1,-15,1) -> 1 | AA13: - | AB13: =IF(E13="NA","NA",IF(E13>'Parâmetros'!$A$9,8,IF(E13>'Parâmetros'!$A$8,4,IF(E13>'Parâmetros'!$A$7,0,-6)))) -> 4 | AC13: =IF(Consultas!AC13='Parâmetros'!$E$1,0,5) -> 0 | AD13: =IF(Consultas!AH13='Parâmetros'!$D$1,-10,5) -> 5 | AE13: =IF(Consultas!AI13>(Consultas!F13*2),-10,0) -> 0 | AF13: =IF(Consultas!AD13>1,(IF(Consultas!AI13>(Consultas!AD13),-20,4))) -> 4 | AG13: =IF(Consultas!AG13='Parâmetros'!$E$1,0,-6) -> 0 | AH13: =IF(Consultas!AF13='Parâmetros'!$E$1,1,-5) -> 1 | AI13: =IF(Consultas!AJ13>700,8,IF(Consultas!AJ13>500,4,IF(Consultas!AJ13>200,-4,IF(Consultas!AJ13>1,-15,-20)))) -> 8 | AJ13: =IF(Consultas!AD13='Parâmetros'!$E$10,0,IF(Consultas!AD13>'Parâmetros'!$A$30,12,IF(Consultas!AD13>'Parâmetros'!$A$31,6,IF(Consultas!AD13>'Parâmetros'!$A$32,0,IF(Consultas!AD13>'Parâmetros'!$A$33,0,IF(Consultas!AD13>'Parâmetros'!$A$34,-3,IF(Consultas!AD13>'Parâmetros'!$A$35,-7,-1))))))) -> 12 | AK13: =IF(Consultas!AO13='Parâmetros'!$D$1,3,-3) -> -3 | AL13: =IF(Consultas!AP13='Parâmetros'!$D$1,5,-3) -> -3 | AM13: =IF(Consultas!AL13="N",-6,0) -> 0 | AN13: =IF(Consultas!AM13="N",-10,0) -> 0 | AO13: =IF(Consultas!AN13="S",4,-2) -> -2 | AQ13: =IF(Consultas!F13>1,(SUM(F13:AO13)),"N/A") -> 35 | AR13: =IF((Consultas!AD13>'Parâmetros'!$A$31),"X",AJ13+Y13+V13+AC13) -> X | AS13: =IF((Consultas!AD13>'Parâmetros'!$A$31),"X",(H13+I13+J13+Q13+T13+Y13+Z13+AJ13+AN13)) -> X | AT13: =IF((Consultas!AD13<'Parâmetros'!$A$31),"X",(AD13+AC13+AB13)) -> 9 | AU13: =SMALL(AR13:AT13,1) -> 9 | AV13: =IF(AQ13="N/A","N/A",IF(AQ13>5,'Parâmetros'!$A$15,(IF(AU13=AR13,'Parâmetros'!$A$17,IF(AU13=AS13,'Parâmetros'!$A$16,'Parâmetros'!$A$14))))) -> SEM-RISCO | AW13: =IF(AQ13="N/A","N/A",IF(AV13='Parâmetros'!$A$15,'Parâmetros'!$C$15,(IF(AV13='Parâmetros'!$A$17,'Parâmetros'!$C$17,IF(AV13='Parâmetros'!$A$16,'Parâmetros'!$C$16,IF(AV13='Parâmetros'!$A$14,'Parâmetros'!$C$12)))))) -> LIBERADO | AX13: =IF(Consultas!F13>1,(IF(Consultas!F13>5000,"SOLICITAR PED COMPRA","N/A"))) -> N/A | AY13: =IF(AND(Consultas!M13<>"S", Consultas!H13="S"), "CHECAGEM REVERSA", "N/A") -> CHECAGEM REVERSA | AZ13: =IF(Consultas!U13="N","PRECISA CORRIGIR END DIVERGENTE","N/A") -> N/A
... A451: Define Risco | B451: =Consultas!B451 | C451: =Consultas!D451 | D451: =Consultas!E451 | E451: =IF(Consultas!AB451>0,YEAR('Parâmetros'!$B$1)-YEAR(Consultas!AB451),"NA") -> NA | F451: =IF(Consultas!F451>'Parâmetros'!$B$2,-8,0) -> 0 | G451: =IF(Consultas!H451='Parâmetros'!$E$1,100,0) -> 0 | H451: =IF(Consultas!I451='Parâmetros'!$E$1,-4,12) -> 12 | I451: =IF(Consultas!J451='Parâmetros'!$E$1,1,-13) -> -13 | J451: =IF(Consultas!K451='Parâmetros'!$E$1,2,-5) -> -5 | K451: =IF(Consultas!L451='Parâmetros'!$D$1,"SOLIC CONTRATO DE ENTREGA","N/A") -> N/A | L451: =IF(Consultas!R451='Parâmetros'!$E$1,1,-3) -> -3 | M451: =IF(Consultas!S451>1,(IF(Consultas!S451='Parâmetros'!$E$1,-3,9))) -> FALSE | N451: =IF(Consultas!T451="S",23,0) -> 0 | O451: =IF(Consultas!U451='Parâmetros'!$E$1,-3,3) -> 3 | P451: =IF(Consultas!V451='Parâmetros'!$E$1,-100,2) -> 2 | Q451: =IF(Consultas!M451='Parâmetros'!$D$1,2,-9) -> -9 | R451: =IF(Consultas!N451="RJ",-12,0) -> 0 | S451: =IF(Consultas!O451="-",-3,IF(Consultas!O451=0,-6,IF(Consultas!O451=5,0,IF(Consultas!O451=10,6)))) -> -6 | T451: =IF(Consultas!M451="S",0,(IF(Consultas!P451="S",6,0))) -> 0 | U451: =IF(Consultas!Q451>97,9,IF(Consultas!Q451>75,0,-7)) -> -7 | V451: =IF(Consultas!W451='Parâmetros'!$E$1,1,-5) -> -5 | W451: =IF(Consultas!X451="S",3,-3) -> -3 | X451: =IF(Consultas!Y451="S",0,-7) -> -7 | Y451: =IF(Consultas!Z451='Parâmetros'!$E$1,2,-8) -> -8 | Z451: =IF(Consultas!AA451='Parâmetros'!$E$1,-15,1) -> 1 | AA451: - | AB451: =IF(E451="NA","NA",IF(E451>'Parâmetros'!$A$9,8,IF(E451>'Parâmetros'!$A$8,4,IF(E451>'Parâmetros'!$A$7,0,-6)))) -> NA | AC451: =IF(Consultas!AC451='Parâmetros'!$E$1,0,5) -> 5 | AD451: =IF(Consultas!AH451='Parâmetros'!$D$1,-10,5) -> 5 | AE451: =IF(Consultas!AI451>(Consultas!F451*2),-10,0) -> 0 | AF451: =IF(Consultas!AD451>1,(IF(Consultas!AI451>(Consultas!AD451),-20,4))) -> FALSE | AG451: =IF(Consultas!AG451='Parâmetros'!$E$1,0,-6) -> -6 | AH451: =IF(Consultas!AF451='Parâmetros'!$E$1,1,-5) -> -5 | AI451: =IF(Consultas!AJ451>700,8,IF(Consultas!AJ451>500,4,IF(Consultas!AJ451>200,-4,IF(Consultas!AJ451>1,-15,-20)))) -> -20 | AJ451: =IF(Consultas!AD451='Parâmetros'!$E$10,0,IF(Consultas!AD451>'Parâmetros'!$A$30,12,IF(Consultas!AD451>'Parâmetros'!$A$31,6,IF(Consultas!AD451>'Parâmetros'!$A$32,0,IF(Consultas!AD451>'Parâmetros'!$A$33,0,IF(Consultas!AD451>'Parâmetros'!$A$34,-3,IF(Consultas!AD451>'Parâmetros'!$A$35,-7,-1))))))) -> -1 | AK451: =IF(Consultas!AO451='Parâmetros'!$D$1,3,-3) -> -3 | AL451: =IF(Consultas!AP451='Parâmetros'!$D$1,5,-3) -> -3 | AM451: =IF(Consultas!AL451="N",-6,0) -> 0 | AN451: =IF(Consultas!AM451="N",-10,0) -> 0 | AO451: =IF(Consultas!AN451="S",4,-2) -> -2 | AQ451: =IF(Consultas!F451>1,(SUM(F451:AO451)),"N/A") -> N/A | AR451: =IF((Consultas!AD451>'Parâmetros'!$A$31),"X",AJ451+Y451+V451+AC451) -> -9 | AS451: =IF((Consultas!AD451>'Parâmetros'!$A$31),"X",(H451+I451+J451+Q451+T451+Y451+Z451+AJ451+AN451)) -> -23 | AT451: =IF((Consultas!AD451<'Parâmetros'!$A$31),"X",(AD451+AC451+AB451)) -> X | AU451: =SMALL(AR451:AT451,1) -> -23 | AV451: =IF(AQ451="N/A","N/A",IF(AQ451>5,'Parâmetros'!$A$15,(IF(AU451=AR451,'Parâmetros'!$A$17,IF(AU451=AS451,'Parâmetros'!$A$16,'Parâmetros'!$A$14))))) -> N/A | AW451: =IF(AQ451="N/A","N/A",IF(AV451='Parâmetros'!$A$15,'Parâmetros'!$C$15,(IF(AV451='Parâmetros'!$A$17,'Parâmetros'!$C$17,IF(AV451='Parâmetros'!$A$16,'Parâmetros'!$C$16,IF(AV451='Parâmetros'!$A$14,'Parâmetros'!$C$12)))))) -> N/A | AX451: =IF(Consultas!F451>1,(IF(Consultas!F451>5000,"SOLICITAR PED COMPRA","N/A"))) -> FALSE | AY451: =IF(AND(Consultas!M451<>"S", Consultas!H451="S"), "CHECAGEM REVERSA", "N/A") -> N/A | AZ451: =IF(Consultas!U451="N","PRECISA CORRIGIR END DIVERGENTE","N/A") -> N/A

Sheet Parâmetros
A1: 15 | B1: =NOW() -> 46258.546 | C1: 0 | D1: S | E1: N
A2: 4 | B2: 21000
A3: 5 | B3: 201000
A4: 25
A5: Idade | B5: pontos
A6: 2 | B6: -6
A7: 5 | B7: 0
A8: 15 | B8: 4
A9: 30 | B9: 8
E10: N/D
A12: GRANDE-FALINDO: | C12: SE FALINDO SÓ ANTECIPADO | SE GRANDE BUROCR PEGAR CONTATOS FINANCEIRO
A13: REFRENCIA-NF: | C13: VER E-MAIL CORPORATIVO SITE REFERENC COML OU NFE IGUAL AO ALTO VALOR FATURADO
A14: GRANDE-OU-FALINDO: | C14: SE FALINDO SÓ ANTECIPADO | SE GRANDE BUROCR PEGAR CONTATOS FINANCEIRO
A15: SEM-RISCO | C15: LIBERADO
A16: GOLPE | C16: ENTRADA OU A VISTA
A17: EMPRESINHA | C17: VER E-MAIL CORPORATIVO SITE REFERENC COML NFE 3S ALTO VALOR FATURADO
A19: Rel. Básico PJ
A29: Capital Social:
A30: 10000000 | B30: 12
A31: 999000 | B31: 6
A32: 150000 | B32: 0
A33: 90000 | B33: 0
A34: 12000 | B34: -3
A35: 0
